Workbook

Sheet Resumen
A1: Tablero de mermas · Agosto 2026
A2: Periodo: Agosto 2026 · Generado: 22/09/2026 17:01 · Límite SAT: merma ≤ 0.5% de la venta
A4: Merma total grupo (L) | D4: Merma total grupo % | G4: Merma total grupo ($)
A5: ='Mermas mensual'!I23 -> 26324.11 | D5: ='Mermas mensual'!J23 -> 0.0048954769 | G5: ='Mermas mensual'!M23 -> 509745.69
A7: Combinaciones FUERA | D7: Pipas NO registradas | G7: Compras sin pipa
A8: =COUNTIF('Mermas mensual'!K5:K22,"FUERA") -> 12 | D8: =COUNTIF('Detalle pipas'!L5:L281,"NO REGISTRADA*") -> 1 | G8: =COUNTA('Compras sin pipa'!D5:D5)+COUNTIF('Registros manuales'!$G$5:$G$104,"SIN PIPA*") -> 0
A10: Merma % mensual por estación y producto
A11: Estación | B11: Regular | C11: Premium | D11: Diesel | E11: Total estación | F11: Merma (L) | G11: Merma ($) | H11: Compras vs pipas | I11: Pipas sin registrar
A12: ATB | B12: =IF(COUNTIFS('Mermas mensual'!$A$5:$A$22,$A12,'Mermas mensual'!$B$5:$B$22,"Regular")=0,"s/d",IF(SUMIFS('Mermas mensual'!$E$5:$E$22,'Mermas mensual'!$A$5:$A$22,$A12,'Mermas mensual'!$B$5:$B$22,"Regular")=0,0,SUMIFS('Mermas mensual'!$I$5:$I$22,'Mermas mensual'!$A$5:$A$22,$A12,'Mermas mensual'!$B$5:$B$22,"Regular")/SUMIFS('Mermas mensual'!$E$5:$E$22,'Mermas mensual'!$A$5:$A$22,$A12,'Mermas mensual'!$B$5:$B$22,"Regular"))) -> s/d | C12: =IF(COUNTIFS('Mermas mensual'!$A$5:$A$22,$A12,'Mermas mensual'!$B$5:$B$22,"Premium")=0,"s/d",IF(SUMIFS('Mermas mensual'!$E$5:$E$22,'Mermas mensual'!$A$5:$A$22,$A12,'Mermas mensual'!$B$5:$B$22,"Premium")=0,0,SUMIFS('Mermas mensual'!$I$5:$I$22,'Mermas mensual'!$A$5:$A$22,$A12,'Mermas mensual'!$B$5:$B$22,"Premium")/SUMIFS('Mermas mensual'!$E$5:$E$22,'Mermas mensual'!$A$5:$A$22,$A12,'Mermas mensual'!$B$5:$B$22,"Premium"))) -> s/d | D12: =IF(COUNTIFS('Mermas mensual'!$A$5:$A$22,$A12,'Mermas mensual'!$B$5:$B$22,"Diesel")=0,"s/d",IF(SUMIFS('Mermas mensual'!$E$5:$E$22,'Mermas mensual'!$A$5:$A$22,$A12,'Mermas mensual'!$B$5:$B$22,"Diesel")=0,0,SUMIFS('Mermas mensual'!$I$5:$I$22,'Mermas mensual'!$A$5:$A$22,$A12,'Mermas mensual'!$B$5:$B$22,"Diesel")/SUMIFS('Mermas mensual'!$E$5:$E$22,'Mermas mensual'!$A$5:$A$22,$A12,'Mermas mensual'!$B$5:$B$22,"Diesel"))) -> s/d | E12: =IF(COUNTIF('Mermas mensual'!$A$5:$A$22,$A12)=0,"s/d",IF(SUMIFS('Mermas mensual'!$E$5:$E$22,'Mermas mensual'!$A$5:$A$22,$A12)=0,0,SUMIFS('Mermas mensual'!$I$5:$I$22,'Mermas mensual'!$A$5:$A$22,$A12)/SUMIFS('Mermas mensual'!$E$5:$E$22,'Mermas mensual'!$A$5:$A$22,$A12))) -> s/d | F12: =IF(COUNTIF('Mermas mensual'!$A$5:$A$22,$A12)=0,"s/d",SUMIFS('Mermas mensual'!$I$5:$I$22,'Mermas mensual'!$A$5:$A$22,$A12)) -> s/d | G12: =IF(COUNTIF('Mermas mensual'!$A$5:$A$22,$A12)=0,"s/d",SUMIFS('Mermas mensual'!$M$5:$M$22,'Mermas mensual'!$A$5:$A$22,$A12)) -> s/d | H12: =IF(COUNTIFS('Conciliación pipas'!$A$5:$A$40,$A12,'Conciliación pipas'!$G$5:$G$40,"NO CUADRA")>0,"NO CUADRA",IF(COUNTIFS('Conciliación pipas'!$A$5:$A$40,$A12,'Conciliación pipas'!$G$5:$G$40,"CUADRA")>0,IF(COUNTIFS('Conciliación pipas'!$A$5:$A$40,$A12,'Conciliación pipas'!$G$5:$G$40,"SIN REPORTE")>0,"PARCIAL","CUADRA"),IF(COUNTIF('Conciliación pipas'!$A$5:$A$40,$A12)=0,"s/d","SIN REPORTE"))) -> SIN REPORTE | I12: =SUMIFS('Conciliación pipas'!$H$5:$H$40,'Conciliación pipas'!$A$5:$A$40,$A12) -> 0
A13: ATP | B13: =IF(COUNTIFS('Mermas mensual'!$A$5:$A$22,$A13,'Mermas mensual'!$B$5:$B$22,"Regular")=0,"s/d",IF(SUMIFS('Mermas mensual'!$E$5:$E$22,'Mermas mensual'!$A$5:$A$22,$A13,'Mermas mensual'!$B$5:$B$22,"Regular")=0,0,SUMIFS('Mermas mensual'!$I$5:$I$22,'Mermas mensual'!$A$5:$A$22,$A13,'Mermas mensual'!$B$5:$B$22,"Regular")/SUMIFS('Mermas mensual'!$E$5:$E$22,'Mermas mensual'!$A$5:$A$22,$A13,'Mermas mensual'!$B$5:$B$22,"Regular"))) -> s/d | C13: =IF(COUNTIFS('Mermas mensual'!$A$5:$A$22,$A13,'Mermas mensual'!$B$5:$B$22,"Premium")=0,"s/d",IF(SUMIFS('Mermas mensual'!$E$5:$E$22,'Mermas mensual'!$A$5:$A$22,$A13,'Mermas mensual'!$B$5:$B$22,"Premium")=0,0,SUMIFS('Mermas mensual'!$I$5:$I$22,'Mermas mensual'!$A$5:$A$22,$A13,'Mermas mensual'!$B$5:$B$22,"Premium")/SUMIFS('Mermas mensual'!$E$5:$E$22,'Mermas mensual'!$A$5:$A$22,$A13,'Mermas mensual'!$B$5:$B$22,"Premium"))) -> s/d | D13: =IF(COUNTIFS('Mermas mensual'!$A$5:$A$22,$A13,'Mermas mensual'!$B$5:$B$22,"Diesel")=0,"s/d",IF(SUMIFS('Mermas mensual'!$E$5:$E$22,'Mermas mensual'!$A$5:$A$22,$A13,'Mermas mensual'!$B$5:$B$22,"Diesel")=0,0,SUMIFS('Mermas mensual'!$I$5:$I$22,'Mermas mensual'!$A$5:$A$22,$A13,'Mermas mensual'!$B$5:$B$22,"Diesel")/SUMIFS('Mermas mensual'!$E$5:$E$22,'Mermas mensual'!$A$5:$A$22,$A13,'Mermas mensual'!$B$5:$B$22,"Diesel"))) -> s/d | E13: =IF(COUNTIF('Mermas mensual'!$A$5:$A$22,$A13)=0,"s/d",IF(SUMIFS('Mermas mensual'!$E$5:$E$22,'Mermas mensual'!$A$5:$A$22,$A13)=0,0,SUMIFS('Mermas mensual'!$I$5:$I$22,'Mermas mensual'!$A$5:$A$22,$A13)/SUMIFS('Mermas mensual'!$E$5:$E$22,'Mermas mensual'!$A$5:$A$22,$A13))) -> s/d | F13: =IF(COUNTIF('Mermas mensual'!$A$5:$A$22,$A13)=0,"s/d",SUMIFS('Mermas mensual'!$I$5:$I$22,'Mermas mensual'!$A$5:$A$22,$A13)) -> s/d | G13: =IF(COUNTIF('Mermas mensual'!$A$5:$A$22,$A13)=0,"s/d",SUMIFS('Mermas mensual'!$M$5:$M$22,'Mermas mensual'!$A$5:$A$22,$A13)) -> s/d | H13: =IF(COUNTIFS('Conciliación pipas'!$A$5:$A$40,$A13,'Conciliación pipas'!$G$5:$G$40,"NO CUADRA")>0,"NO CUADRA",IF(COUNTIFS('Conciliación pipas'!$A$5:$A$40,$A13,'Conciliación pipas'!$G$5:$G$40,"CUADRA")>0,IF(COUNTIFS('Conciliación pipas'!$A$5:$A$40,$A13,'Conciliación pipas'!$G$5:$G$40,"SIN REPORTE")>0,"PARCIAL","CUADRA"),IF(COUNTIF('Conciliación pipas'!$A$5:$A$40,$A13)=0,"s/d","SIN REPORTE"))) -> SIN REPORTE | I13: =SUMIFS('Conciliación pipas'!$H$5:$H$40,'Conciliación pipas'!$A$5:$A$40,$A13) -> 0
A14: AVE FENIX | B14: =IF(COUNTIFS('Mermas mensual'!$A$5:$A$22,$A14,'Mermas mensual'!$B$5:$B$22,"Regular")=0,"s/d",IF(SUMIFS('Mermas mensual'!$E$5:$E$22,'Mermas mensual'!$A$5:$A$22,$A14,'Mermas mensual'!$B$5:$B$22,"Regular")=0,0,SUMIFS('Mermas mensual'!$I$5:$I$22,'Mermas mensual'!$A$5:$A$22,$A14,'Mermas mensual'!$B$5:$B$22,"Regular")/SUMIFS('Mermas mensual'!$E$5:$E$22,'Mermas mensual'!$A$5:$A$22,$A14,'Mermas mensual'!$B$5:$B$22,"Regular"))) -> s/d | C14: =IF(COUNTIFS('Mermas mensual'!$A$5:$A$22,$A14,'Mermas mensual'!$B$5:$B$22,"Premium")=0,"s/d",IF(SUMIFS('Mermas mensual'!$E$5:$E$22,'Mermas mensual'!$A$5:$A$22,$A14,'Mermas mensual'!$B$5:$B$22,"Premium")=0,0,SUMIFS('Mermas mensual'!$I$5:$I$22,'Mermas mensual'!$A$5:$A$22,$A14,'Mermas mensual'!$B$5:$B$22,"Premium")/SUMIFS('Mermas mensual'!$E$5:$E$22,'Mermas mensual'!$A$5:$A$22,$A14,'Mermas mensual'!$B$5:$B$22,"Premium"))) -> s/d | D14: =IF(COUNTIFS('Mermas mensual'!$A$5:$A$22,$A14,'Mermas mensual'!$B$5:$B$22,"Diesel")=0,"s/d",IF(SUMIFS('Mermas mensual'!$E$5:$E$22,'Mermas mensual'!$A$5:$A$22,$A14,'Mermas mensual'!$B$5:$B$22,"Diesel")=0,0,SUMIFS('Mermas mensual'!$I$5:$I$22,'Mermas mensual'!$A$5:$A$22,$A14,'Mermas mensual'!$B$5:$B$22,"Diesel")/SUMIFS('Mermas mensual'!$E$5:$E$22,'Mermas mensual'!$A$5:$A$22,$A14,'Mermas mensual'!$B$5:$B$22,"Diesel"))) -> s/d | E14: =IF(COUNTIF('Mermas mensual'!$A$5:$A$22,$A14)=0,"s/d",IF(SUMIFS('Mermas mensual'!$E$5:$E$22,'Mermas mensual'!$A$5:$A$22,$A14)=0,0,SUMIFS('Mermas mensual'!$I$5:$I$22,'Mermas mensual'!$A$5:$A$22,$A14)/SUMIFS('Mermas mensual'!$E$5:$E$22,'Mermas mensual'!$A$5:$A$22,$A14))) -> s/d | F14: =IF(COUNTIF('Mermas mensual'!$A$5:$A$22,$A14)=0,"s/d",SUMIFS('Mermas mensual'!$I$5:$I$22,'Mermas mensual'!$A$5:$A$22,$A14)) -> s/d | G14: =IF(COUNTIF('Mermas mensual'!$A$5:$A$22,$A14)=0,"s/d",SUMIFS('Mermas mensual'!$M$5:$M$22,'Mermas mensual'!$A$5:$A$22,$A14)) -> s/d | H14: =IF(COUNTIFS('Conciliación pipas'!$A$5:$A$40,$A14,'Conciliación pipas'!$G$5:$G$40,"NO CUADRA")>0,"NO CUADRA",IF(COUNTIFS('Conciliación pipas'!$A$5:$A$40,$A14,'Conciliación pipas'!$G$5:$G$40,"CUADRA")>0,IF(COUNTIFS('Conciliación pipas'!$A$5:$A$40,$A14,'Conciliación pipas'!$G$5:$G$40,"SIN REPORTE")>0,"PARCIAL","CUADRA"),IF(COUNTIF('Conciliación pipas'!$A$5:$A$40,$A14)=0,"s/d","SIN REPORTE"))) -> SIN REPORTE | I14: =SUMIFS('Conciliación pipas'!$H$5:$H$40,'Conciliación pipas'!$A$5:$A$40,$A14) -> 0
A15: AURORA | B15: =IF(COUNTIFS('Mermas mensual'!$A$5:$A$22,$A15,'Mermas mensual'!$B$5:$B$22,"Regular")=0,"s/d",IF(SUMIFS('Mermas mensual'!$E$5:$E$22,'Mermas mensual'!$A$5:$A$22,$A15,'Mermas mensual'!$B$5:$B$22,"Regular")=0,0,SUMIFS('Mermas mensual'!$I$5:$I$22,'Mermas mensual'!$A$5:$A$22,$A15,'Mermas mensual'!$B$5:$B$22,"Regular")/SUMIFS('Mermas mensual'!$E$5:$E$22,'Mermas mensual'!$A$5:$A$22,$A15,'Mermas mensual'!$B$5:$B$22,"Regular"))) -> 0.044792954 | C15: =IF(COUNTIFS('Mermas mensual'!$A$5:$A$22,$A15,'Mermas mensual'!$B$5:$B$22,"Premium")=0,"s/d",IF(SUMIFS('Mermas mensual'!$E$5:$E$22,'Mermas mensual'!$A$5:$A$22,$A15,'Mermas mensual'!$B$5:$B$22,"Premium")=0,0,SUMIFS('Mermas mensual'!$I$5:$I$22,'Mermas mensual'!$A$5:$A$22,$A15,'Mermas mensual'!$B$5:$B$22,"Premium")/SUMIFS('Mermas mensual'!$E$5:$E$22,'Mermas mensual'!$A$5:$A$22,$A15,'Mermas mensual'!$B$5:$B$22,"Premium"))) -> -0.0065614899 | D15: =IF(COUNTIFS('Mermas mensual'!$A$5:$A$22,$A15,'Mermas mensual'!$B$5:$B$22,"Diesel")=0,"s/d",IF(SUMIFS('Mermas mensual'!$E$5:$E$22,'Mermas mensual'!$A$5:$A$22,$A15,'Mermas mensual'!$B$5:$B$22,"Diesel")=0,0,SUMIFS('Mermas mensual'!$I$5:$I$22,'Mermas mensual'!$A$5:$A$22,$A15,'Mermas mensual'!$B$5:$B$22,"Diesel")/SUMIFS('Mermas mensual'!$E$5:$E$22,'Mermas mensual'!$A$5:$A$22,$A15,'Mermas mensual'!$B$5:$B$22,"Diesel"))) -> 0.0017236447 | E15: =IF(COUNTIF('Mermas mensual'!$A$5:$A$22,$A15)=0,"s/d",IF(SUMIFS('Mermas mensual'!$E$5:$E$22,'Mermas mensual'!$A$5:$A$22,$A15)=0,0,SUMIFS('Mermas mensual'!$I$5:$I$22,'Mermas mensual'!$A$5:$A$22,$A15)/SUMIFS('Mermas mensual'!$E$5:$E$22,'Mermas mensual'!$A$5:$A$22,$A15))) -> 0.029270285 | F15: =IF(COUNTIF('Mermas mensual'!$A$5:$A$22,$A15)=0,"s/d",SUMIFS('Mermas mensual'!$I$5:$I$22,'Mermas mensual'!$A$5:$A$22,$A15)) -> 29187.44 | G15: =IF(COUNTIF('Mermas mensual'!$A$5:$A$22,$A15)=0,"s/d",SUMIFS('Mermas mensual'!$M$5:$M$22,'Mermas mensual'!$A$5:$A$22,$A15)) -> 553962.05 | H15: =IF(COUNTIFS('Conciliación pipas'!$A$5:$A$40,$A15,'Conciliación pipas'!$G$5:$G$40,"NO CUADRA")>0,"NO CUADRA",IF(COUNTIFS('Conciliación pipas'!$A$5:$A$40,$A15,'Conciliación pipas'!$G$5:$G$40,"CUADRA")>0,IF(COUNTIFS('Conciliación pipas'!$A$5:$A$40,$A15,'Conciliación pipas'!$G$5:$G$40,"SIN REPORTE")>0,"PARCIAL","CUADRA"),IF(COUNTIF('Conciliación pipas'!$A$5:$A$40,$A15)=0,"s/d","SIN REPORTE"))) -> NO CUADRA | I15: =SUMIFS('Conciliación pipas'!$H$5:$H$40,'Conciliación pipas'!$A$5:$A$40,$A15) -> 1
A16: COMBULUB | B16: =IF(COUNTIFS('Mermas mensual'!$A$5:$A$22,$A16,'Mermas mensual'!$B$5:$B$22,"Regular")=0,"s/d",IF(SUMIFS('Mermas mensual'!$E$5:$E$22,'Mermas mensual'!$A$5:$A$22,$A16,'Mermas mensual'!$B$5:$B$22,"Regular")=0,0,SUMIFS('Mermas mensual'!$I$5:$I$22,'Mermas mensual'!$A$5:$A$22,$A16,'Mermas mensual'!$B$5:$B$22,"Regular")/SUMIFS('Mermas mensual'!$E$5:$E$22,'Mermas mensual'!$A$5:$A$22,$A16,'Mermas mensual'!$B$5:$B$22,"Regular"))) -> s/d | C16: =IF(COUNTIFS('Mermas mensual'!$A$5:$A$22,$A16,'Mermas mensual'!$B$5:$B$22,"Premium")=0,"s/d",IF(SUMIFS('Mermas mensual'!$E$5:$E$22,'Mermas mensual'!$A$5:$A$22,$A16,'Mermas mensual'!$B$5:$B$22,"Premium")=0,0,SUMIFS('Mermas mensual'!$I$5:$I$22,'Mermas mensual'!$A$5:$A$22,$A16,'Mermas mensual'!$B$5:$B$22,"Premium")/SUMIFS('Mermas mensual'!$E$5:$E$22,'Mermas mensual'!$A$5:$A$22,$A16,'Mermas mensual'!$B$5:$B$22,"Premium"))) -> s/d | D16: =IF(COUNTIFS('Mermas mensual'!$A$5:$A$22,$A16,'Mermas mensual'!$B$5:$B$22,"Diesel")=0,"s/d",IF(SUMIFS('Mermas mensual'!$E$5:$E$22,'Mermas mensual'!$A$5:$A$22,$A16,'Mermas mensual'!$B$5:$B$22,"Diesel")=0,0,SUMIFS('Mermas mensual'!$I$5:$I$22,'Mermas mensual'!$A$5:$A$22,$A16,'Mermas mensual'!$B$5:$B$22,"Diesel")/SUMIFS('Mermas mensual'!$E$5:$E$22,'Mermas mensual'!$A$5:$A$22,$A16,'Mermas mensual'!$B$5:$B$22,"Diesel"))) -> s/d | E16: =IF(COUNTIF('Mermas mensual'!$A$5:$A$22,$A16)=0,"s/d",IF(SUMIFS('Mermas mensual'!$E$5:$E$22,'Mermas mensual'!$A$5:$A$22,$A16)=0,0,SUMIFS('Mermas mensual'!$I$5:$I$22,'Mermas mensual'!$A$5:$A$22,$A16)/SUMIFS('Mermas mensual'!$E$5:$E$22,'Mermas mensual'!$A$5:$A$22,$A16))) -> s/d | F16: =IF(COUNTIF('Mermas mensual'!$A$5:$A$22,$A16)=0,"s/d",SUMIFS('Mermas mensual'!$I$5:$I$22,'Mermas mensual'!$A$5:$A$22,$A16)) -> s/d | G16: =IF(COUNTIF('Mermas mensual'!$A$5:$A$22,$A16)=0,"s/d",SUMIFS('Mermas mensual'!$M$5:$M$22,'Mermas mensual'!$A$5:$A$22,$A16)) -> s/d | H16: =IF(COUNTIFS('Conciliación pipas'!$A$5:$A$40,$A16,'Conciliación pipas'!$G$5:$G$40,"NO CUADRA")>0,"NO CUADRA",IF(COUNTIFS('Conciliación pipas'!$A$5:$A$40,$A16,'Conciliación pipas'!$G$5:$G$40,"CUADRA")>0,IF(COUNTIFS('Conciliación pipas'!$A$5:$A$40,$A16,'Conciliación pipas'!$G$5:$G$40,"SIN REPORTE")>0,"PARCIAL","CUADRA"),IF(COUNTIF('Conciliación pipas'!$A$5:$A$40,$A16)=0,"s/d","SIN REPORTE"))) -> SIN REPORTE | I16: =SUMIFS('Conciliación pipas'!$H$5:$H$40,'Conciliación pipas'!$A$5:$A$40,$A16) -> 0
A17: HUEHUETOCA | B17: =IF(COUNTIFS('Mermas mensual'!$A$5:$A$22,$A17,'Mermas mensual'!$B$5:$B$22,"Regular")=0,"s/d",IF(SUMIFS('Mermas mensual'!$E$5:$E$22,'Mermas mensual'!$A$5:$A$22,$A17,'Mermas mensual'!$B$5:$B$22,"Regular")=0,0,SUMIFS('Mermas mensual'!$I$5:$I$22,'Mermas mensual'!$A$5:$A$22,$A17,'Mermas mensual'!$B$5:$B$22,"Regular")/SUMIFS('Mermas mensual'!$E$5:$E$22,'Mermas mensual'!$A$5:$A$22,$A17,'Mermas mensual'!$B$5:$B$22,"Regular"))) -> -0.0054329434 | C17: =IF(COUNTIFS('Mermas mensual'!$A$5:$A$22,$A17,'Mermas mensual'!$B$5:$B$22,"Premium")=0,"s/d",IF(SUMIFS('Mermas mensual'!$E$5:$E$22,'Mermas mensual'!$A$5:$A$22,$A17,'Mermas mensual'!$B$5:$B$22,"Premium")=0,0,SUMIFS('Mermas mensual'!$I$5:$I$22,'Mermas mensual'!$A$5:$A$22,$A17,'Mermas mensual'!$B$5:$B$22,"Premium")/SUMIFS('Mermas mensual'!$E$5:$E$22,'Mermas mensual'!$A$5:$A$22,$A17,'Mermas mensual'!$B$5:$B$22,"Premium"))) -> -0.0029814637 | D17: =IF(COUNTIFS('Mermas mensual'!$A$5:$A$22,$A17,'Mermas mensual'!$B$5:$B$22,"Diesel")=0,"s/d",IF(SUMIFS('Mermas mensual'!$E$5:$E$22,'Mermas mensual'!$A$5:$A$22,$A17,'Mermas mensual'!$B$5:$B$22,"Diesel")=0,0,SUMIFS('Mermas mensual'!$I$5:$I$22,'Mermas mensual'!$A$5:$A$22,$A17,'Mermas mensual'!$B$5:$B$22,"Diesel")/SUMIFS('Mermas mensual'!$E$5:$E$22,'Mermas mensual'!$A$5:$A$22,$A17,'Mermas mensual'!$B$5:$B$22,"Diesel"))) -> -0.0042455339 | E17: =IF(COUNTIF('Mermas mensual'!$A$5:$A$22,$A17)=0,"s/d",IF(SUMIFS('Mermas mensual'!$E$5:$E$22,'Mermas mensual'!$A$5:$A$22,$A17)=0,0,SUMIFS('Mermas mensual'!$I$5:$I$22,'Mermas mensual'!$A$5:$A$22,$A17)/SUMIFS('Mermas mensual'!$E$5:$E$22,'Mermas mensual'!$A$5:$A$22,$A17))) -> -0.0048737038 | F17: =IF(COUNTIF('Mermas mensual'!$A$5:$A$22,$A17)=0,"s/d",SUMIFS('Mermas mensual'!$I$5:$I$22,'Mermas mensual'!$A$5:$A$22,$A17)) -> -3857.85 | G17: =IF(COUNTIF('Mermas mensual'!$A$5:$A$22,$A17)=0,"s/d",SUMIFS('Mermas mensual'!$M$5:$M$22,'Mermas mensual'!$A$5:$A$22,$A17)) -> -76454.13 | H17: =IF(COUNTIFS('Conciliación pipas'!$A$5:$A$40,$A17,'Conciliación pipas'!$G$5:$G$40,"NO CUADRA")>0,"NO CUADRA",IF(COUNTIFS('Conciliación pipas'!$A$5:$A$40,$A17,'Conciliación pipas'!$G$5:$G$40,"CUADRA")>0,IF(COUNTIFS('Conciliación pipas'!$A$5:$A$40,$A17,'Conciliación pipas'!$G$5:$G$40,"SIN REPORTE")>0,"PARCIAL","CUADRA"),IF(COUNTIF('Conciliación pipas'!$A$5:$A$40,$A17)=0,"s/d","SIN REPORTE"))) -> CUADRA | I17: =SUMIFS('Conciliación pipas'!$H$5:$H$40,'Conciliación pipas'!$A$5:$A$40,$A17) -> 0
A18: QL | B18: =IF(COUNTIFS('Mermas mensual'!$A$5:$A$22,$A18,'Mermas mensual'!$B$5:$B$22,"Regular")=0,"s/d",IF(SUMIFS('Mermas mensual'!$E$5:$E$22,'Mermas mensual'!$A$5:$A$22,$A18,'Mermas mensual'!$B$5:$B$22,"Regular")=0,0,SUMIFS('Mermas mensual'!$I$5:$I$22,'Mermas mensual'!$A$5:$A$22,$A18,'Mermas mensual'!$B$5:$B$22,"Regular")/SUMIFS('Mermas mensual'!$E$5:$E$22,'Mermas mensual'!$A$5:$A$22,$A18,'Mermas mensual'!$B$5:$B$22,"Regular"))) -> -0.0047053512 | C18: =IF(COUNTIFS('Mermas mensual'!$A$5:$A$22,$A18,'Mermas mensual'!$B$5:$B$22,"Premium")=0,"s/d",IF(SUMIFS('Mermas mensual'!$E$5:$E$22,'Mermas mensual'!$A$5:$A$22,$A18,'Mermas mensual'!$B$5:$B$22,"Premium")=0,0,SUMIFS('Mermas mensual'!$I$5:$I$22,'Mermas mensual'!$A$5:$A$22,$A18,'Mermas mensual'!$B$5:$B$22,"Premium")/SUMIFS('Mermas mensual'!$E$5:$E$22,'Mermas mensual'!$A$5:$A$22,$A18,'Mermas mensual'!$B$5:$B$22,"Premium"))) -> -0.0064908831 | D18: =IF(COUNTIFS('Mermas mensual'!$A$5:$A$22,$A18,'Mermas mensual'!$B$5:$B$22,"Diesel")=0,"s/d",IF(SUMIFS('Mermas mensual'!$E$5:$E$22,'Mermas mensual'!$A$5:$A$22,$A18,'Mermas mensual'!$B$5:$B$22,"Diesel")=0,0,SUMIFS('Mermas mensual'!$I$5:$I$22,'Mermas mensual'!$A$5:$A$22,$A18,'Mermas mensual'!$B$5:$B$22,"Diesel")/SUMIFS('Mermas mensual'!$E$5:$E$22,'Mermas mensual'!$A$5:$A$22,$A18,'Mermas mensual'!$B$5:$B$22,"Diesel"))) -> 0.0063870109 | E18: =IF(COUNTIF('Mermas mensual'!$A$5:$A$22,$A18)=0,"s/d",IF(SUMIFS('Mermas mensual'!$E$5:$E$22,'Mermas mensual'!$A$5:$A$22,$A18)=0,0,SUMIFS('Mermas mensual'!$I$5:$I$22,'Mermas mensual'!$A$5:$A$22,$A18)/SUMIFS('Mermas mensual'!$E$5:$E$22,'Mermas mensual'!$A$5:$A$22,$A18))) -> 0.00052847199 | F18: =IF(COUNTIF('Mermas mensual'!$A$5:$A$22,$A18)=0,"s/d",SUMIFS('Mermas mensual'!$I$5:$I$22,'Mermas mensual'!$A$5:$A$22,$A18)) -> 978.88 | G18: =IF(COUNTIF('Mermas mensual'!$A$5:$A$22,$A18)=0,"s/d",SUMIFS('Mermas mensual'!$M$5:$M$22,'Mermas mensual'!$A$5:$A$22,$A18)) -> 28014.586 | H18: =IF(COUNTIFS('Conciliación pipas'!$A$5:$A$40,$A18,'Conciliación pipas'!$G$5:$G$40,"NO CUADRA")>0,"NO CUADRA",IF(COUNTIFS('Conciliación pipas'!$A$5:$A$40,$A18,'Conciliación pipas'!$G$5:$G$40,"CUADRA")>0,IF(COUNTIFS('Conciliación pipas'!$A$5:$A$40,$A18,'Conciliación pipas'!$G$5:$G$40,"SIN REPORTE")>0,"PARCIAL","CUADRA"),IF(COUNTIF('Conciliación pipas'!$A$5:$A$40,$A18)=0,"s/d","SIN REPORTE"))) -> CUADRA | I18: =SUMIFS('Conciliación pipas'!$H$5:$H$40,'Conciliación pipas'!$A$5:$A$40,$A18) -> 0
A19: IXTAZACUALA | B19: =IF(COUNTIFS('Mermas mensual'!$A$5:$A$22,$A19,'Mermas mensual'!$B$5:$B$22,"Regular")=0,"s/d",IF(SUMIFS('Mermas mensual'!$E$5:$E$22,'Mermas mensual'!$A$5:$A$22,$A19,'Mermas mensual'!$B$5:$B$22,"Regular")=0,0,SUMIFS('Mermas mensual'!$I$5:$I$22,'Mermas mensual'!$A$5:$A$22,$A19,'Mermas mensual'!$B$5:$B$22,"Regular")/SUMIFS('Mermas mensual'!$E$5:$E$22,'Mermas mensual'!$A$5:$A$22,$A19,'Mermas mensual'!$B$5:$B$22,"Regular"))) -> -0.0055998104 | C19: =IF(COUNTIFS('Mermas mensual'!$A$5:$A$22,$A19,'Mermas mensual'!$B$5:$B$22,"Premium")=0,"s/d",IF(SUMIFS('Mermas mensual'!$E$5:$E$22,'Mermas mensual'!$A$5:$A$22,$A19,'Mermas mensual'!$B$5:$B$22,"Premium")=0,0,SUMIFS('Mermas mensual'!$I$5:$I$22,'Mermas mensual'!$A$5:$A$22,$A19,'Mermas mensual'!$B$5:$B$22,"Premium")/SUMIFS('Mermas mensual'!$E$5:$E$22,'Mermas mensual'!$A$5:$A$22,$A19,'Mermas mensual'!$B$5:$B$22,"Premium"))) -> -0.0094117742 | D19: =IF(COUNTIFS('Mermas mensual'!$A$5:$A$22,$A19,'Mermas mensual'!$B$5:$B$22,"Diesel")=0,"s/d",IF(SUMIFS('Mermas mensual'!$E$5:$E$22,'Mermas mensual'!$A$5:$A$22,$A19,'Mermas mensual'!$B$5:$B$22,"Diesel")=0,0,SUMIFS('Mermas mensual'!$I$5:$I$22,'Mermas mensual'!$A$5:$A$22,$A19,'Mermas mensual'!$B$5:$B$22,"Diesel")/SUMIFS('Mermas mensual'!$E$5:$E$22,'Mermas mensual'!$A$5:$A$22,$A19,'Mermas mensual'!$B$5:$B$22,"Diesel"))) -> 0.00018556007 | E19: =IF(COUNTIF('Mermas mensual'!$A$5:$A$22,$A19)=0,"s/d",IF(SUMIFS('Mermas mensual'!$E$5:$E$22,'Mermas mensual'!$A$5:$A$22,$A19)=0,0,SUMIFS('Mermas mensual'!$I$5:$I$22,'Mermas mensual'!$A$5:$A$22,$A19)/SUMIFS('Mermas mensual'!$E$5:$E$22,'Mermas mensual'!$A$5:$A$22,$A19))) -> -0.0033777986 | F19: =IF(COUNTIF('Mermas mensual'!$A$5:$A$22,$A19)=0,"s/d",SUMIFS('Mermas mensual'!$I$5:$I$22,'Mermas mensual'!$A$5:$A$22,$A19)) -> -2427.34 | G19: =IF(COUNTIF('Mermas mensual'!$A$5:$A$22,$A19)=0,"s/d",SUMIFS('Mermas mensual'!$M$5:$M$22,'Mermas mensual'!$A$5:$A$22,$A19)) -> -48130.659 | H19: =IF(COUNTIFS('Conciliación pipas'!$A$5:$A$40,$A19,'Conciliación pipas'!$G$5:$G$40,"NO CUADRA")>0,"NO CUADRA",IF(COUNTIFS('Conciliación pipas'!$A$5:$A$40,$A19,'Conciliación pipas'!$G$5:$G$40,"CUADRA")>0,IF(COUNTIFS('Conciliación pipas'!$A$5:$A$40,$A19,'Conciliación pipas'!$G$5:$G$40,"SIN REPORTE")>0,"PARCIAL","CUADRA"),IF(COUNTIF('Conciliación pipas'!$A$5:$A$40,$A19)=0,"s/d","SIN REPORTE"))) -> CUADRA | I19: =SUMIFS('Conciliación pipas'!$H$5:$H$40,'Conciliación pipas'!$A$5:$A$40,$A19) -> 0
A20: TREHER | B20: =IF(COUNTIFS('Mermas mensual'!$A$5:$A$22,$A20,'Mermas mensual'!$B$5:$B$22,"Regular")=0,"s/d",IF(SUMIFS('Mermas mensual'!$E$5:$E$22,'Mermas mensual'!$A$5:$A$22,$A20,'Mermas mensual'!$B$5:$B$22,"Regular")=0,0,SUMIFS('Mermas mensual'!$I$5:$I$22,'Mermas mensual'!$A$5:$A$22,$A20,'Mermas mensual'!$B$5:$B$22,"Regular")/SUMIFS('Mermas mensual'!$E$5:$E$22,'Mermas mensual'!$A$5:$A$22,$A20,'Mermas mensual'!$B$5:$B$22,"Regular"))) -> -0.0060210826 | C20: =IF(COUNTIFS('Mermas mensual'!$A$5:$A$22,$A20,'Mermas mensual'!$B$5:$B$22,"Premium")=0,"s/d",IF(SUMIFS('Mermas mensual'!$E$5:$E$22,'Mermas mensual'!$A$5:$A$22,$A20,'Mermas mensual'!$B$5:$B$22,"Premium")=0,0,SUMIFS('Mermas mensual'!$I$5:$I$22,'Mermas mensual'!$A$5:$A$22,$A20,'Mermas mensual'!$B$5:$B$22,"Premium")/SUMIFS('Mermas mensual'!$E$5:$E$22,'Mermas mensual'!$A$5:$A$22,$A20,'Mermas mensual'!$B$5:$B$22,"Premium"))) -> -0.0099483027 | D20: =IF(COUNTIFS('Mermas mensual'!$A$5:$A$22,$A20,'Mermas mensual'!$B$5:$B$22,"Diesel")=0,"s/d",IF(SUMIFS('Mermas mensual'!$E$5:$E$22,'Mermas mensual'!$A$5:$A$22,$A20,'Mermas mensual'!$B$5:$B$22,"Diesel")=0,0,SUMIFS('Mermas mensual'!$I$5:$I$22,'Mermas mensual'!$A$5:$A$22,$A20,'Mermas mensual'!$B$5:$B$22,"Diesel")/SUMIFS('Mermas mensual'!$E$5:$E$22,'Mermas mensual'!$A$5:$A$22,$A20,'Mermas mensual'!$B$5:$B$22,"Diesel"))) -> -0.001668718 | E20: =IF(COUNTIF('Mermas mensual'!$A$5:$A$22,$A20)=0,"s/d",IF(SUMIFS('Mermas mensual'!$E$5:$E$22,'Mermas mensual'!$A$5:$A$22,$A20)=0,0,SUMIFS('Mermas mensual'!$I$5:$I$22,'Mermas mensual'!$A$5:$A$22,$A20)/SUMIFS('Mermas mensual'!$E$5:$E$22,'Mermas mensual'!$A$5:$A$22,$A20))) -> -0.0045186915 | F20: =IF(COUNTIF('Mermas mensual'!$A$5:$A$22,$A20)=0,"s/d",SUMIFS('Mermas mensual'!$I$5:$I$22,'Mermas mensual'!$A$5:$A$22,$A20)) -> -2919.12 | G20: =IF(COUNTIF('Mermas mensual'!$A$5:$A$22,$A20)=0,"s/d",SUMIFS('Mermas mensual'!$M$5:$M$22,'Mermas mensual'!$A$5:$A$22,$A20)) -> -58520.049 | H20: =IF(COUNTIFS('Conciliación pipas'!$A$5:$A$40,$A20,'Conciliación pipas'!$G$5:$G$40,"NO CUADRA")>0,"NO CUADRA",IF(COUNTIFS('Conciliación pipas'!$A$5:$A$40,$A20,'Conciliación pipas'!$G$5:$G$40,"CUADRA")>0,IF(COUNTIFS('Conciliación pipas'!$A$5:$A$40,$A20,'Conciliación pipas'!$G$5:$G$40,"SIN REPORTE")>0,"PARCIAL","CUADRA"),IF(COUNTIF('Conciliación pipas'!$A$5:$A$40,$A20)=0,"s/d","SIN REPORTE"))) -> CUADRA | I20: =SUMIFS('Conciliación pipas'!$H$5:$H$40,'Conciliación pipas'!$A$5:$A$40,$A20) -> 0
A21: TH | B21: =IF(COUNTIFS('Mermas mensual'!$A$5:$A$22,$A21,'Mermas mensual'!$B$5:$B$22,"Regular")=0,"s/d",IF(SUMIFS('Mermas mensual'!$E$5:$E$22,'Mermas mensual'!$A$5:$A$22,$A21,'Mermas mensual'!$B$5:$B$22,"Regular")=0,0,SUMIFS('Mermas mensual'!$I$5:$I$22,'Mermas mensual'!$A$5:$A$22,$A21,'Mermas mensual'!$B$5:$B$22,"Regular")/SUMIFS('Mermas mensual'!$E$5:$E$22,'Mermas mensual'!$A$5:$A$22,$A21,'Mermas mensual'!$B$5:$B$22,"Regular"))) -> s/d | C21: =IF(COUNTIFS('Mermas mensual'!$A$5:$A$22,$A21,'Mermas mensual'!$B$5:$B$22,"Premium")=0,"s/d",IF(SUMIFS('Mermas mensual'!$E$5:$E$22,'Mermas mensual'!$A$5:$A$22,$A21,'Mermas mensual'!$B$5:$B$22,"Premium")=0,0,SUMIFS('Mermas mensual'!$I$5:$I$22,'Mermas mensual'!$A$5:$A$22,$A21,'Mermas mensual'!$B$5:$B$22,"Premium")/SUMIFS('Mermas mensual'!$E$5:$E$22,'Mermas mensual'!$A$5:$A$22,$A21,'Mermas mensual'!$B$5:$B$22,"Premium"))) -> s/d | D21: =IF(COUNTIFS('Mermas mensual'!$A$5:$A$22,$A21,'Mermas mensual'!$B$5:$B$22,"Diesel")=0,"s/d",IF(SUMIFS('Mermas mensual'!$E$5:$E$22,'Mermas mensual'!$A$5:$A$22,$A21,'Mermas mensual'!$B$5:$B$22,"Diesel")=0,0,SUMIFS('Mermas mensual'!$I$5:$I$22,'Mermas mensual'!$A$5:$A$22,$A21,'Mermas mensual'!$B$5:$B$22,"Diesel")/SUMIFS('Mermas mensual'!$E$5:$E$22,'Mermas mensual'!$A$5:$A$22,$A21,'Mermas mensual'!$B$5:$B$22,"Diesel"))) -> s/d | E21: =IF(COUNTIF('Mermas mensual'!$A$5:$A$22,$A21)=0,"s/d",IF(SUMIFS('Mermas mensual'!$E$5:$E$22,'Mermas mensual'!$A$5:$A$22,$A21)=0,0,SUMIFS('Mermas mensual'!$I$5:$I$22,'Mermas mensual'!$A$5:$A$22,$A21)/SUMIFS('Mermas mensual'!$E$5:$E$22,'Mermas mensual'!$A$5:$A$22,$A21))) -> s/d | F21: =IF(COUNTIF('Mermas mensual'!$A$5:$A$22,$A21)=0,"s/d",SUMIFS('Mermas mensual'!$I$5:$I$22,'Mermas mensual'!$A$5:$A$22,$A21)) -> s/d | G21: =IF(COUNTIF('Mermas mensual'!$A$5:$A$22,$A21)=0,"s/d",SUMIFS('Mermas mensual'!$M$5:$M$22,'Mermas mensual'!$A$5:$A$22,$A21)) -> s/d | H21: =IF(COUNTIFS('Conciliación pipas'!$A$5:$A$40,$A21,'Conciliación pipas'!$G$5:$G$40,"NO CUADRA")>0,"NO CUADRA",IF(COUNTIFS('Conciliación pipas'!$A$5:$A$40,$A21,'Conciliación pipas'!$G$5:$G$40,"CUADRA")>0,IF(COUNTIFS('Conciliación pipas'!$A$5:$A$40,$A21,'Conciliación pipas'!$G$5:$G$40,"SIN REPORTE")>0,"PARCIAL","CUADRA"),IF(COUNTIF('Conciliación pipas'!$A$5:$A$40,$A21)=0,"s/d","SIN REPORTE"))) -> SIN REPORTE | I21: =SUMIFS('Conciliación pipas'!$H$5:$H$40,'Conciliación pipas'!$A$5:$A$40,$A21) -> 0
A22: TOREMEX | B22: =IF(COUNTIFS('Mermas mensual'!$A$5:$A$22,$A22,'Mermas mensual'!$B$5:$B$22,"Regular")=0,"s/d",IF(SUMIFS('Mermas mensual'!$E$5:$E$22,'Mermas mensual'!$A$5:$A$22,$A22,'Mermas mensual'!$B$5:$B$22,"Regular")=0,0,SUMIFS('Mermas mensual'!$I$5:$I$22,'Mermas mensual'!$A$5:$A$22,$A22,'Mermas mensual'!$B$5:$B$22,"Regular")/SUMIFS('Mermas mensual'!$E$5:$E$22,'Mermas mensual'!$A$5:$A$22,$A22,'Mermas mensual'!$B$5:$B$22,"Regular"))) -> s/d | C22: =IF(COUNTIFS('Mermas mensual'!$A$5:$A$22,$A22,'Mermas mensual'!$B$5:$B$22,"Premium")=0,"s/d",IF(SUMIFS('Mermas mensual'!$E$5:$E$22,'Mermas mensual'!$A$5:$A$22,$A22,'Mermas mensual'!$B$5:$B$22,"Premium")=0,0,SUMIFS('Mermas mensual'!$I$5:$I$22,'Mermas mensual'!$A$5:$A$22,$A22,'Mermas mensual'!$B$5:$B$22,"Premium")/SUMIFS('Mermas mensual'!$E$5:$E$22,'Mermas mensual'!$A$5:$A$22,$A22,'Mermas mensual'!$B$5:$B$22,"Premium"))) -> s/d | D22: =IF(COUNTIFS('Mermas mensual'!$A$5:$A$22,$A22,'Mermas mensual'!$B$5:$B$22,"Diesel")=0,"s/d",IF(SUMIFS('Mermas mensual'!$E$5:$E$22,'Mermas mensual'!$A$5:$A$22,$A22,'Mermas mensual'!$B$5:$B$22,"Diesel")=0,0,SUMIFS('Mermas mensual'!$I$5:$I$22,'Mermas mensual'!$A$5:$A$22,$A22,'Mermas mensual'!$B$5:$B$22,"Diesel")/SUMIFS('Mermas mensual'!$E$5:$E$22,'Mermas mensual'!$A$5:$A$22,$A22,'Mermas mensual'!$B$5:$B$22,"Diesel"))) -> s/d | E22: =IF(COUNTIF('Mermas mensual'!$A$5:$A$22,$A22)=0,"s/d",IF(SUMIFS('Mermas mensual'!$E$5:$E$22,'Mermas mensual'!$A$5:$A$22,$A22)=0,0,SUMIFS('Mermas mensual'!$I$5:$I$22,'Mermas mensual'!$A$5:$A$22,$A22)/SUMIFS('Mermas mensual'!$E$5:$E$22,'Mermas mensual'!$A$5:$A$22,$A22))) -> s/d | F22: =IF(COUNTIF('Mermas mensual'!$A$5:$A$22,$A22)=0,"s/d",SUMIFS('Mermas mensual'!$I$5:$I$22,'Mermas mensual'!$A$5:$A$22,$A22)) -> s/d | G22: =IF(COUNTIF('Mermas mensual'!$A$5:$A$22,$A22)=0,"s/d",SUMIFS('Mermas mensual'!$M$5:$M$22,'Mermas mensual'!$A$5:$A$22,$A22)) -> s/d | H22: =IF(COUNTIFS('Conciliación pipas'!$A$5:$A$40,$A22,'Conciliación pipas'!$G$5:$G$40,"NO CUADRA")>0,"NO CUADRA",IF(COUNTIFS('Conciliación pipas'!$A$5:$A$40,$A22,'Conciliación pipas'!$G$5:$G$40,"CUADRA")>0,IF(COUNTIFS('Conciliación pipas'!$A$5:$A$40,$A22,'Conciliación pipas'!$G$5:$G$40,"SIN REPORTE")>0,"PARCIAL","CUADRA"),IF(COUNTIF('Conciliación pipas'!$A$5:$A$40,$A22)=0,"s/d","SIN REPORTE"))) -> SIN REPORTE | I22: =SUMIFS('Conciliación pipas'!$H$5:$H$40,'Conciliación pipas'!$A$5:$A$40,$A22) -> 0
A23: TEOLOYUCAN | B23: =IF(COUNTIFS('Mermas mensual'!$A$5:$A$22,$A23,'Mermas mensual'!$B$5:$B$22,"Regular")=0,"s/d",IF(SUMIFS('Mermas mensual'!$E$5:$E$22,'Mermas mensual'!$A$5:$A$22,$A23,'Mermas mensual'!$B$5:$B$22,"Regular")=0,0,SUMIFS('Mermas mensual'!$I$5:$I$22,'Mermas mensual'!$A$5:$A$22,$A23,'Mermas mensual'!$B$5:$B$22,"Regular")/SUMIFS('Mermas mensual'!$E$5:$E$22,'Mermas mensual'!$A$5:$A$22,$A23,'Mermas mensual'!$B$5:$B$22,"Regular"))) -> 0.020096157 | C23: =IF(COUNTIFS('Mermas mensual'!$A$5:$A$22,$A23,'Mermas mensual'!$B$5:$B$22,"Premium")=0,"s/d",IF(SUMIFS('Mermas mensual'!$E$5:$E$22,'Mermas mensual'!$A$5:$A$22,$A23,'Mermas mensual'!$B$5:$B$22,"Premium")=0,0,SUMIFS('Mermas mensual'!$I$5:$I$22,'Mermas mensual'!$A$5:$A$22,$A23,'Mermas mensual'!$B$5:$B$22,"Premium")/SUMIFS('Mermas mensual'!$E$5:$E$22,'Mermas mensual'!$A$5:$A$22,$A23,'Mermas mensual'!$B$5:$B$22,"Premium"))) -> 0.035197495 | D23: =IF(COUNTIFS('Mermas mensual'!$A$5:$A$22,$A23,'Mermas mensual'!$B$5:$B$22,"Diesel")=0,"s/d",IF(SUMIFS('Mermas mensual'!$E$5:$E$22,'Mermas mensual'!$A$5:$A$22,$A23,'Mermas mensual'!$B$5:$B$22,"Diesel")=0,0,SUMIFS('Mermas mensual'!$I$5:$I$22,'Mermas mensual'!$A$5:$A$22,$A23,'Mermas mensual'!$B$5:$B$22,"Diesel")/SUMIFS('Mermas mensual'!$E$5:$E$22,'Mermas mensual'!$A$5:$A$22,$A23,'Mermas mensual'!$B$5:$B$22,"Diesel"))) -> 0.0051166726 | E23: =IF(COUNTIF('Mermas mensual'!$A$5:$A$22,$A23)=0,"s/d",IF(SUMIFS('Mermas mensual'!$E$5:$E$22,'Mermas mensual'!$A$5:$A$22,$A23)=0,0,SUMIFS('Mermas mensual'!$I$5:$I$22,'Mermas mensual'!$A$5:$A$22,$A23)/SUMIFS('Mermas mensual'!$E$5:$E$22,'Mermas mensual'!$A$5:$A$22,$A23))) -> 0.014430254 | F23: =IF(COUNTIF('Mermas mensual'!$A$5:$A$22,$A23)=0,"s/d",SUMIFS('Mermas mensual'!$I$5:$I$22,'Mermas mensual'!$A$5:$A$22,$A23)) -> 5362.1 | G23: =IF(COUNTIF('Mermas mensual'!$A$5:$A$22,$A23)=0,"s/d",SUMIFS('Mermas mensual'!$M$5:$M$22,'Mermas mensual'!$A$5:$A$22,$A23)) -> 110873.89 | H23: =IF(COUNTIFS('Conciliación pipas'!$A$5:$A$40,$A23,'Conciliación pipas'!$G$5:$G$40,"NO CUADRA")>0,"NO CUADRA",IF(COUNTIFS('Conciliación pipas'!$A$5:$A$40,$A23,'Conciliación pipas'!$G$5:$G$40,"CUADRA")>0,IF(COUNTIFS('Conciliación pipas'!$A$5:$A$40,$A23,'Conciliación pipas'!$G$5:$G$40,"SIN REPORTE")>0,"PARCIAL","CUADRA"),IF(COUNTIF('Conciliación pipas'!$A$5:$A$40,$A23)=0,"s/d","SIN REPORTE"))) -> CUADRA | I23: =SUMIFS('Conciliación pipas'!$H$5:$H$40,'Conciliación pipas'!$A$5:$A$40,$A23) -> 0
A25: Semáforo: | B25: Verde: |merma| ≤ 0.40 % | D25: Amarillo: 0.40 % – 0.50 % | F25: Rojo: > 0.50 % (fuera SAT) | H25: s/d: sin reporte de mermas
A26: Negativo = faltante de combustible · Positivo = sobrante. Los umbrales se cambian en la hoja Parámetros.

Sheet Mermas mensual
A1: Mermas mensuales por estación y producto
A2: Periodo: Agosto 2026 · Generado: 22/09/2026 17:01 · Límite SAT: merma ≤ 0.5% de la venta
A4: Estación | B4: Producto | C4: Sdo. Inicial (1er día) | D4: Compras | E4: Ventas | F4: Ajustes | G4: Sdo. Final (teórico) | H4: Sdo. Real (último día) | I4: Merma (L) | J4: Merma % | K4: Estado | L4: Costo prom. pipas ($/L) | M4: Merma ($) | N4: Pipas NO registradas (L) | O4: Merma ajustada (L) | P4: Merma % ajustada | R4: Etiqueta gráfica
A5: AURORA | B5: Regular | C5: 39387.69 | D5: =SUMIFS('Detalle diario'!$E$5:$E$550,'Detalle diario'!$A$5:$A$550,A5,'Detalle diario'!$B$5:$B$550,B5)+SUMIFS('Detalle diario'!$L$5:$L$550,'Detalle diario'!$A$5:$A$550,A5,'Detalle diario'!$B$5:$B$550,B5) -> 643188 | E5: =SUMIFS('Detalle diario'!$F$5:$F$550,'Detalle diario'!$A$5:$A$550,A5,'Detalle diario'!$B$5:$B$550,B5) -> 649583.42 | F5: =SUMIFS('Detalle diario'!$G$5:$G$550,'Detalle diario'!$A$5:$A$550,A5,'Detalle diario'!$B$5:$B$550,B5) -> 0 | G5: =C5+D5-E5+F5 -> 32992.27 | H5: 62089.03 | I5: =H5-G5 -> 29096.76 | J5: =IF(E5=0,0,I5/E5) -> 0.044792954 | K5: =IF(ABS(J5)>Parámetros!$C$5,"FUERA",IF(ABS(J5)>Parámetros!$C$6,"ALERTA","OK")) -> FUERA | L5: 18.979 | M5: =I5*L5 -> 552227.41 | N5: =SUMIFS('Detalle pipas'!$G$5:$G$281,'Detalle pipas'!$A$5:$A$281,A5,'Detalle pipas'!$B$5:$B$281,B5,'Detalle pipas'!$L$5:$L$281,"NO REGISTRADA*") -> 33465 | O5: =I5-N5 -> -4368.24 | P5: =IF(E5=0,0,O5/E5) -> -0.006724679 | R5: =A5&" · "&B5 -> AURORA · Regular
A6: AURORA | B6: Premium | C6: 13598.9 | D6: =SUMIFS('Detalle diario'!$E$5:$E$550,'Detalle diario'!$A$5:$A$550,A6,'Detalle diario'!$B$5:$B$550,B6)+SUMIFS('Detalle diario'!$L$5:$L$550,'Detalle diario'!$A$5:$A$550,A6,'Detalle diario'!$B$5:$B$550,B6) -> 72049 | E6: =SUMIFS('Detalle diario'!$F$5:$F$550,'Detalle diario'!$A$5:$A$550,A6,'Detalle diario'!$B$5:$B$550,B6) -> 61367.16 | F6: =SUMIFS('Detalle diario'!$G$5:$G$550,'Detalle diario'!$A$5:$A$550,A6,'Detalle diario'!$B$5:$B$550,B6) -> 0 | G6: =C6+D6-E6+F6 -> 24280.74 | H6: 23878.08 | I6: =H6-G6 -> -402.66 | J6: =IF(E6=0,0,I6/E6) -> -0.0065614899 | K6: =IF(ABS(J6)>Parámetros!$C$5,"FUERA",IF(ABS(J6)>Parámetros!$C$6,"ALERTA","OK")) -> FUERA | L6: 22.3794 | M6: =I6*L6 -> -9011.2892 | N6: =SUMIFS('Detalle pipas'!$G$5:$G$281,'Detalle pipas'!$A$5:$A$281,A6,'Detalle pipas'!$B$5:$B$281,B6,'Detalle pipas'!$L$5:$L$281,"NO REGISTRADA*") -> 0 | O6: =I6-N6 -> -402.66 | P6: =IF(E6=0,0,O6/E6) -> -0.0065614899 | R6: =A6&" · "&B6 -> AURORA · Premium
A7: AURORA | B7: Diesel | C7: 27221.33 | D7: =SUMIFS('Detalle diario'!$E$5:$E$550,'Detalle diario'!$A$5:$A$550,A7,'Detalle diario'!$B$5:$B$550,B7)+SUMIFS('Detalle diario'!$L$5:$L$550,'Detalle diario'!$A$5:$A$550,A7,'Detalle diario'!$B$5:$B$550,B7) -> 287001 | E7: =SUMIFS('Detalle diario'!$F$5:$F$550,'Detalle diario'!$A$5:$A$550,A7,'Detalle diario'!$B$5:$B$550,B7) -> 286219.08 | F7: =SUMIFS('Detalle diario'!$G$5:$G$550,'Detalle diario'!$A$5:$A$550,A7,'Detalle diario'!$B$5:$B$550,B7) -> 0 | G7: =C7+D7-E7+F7 -> 28003.25 | H7: 28496.59 | I7: =H7-G7 -> 493.34 | J7: =IF(E7=0,0,I7/E7) -> 0.0017236447 | K7: =IF(ABS(J7)>Parámetros!$C$5,"FUERA",IF(ABS(J7)>Parámetros!$C$6,"ALERTA","OK")) -> OK | L7: 21.782 | M7: =I7*L7 -> 10745.932 | N7: =SUMIFS('Detalle pipas'!$G$5:$G$281,'Detalle pipas'!$A$5:$A$281,A7,'Detalle pipas'!$B$5:$B$281,B7,'Detalle pipas'!$L$5:$L$281,"NO REGISTRADA*") -> 0 | O7: =I7-N7 -> 493.34 | P7: =IF(E7=0,0,O7/E7) -> 0.0017236447 | R7: =A7&" · "&B7 -> AURORA · Diesel
A8: HUEHUETOCA | B8: Regular | C8: 24744.8 | D8: =SUMIFS('Detalle diario'!$E$5:$E$550,'Detalle diario'!$A$5:$A$550,A8,'Detalle diario'!$B$5:$B$550,B8)+SUMIFS('Detalle diario'!$L$5:$L$550,'Detalle diario'!$A$5:$A$550,A8,'Detalle diario'!$B$5:$B$550,B8) -> 512270 | E8: =SUMIFS('Detalle diario'!$F$5:$F$550,'Detalle diario'!$A$5:$A$550,A8,'Detalle diario'!$B$5:$B$550,B8) -> 474394.78 | F8: =SUMIFS('Detalle diario'!$G$5:$G$550,'Detalle diario'!$A$5:$A$550,A8,'Detalle diario'!$B$5:$B$550,B8) -> 0 | G8: =C8+D8-E8+F8 -> 62620.02 | H8: 60042.66 | I8: =H8-G8 -> -2577.36 | J8: =IF(E8=0,0,I8/E8) -> -0.0054329434 | K8: =IF(ABS(J8)>Parámetros!$C$5,"FUERA",IF(ABS(J8)>Parámetros!$C$6,"ALERTA","OK")) -> FUERA | L8: 18.8382 | M8: =I8*L8 -> -48552.823 | N8: =SUMIFS('Detalle pipas'!$G$5:$G$281,'Detalle pipas'!$A$5:$A$281,A8,'Detalle pipas'!$B$5:$B$281,B8,'Detalle pipas'!$L$5:$L$281,"NO REGISTRADA*") -> 0 | O8: =I8-N8 -> -2577.36 | P8: =IF(E8=0,0,O8/E8) -> -0.0054329434 | R8: =A8&" · "&B8 -> HUEHUETOCA · Regular
A9: HUEHUETOCA | B9: Premium | C9: 26497.19 | D9: =SUMIFS('Detalle diario'!$E$5:$E$550,'Detalle diario'!$A$5:$A$550,A9,'Detalle diario'!$B$5:$B$550,B9)+SUMIFS('Detalle diario'!$L$5:$L$550,'Detalle diario'!$A$5:$A$550,A9,'Detalle diario'!$B$5:$B$550,B9) -> 60101 | E9: =SUMIFS('Detalle diario'!$F$5:$F$550,'Detalle diario'!$A$5:$A$550,A9,'Detalle diario'!$B$5:$B$550,B9) -> 52262.92 | F9: =SUMIFS('Detalle diario'!$G$5:$G$550,'Detalle diario'!$A$5:$A$550,A9,'Detalle diario'!$B$5:$B$550,B9) -> 0 | G9: =C9+D9-E9+F9 -> 34335.27 | H9: 34179.45 | I9: =H9-G9 -> -155.82 | J9: =IF(E9=0,0,I9/E9) -> -0.0029814637 | K9: =IF(ABS(J9)>Parámetros!$C$5,"FUERA",IF(ABS(J9)>Parámetros!$C$6,"ALERTA","OK")) -> OK | L9: 22.4114 | M9: =I9*L9 -> -3492.1443 | N9: =SUMIFS('Detalle pipas'!$G$5:$G$281,'Detalle pipas'!$A$5:$A$281,A9,'Detalle pipas'!$B$5:$B$281,B9,'Detalle pipas'!$L$5:$L$281,"NO REGISTRADA*") -> 0 | O9: =I9-N9 -> -155.82 | P9: =IF(E9=0,0,O9/E9) -> -0.0029814637 | R9: =A9&" · "&B9 -> HUEHUETOCA · Premium
A10: HUEHUETOCA | B10: Diesel | C10: 46175.06 | D10: =SUMIFS('Detalle diario'!$E$5:$E$550,'Detalle diario'!$A$5:$A$550,A10,'Detalle diario'!$B$5:$B$550,B10)+SUMIFS('Detalle diario'!$L$5:$L$550,'Detalle diario'!$A$5:$A$550,A10,'Detalle diario'!$B$5:$B$550,B10) -> 272939 | E10: =SUMIFS('Detalle diario'!$F$5:$F$550,'Detalle diario'!$A$5:$A$550,A10,'Detalle diario'!$B$5:$B$550,B10) -> 264906.61 | F10: =SUMIFS('Detalle diario'!$G$5:$G$550,'Detalle diario'!$A$5:$A$550,A10,'Detalle diario'!$B$5:$B$550,B10) -> 0 | G10: =C10+D10-E10+F10 -> 54207.45 | H10: 53082.78 | I10: =H10-G10 -> -1124.67 | J10: =IF(E10=0,0,I10/E10) -> -0.0042455339 | K10: =IF(ABS(J10)>Parámetros!$C$5,"FUERA",IF(ABS(J10)>Parámetros!$C$6,"ALERTA","OK")) -> ALERTA | L10: 21.7034 | M10: =I10*L10 -> -24409.163 | N10: =SUMIFS('Detalle pipas'!$G$5:$G$281,'Detalle pipas'!$A$5:$A$281,A10,'Detalle pipas'!$B$5:$B$281,B10,'Detalle pipas'!$L$5:$L$281,"NO REGISTRADA*") -> 0 | O10: =I10-N10 -> -1124.67 | P10: =IF(E10=0,0,O10/E10) -> -0.0042455339 | R10: =A10&" · "&B10 -> HUEHUETOCA · Diesel
A11: QL | B11: Regular | C11: 164102.01 | D11: =SUMIFS('Detalle diario'!$E$5:$E$550,'Detalle diario'!$A$5:$A$550,A11,'Detalle diario'!$B$5:$B$550,B11)+SUMIFS('Detalle diario'!$L$5:$L$550,'Detalle diario'!$A$5:$A$550,A11,'Detalle diario'!$B$5:$B$550,B11) -> 579699 | E11: =SUMIFS('Detalle diario'!$F$5:$F$550,'Detalle diario'!$A$5:$A$550,A11,'Detalle diario'!$B$5:$B$550,B11) -> 611397.51 | F11: =SUMIFS('Detalle diario'!$G$5:$G$550,'Detalle diario'!$A$5:$A$550,A11,'Detalle diario'!$B$5:$B$550,B11) -> 0 | G11: =C11+D11-E11+F11 -> 132403.5 | H11: 129526.66 | I11: =H11-G11 -> -2876.84 | J11: =IF(E11=0,0,I11/E11) -> -0.0047053512 | K11: =IF(ABS(J11)>Parámetros!$C$5,"FUERA",IF(ABS(J11)>Parámetros!$C$6,"ALERTA","OK")) -> ALERTA | L11: 18.9784 | M11: =I11*L11 -> -54597.82 | N11: =SUMIFS('Detalle pipas'!$G$5:$G$281,'Detalle pipas'!$A$5:$A$281,A11,'Detalle pipas'!$B$5:$B$281,B11,'Detalle pipas'!$L$5:$L$281,"NO REGISTRADA*") -> 0 | O11: =I11-N11 -> -2876.84 | P11: =IF(E11=0,0,O11/E11) -> -0.0047053512 | R11: =A11&" · "&B11 -> QL · Regular
A12: QL | B12: Premium | C12: 62944.93 | D12: =SUMIFS('Detalle diario'!$E$5:$E$550,'Detalle diario'!$A$5:$A$550,A12,'Detalle diario'!$B$5:$B$550,B12)+SUMIFS('Detalle diario'!$L$5:$L$550,'Detalle diario'!$A$5:$A$550,A12,'Detalle diario'!$B$5:$B$550,B12) -> 300298 | E12: =SUMIFS('Detalle diario'!$F$5:$F$550,'Detalle diario'!$A$5:$A$550,A12,'Detalle diario'!$B$5:$B$550,B12) -> 316032.5 | F12: =SUMIFS('Detalle diario'!$G$5:$G$550,'Detalle diario'!$A$5:$A$550,A12,'Detalle diario'!$B$5:$B$550,B12) -> 0 | G12: =C12+D12-E12+F12 -> 47210.43 | H12: 45159.1 | I12: =H12-G12 -> -2051.33 | J12: =IF(E12=0,0,I12/E12) -> -0.0064908831 | K12: =IF(ABS(J12)>Parámetros!$C$5,"FUERA",IF(ABS(J12)>Parámetros!$C$6,"ALERTA","OK")) -> FUERA | L12: 22.5031 | M12: =I12*L12 -> -46161.284 | N12: =SUMIFS('Detalle pipas'!$G$5:$G$281,'Detalle pipas'!$A$5:$A$281,A12,'Detalle pipas'!$B$5:$B$281,B12,'Detalle pipas'!$L$5:$L$281,"NO REGISTRADA*") -> 0 | O12: =I12-N12 -> -2051.33 | P12: =IF(E12=0,0,O12/E12) -> -0.0064908831 | R12: =A12&" · "&B12 -> QL · Premium
A13: QL | B13: Diesel | C13: 117500.54 | D13: =SUMIFS('Detalle diario'!$E$5:$E$550,'Detalle diario'!$A$5:$A$550,A13,'Detalle diario'!$B$5:$B$550,B13)+SUMIFS('Detalle diario'!$L$5:$L$550,'Detalle diario'!$A$5:$A$550,A13,'Detalle diario'!$B$5:$B$550,B13) -> 877365 | E13: =SUMIFS('Detalle diario'!$F$5:$F$550,'Detalle diario'!$A$5:$A$550,A13,'Detalle diario'!$B$5:$B$550,B13) -> 924853.59 | F13: =SUMIFS('Detalle diario'!$G$5:$G$550,'Detalle diario'!$A$5:$A$550,A13,'Detalle diario'!$B$5:$B$550,B13) -> 0 | G13: =C13+D13-E13+F13 -> 70011.95 | H13: 75919 | I13: =H13-G13 -> 5907.05 | J13: =IF(E13=0,0,I13/E13) -> 0.0063870109 | K13: =IF(ABS(J13)>Parámetros!$C$5,"FUERA",IF(ABS(J13)>Parámetros!$C$6,"ALERTA","OK")) -> FUERA | L13: 21.8 | M13: =I13*L13 -> 128773.69 | N13: =SUMIFS('Detalle pipas'!$G$5:$G$281,'Detalle pipas'!$A$5:$A$281,A13,'Detalle pipas'!$B$5:$B$281,B13,'Detalle pipas'!$L$5:$L$281,"NO REGISTRADA*") -> 0 | O13: =I13-N13 -> 5907.05 | P13: =IF(E13=0,0,O13/E13) -> 0.0063870109 | R13: =A13&" · "&B13 -> QL · Diesel
A14: IXTAZACUALA | B14: Regular | C14: 0 | D14: =SUMIFS('Detalle diario'!$E$5:$E$550,'Detalle diario'!$A$5:$A$550,A14,'Detalle diario'!$B$5:$B$550,B14)+SUMIFS('Detalle diario'!$L$5:$L$550,'Detalle diario'!$A$5:$A$550,A14,'Detalle diario'!$B$5:$B$550,B14) -> 332823 | E14: =SUMIFS('Detalle diario'!$F$5:$F$550,'Detalle diario'!$A$5:$A$550,A14,'Detalle diario'!$B$5:$B$550,B14) -> 347704.63 | F14: =SUMIFS('Detalle diario'!$G$5:$G$550,'Detalle diario'!$A$5:$A$550,A14,'Detalle diario'!$B$5:$B$550,B14) -> 51578 | G14: =C14+D14-E14+F14 -> 36696.37 | H14: 34749.29 | I14: =H14-G14 -> -1947.08 | J14: =IF(E14=0,0,I14/E14) -> -0.0055998104 | K14: =IF(ABS(J14)>Parámetros!$C$5,"FUERA",IF(ABS(J14)>Parámetros!$C$6,"ALERTA","OK")) -> FUERA | L14: 19.128 | M14: =I14*L14 -> -37243.746 | N14: =SUMIFS('Detalle pipas'!$G$5:$G$281,'Detalle pipas'!$A$5:$A$281,A14,'Detalle pipas'!$B$5:$B$281,B14,'Detalle pipas'!$L$5:$L$281,"NO REGISTRADA*") -> 0 | O14: =I14-N14 -> -1947.08 | P14: =IF(E14=0,0,O14/E14) -> -0.0055998104 | R14: =A14&" · "&B14 -> IXTAZACUALA · Regular
A15: IXTAZACUALA | B15: Premium | C15: 0 | D15: =SUMIFS('Detalle diario'!$E$5:$E$550,'Detalle diario'!$A$5:$A$550,A15,'Detalle diario'!$B$5:$B$550,B15)+SUMIFS('Detalle diario'!$L$5:$L$550,'Detalle diario'!$A$5:$A$550,A15,'Detalle diario'!$B$5:$B$550,B15) -> 59834 | E15: =SUMIFS('Detalle diario'!$F$5:$F$550,'Detalle diario'!$A$5:$A$550,A15,'Detalle diario'!$B$5:$B$550,B15) -> 57212.38 | F15: =SUMIFS('Detalle diario'!$G$5:$G$550,'Detalle diario'!$A$5:$A$550,A15,'Detalle diario'!$B$5:$B$550,B15) -> 27932 | G15: =C15+D15-E15+F15 -> 30553.62 | H15: 30015.15 | I15: =H15-G15 -> -538.47 | J15: =IF(E15=0,0,I15/E15) -> -0.0094117742 | K15: =IF(ABS(J15)>Parámetros!$C$5,"FUERA",IF(ABS(J15)>Parámetros!$C$6,"ALERTA","OK")) -> FUERA | L15: 22.5882 | M15: =I15*L15 -> -12163.068 | N15: =SUMIFS('Detalle pipas'!$G$5:$G$281,'Detalle pipas'!$A$5:$A$281,A15,'Detalle pipas'!$B$5:$B$281,B15,'Detalle pipas'!$L$5:$L$281,"NO REGISTRADA*") -> 0 | O15: =I15-N15 -> -538.47 | P15: =IF(E15=0,0,O15/E15) -> -0.0094117742 | R15: =A15&" · "&B15 -> IXTAZACUALA · Premium
A16: IXTAZACUALA | B16: Diesel | C16: 0 | D16: =SUMIFS('Detalle diario'!$E$5:$E$550,'Detalle diario'!$A$5:$A$550,A16,'Detalle diario'!$B$5:$B$550,B16)+SUMIFS('Detalle diario'!$L$5:$L$550,'Detalle diario'!$A$5:$A$550,A16,'Detalle diario'!$B$5:$B$550,B16) -> 303295 | E16: =SUMIFS('Detalle diario'!$F$5:$F$550,'Detalle diario'!$A$5:$A$550,A16,'Detalle diario'!$B$5:$B$550,B16) -> 313698.96 | F16: =SUMIFS('Detalle diario'!$G$5:$G$550,'Detalle diario'!$A$5:$A$550,A16,'Detalle diario'!$B$5:$B$550,B16) -> 38703 | G16: =C16+D16-E16+F16 -> 28299.04 | H16: 28357.25 | I16: =H16-G16 -> 58.21 | J16: =IF(E16=0,0,I16/E16) -> 0.00018556007 | K16: =IF(ABS(J16)>Parámetros!$C$5,"FUERA",IF(ABS(J16)>Parámetros!$C$6,"ALERTA","OK")) -> OK | L16: 21.9233 | M16: =I16*L16 -> 1276.1553 | N16: =SUMIFS('Detalle pipas'!$G$5:$G$281,'Detalle pipas'!$A$5:$A$281,A16,'Detalle pipas'!$B$5:$B$281,B16,'Detalle pipas'!$L$5:$L$281,"NO REGISTRADA*") -> 0 | O16: =I16-N16 -> 58.21 | P16: =IF(E16=0,0,O16/E16) -> 0.00018556007 | R16: =A16&" · "&B16 -> IXTAZACUALA · Diesel
... A22: TEOLOYUCAN | B22: Diesel | C22: 60935.26 | D22: =SUMIFS('Detalle diario'!$E$5:$E$550,'Detalle diario'!$A$5:$A$550,A22,'Detalle diario'!$B$5:$B$550,B22)+SUMIFS('Detalle diario'!$L$5:$L$550,'Detalle diario'!$A$5:$A$550,A22,'Detalle diario'!$B$5:$B$550,B22) -> 166412 | E22: =SUMIFS('Detalle diario'!$F$5:$F$550,'Detalle diario'!$A$5:$A$550,A22,'Detalle diario'!$B$5:$B$550,B22) -> 194806.29 | F22: =SUMIFS('Detalle diario'!$G$5:$G$550,'Detalle diario'!$A$5:$A$550,A22,'Detalle diario'!$B$5:$B$550,B22) -> 0 | G22: =C22+D22-E22+F22 -> 32540.97 | H22: 33537.73 | I22: =H22-G22 -> 996.76 | J22: =IF(E22=0,0,I22/E22) -> 0.0051166726 | K22: =IF(ABS(J22)>Parámetros!$C$5,"FUERA",IF(ABS(J22)>Parámetros!$C$6,"ALERTA","OK")) -> FUERA | L22: 21.8312 | M22: =I22*L22 -> 21760.467 | N22: =SUMIFS('Detalle pipas'!$G$5:$G$281,'Detalle pipas'!$A$5:$A$281,A22,'Detalle pipas'!$B$5:$B$281,B22,'Detalle pipas'!$L$5:$L$281,"NO REGISTRADA*") -> 0 | O22: =I22-N22 -> 996.76 | P22: =IF(E22=0,0,O22/E22) -> 0.0051166726 | R22: =A22&" · "&B22 -> TEOLOYUCAN · Diesel
A23: TOTAL GRUPO | C23: =SUM(C5:C22) -> 800950.46 | D23: =SUM(D5:D22) -> 5246240 | E23: =SUM(E5:E22) -> 5377230.9 | F23: =SUM(F5:F22) -> 118213 | G23: =SUM(G5:G22) -> 788172.54 | H23: =SUM(H5:H22) -> 814496.65 | I23: =SUM(I5:I22) -> 26324.11 | J23: =IF(E23=0,0,I23/E23) -> 0.0048954769 | K23: =IF(ABS(J23)>Parámetros!$C$5,"FUERA",IF(ABS(J23)>Parámetros!$C$6,"ALERTA","OK")) -> ALERTA | M23: =SUM(M5:M22) -> 509745.69 | N23: =SUM(N5:N22) -> 33465 | O23: =SUM(O5:O22) -> -7140.89 | P23: =IF(E23=0,0,O23/E23) -> -0.0013279865
A25: Merma = Sdo. Real − Sdo. Final; Sdo. Final = Sdo. Inicial + Compras − Ventas + Ajustes; Merma % = Merma / Ventas. Negativo = faltante, positivo = sobrante.
A26: Costo prom. = promedio ponderado del CTO UNIT de las pipas del mes (dato del Excel de pipas); Merma ($) = Merma (L) × Costo prom.
A27: Merma ajustada = Merma − litros de pipas NO registradas: si una pipa llegó físicamente pero no se capturó, aparece como sobrante. Es un indicador de apoyo; el oficial es Merma %.
A28: Compras incluye lo capturado en la hoja Registros manuales.

Sheet Compras sin pipa
A1: Compras registradas en mermas que no se encontraron en PIPAS DEL MES
A2: Periodo: Agosto 2026 · Generado: 22/09/2026 17:01 · Límite SAT: merma ≤ 0.5% de la venta
A4: Estación | B4: Producto | C4: Fecha | D4: Litros | E4: Nota
A5: ✔ Todas las compras del reporte de mermas tienen una pipa que las respalda.

Sheet Detalle diario
A1: Detalle diario de mermas
A2: Periodo: Agosto 2026 · Generado: 22/09/2026 17:01 · Límite SAT: merma ≤ 0.5% de la venta
A4: Estación | B4: Producto | C4: Fecha | D4: Sdo. Inicial | E4: Compras | F4: Ventas | G4: Ajustes | H4: Sdo. Final | I4: Sdo. Real | J4: Merma | K4: Merma % | L4: Compras manuales
A5: AURORA | B5: Regular | C5: 46235 | D5: 39387.69 | E5: 36301 | F5: 21890.23 | G5: 0 | H5: =D5+E5+L5-F5+G5 -> 53798.46 | I5: 53530.23 | J5: =I5-H5 -> -268.23 | K5: =IF(F5=0,0,J5/F5) -> -0.012253412 | L5: =SUMIFS('Registros manuales'!$D$5:$D$104,'Registros manuales'!$A$5:$A$104,A5,'Registros manuales'!$B$5:$B$104,B5,'Registros manuales'!$C$5:$C$104,C5) -> 0
A6: AURORA | B6: Regular | C6: 46236 | D6: 53530.23 | E6: 0 | F6: 21607.51 | G6: 0 | H6: =D6+E6+L6-F6+G6 -> 31922.72 | I6: 31700.8 | J6: =I6-H6 -> -221.92 | K6: =IF(F6=0,0,J6/F6) -> -0.010270503 | L6: =SUMIFS('Registros manuales'!$D$5:$D$104,'Registros manuales'!$A$5:$A$104,A6,'Registros manuales'!$B$5:$B$104,B6,'Registros manuales'!$C$5:$C$104,C6) -> 0
A7: AURORA | B7: Regular | C7: 46237 | D7: 31700.8 | E7: 0 | F7: 21480.42 | G7: 0 | H7: =D7+E7+L7-F7+G7 -> 10220.38 | I7: 46203.5 | J7: =I7-H7 -> 35983.12 | K7: =IF(F7=0,0,J7/F7) -> 1.6751591 | L7: =SUMIFS('Registros manuales'!$D$5:$D$104,'Registros manuales'!$A$5:$A$104,A7,'Registros manuales'!$B$5:$B$104,B7,'Registros manuales'!$C$5:$C$104,C7) -> 0
A8: AURORA | B8: Regular | C8: 46238 | D8: 46203.5 | E8: 71939 | F8: 19654.4 | G8: 0 | H8: =D8+E8+L8-F8+G8 -> 98488.1 | I8: 62940.98 | J8: =I8-H8 -> -35547.12 | K8: =IF(F8=0,0,J8/F8) -> -1.8086088 | L8: =SUMIFS('Registros manuales'!$D$5:$D$104,'Registros manuales'!$A$5:$A$104,A8,'Registros manuales'!$B$5:$B$104,B8,'Registros manuales'!$C$5:$C$104,C8) -> 0
A9: AURORA | B9: Regular | C9: 46239 | D9: 62940.98 | E9: 36205 | F9: 18995.34 | G9: 0 | H9: =D9+E9+L9-F9+G9 -> 80150.64 | I9: 80328.18 | J9: =I9-H9 -> 177.54 | K9: =IF(F9=0,0,J9/F9) -> 0.0093465029 | L9: =SUMIFS('Registros manuales'!$D$5:$D$104,'Registros manuales'!$A$5:$A$104,A9,'Registros manuales'!$B$5:$B$104,B9,'Registros manuales'!$C$5:$C$104,C9) -> 0
A10: AURORA | B10: Regular | C10: 46240 | D10: 80328.18 | E10: 0 | F10: 18973.63 | G10: 0 | H10: =D10+E10+L10-F10+G10 -> 61354.55 | I10: 60852.39 | J10: =I10-H10 -> -502.16 | K10: =IF(F10=0,0,J10/F10) -> -0.026466206 | L10: =SUMIFS('Registros manuales'!$D$5:$D$104,'Registros manuales'!$A$5:$A$104,A10,'Registros manuales'!$B$5:$B$104,B10,'Registros manuales'!$C$5:$C$104,C10) -> 0
A11: AURORA | B11: Regular | C11: 46241 | D11: 60852.39 | E11: 0 | F11: 20761.1 | G11: 0 | H11: =D11+E11+L11-F11+G11 -> 40091.29 | I11: 76261.01 | J11: =I11-H11 -> 36169.72 | K11: =IF(F11=0,0,J11/F11) -> 1.7421871 | L11: =SUMIFS('Registros manuales'!$D$5:$D$104,'Registros manuales'!$A$5:$A$104,A11,'Registros manuales'!$B$5:$B$104,B11,'Registros manuales'!$C$5:$C$104,C11) -> 0
A12: AURORA | B12: Regular | C12: 46242 | D12: 76261.01 | E12: 0 | F12: 22083.9 | G12: 0 | H12: =D12+E12+L12-F12+G12 -> 54177.11 | I12: 53582.48 | J12: =I12-H12 -> -594.63 | K12: =IF(F12=0,0,J12/F12) -> -0.026925951 | L12: =SUMIFS('Registros manuales'!$D$5:$D$104,'Registros manuales'!$A$5:$A$104,A12,'Registros manuales'!$B$5:$B$104,B12,'Registros manuales'!$C$5:$C$104,C12) -> 0
A13: AURORA | B13: Regular | C13: 46243 | D13: 53582.48 | E13: 35932 | F13: 20327.96 | G13: 0 | H13: =D13+E13+L13-F13+G13 -> 69186.52 | I13: 32968.45 | J13: =I13-H13 -> -36218.07 | K13: =IF(F13=0,0,J13/F13) -> -1.7816874 | L13: =SUMIFS('Registros manuales'!$D$5:$D$104,'Registros manuales'!$A$5:$A$104,A13,'Registros manuales'!$B$5:$B$104,B13,'Registros manuales'!$C$5:$C$104,C13) -> 0
A14: AURORA | B14: Regular | C14: 46244 | D14: 32968.45 | E14: 0 | F14: 19657.01 | G14: 0 | H14: =D14+E14+L14-F14+G14 -> 13311.44 | I14: 49495.2 | J14: =I14-H14 -> 36183.76 | K14: =IF(F14=0,0,J14/F14) -> 1.840756 | L14: =SUMIFS('Registros manuales'!$D$5:$D$104,'Registros manuales'!$A$5:$A$104,A14,'Registros manuales'!$B$5:$B$104,B14,'Registros manuales'!$C$5:$C$104,C14) -> 0
A15: AURORA | B15: Regular | C15: 46245 | D15: 49495.2 | E15: 72420 | F15: 19919.71 | G15: 0 | H15: =D15+E15+L15-F15+G15 -> 101995.49 | I15: 65871.94 | J15: =I15-H15 -> -36123.55 | K15: =IF(F15=0,0,J15/F15) -> -1.8134576 | L15: =SUMIFS('Registros manuales'!$D$5:$D$104,'Registros manuales'!$A$5:$A$104,A15,'Registros manuales'!$B$5:$B$104,B15,'Registros manuales'!$C$5:$C$104,C15) -> 0
A16: AURORA | B16: Regular | C16: 46246 | D16: 65871.94 | E16: 36007 | F16: 19356.4 | G16: 0 | H16: =D16+E16+L16-F16+G16 -> 82522.54 | I16: 82826.43 | J16: =I16-H16 -> 303.89 | K16: =IF(F16=0,0,J16/F16) -> 0.015699717 | L16: =SUMIFS('Registros manuales'!$D$5:$D$104,'Registros manuales'!$A$5:$A$104,A16,'Registros manuales'!$B$5:$B$104,B16,'Registros manuales'!$C$5:$C$104,C16) -> 0
... A550: TEOLOYUCAN | B550: Diesel | C550: 46265 | D550: 38280.1 | E550: 0 | F550: 4727.86 | G550: 0 | H550: =D550+E550+L550-F550+G550 -> 33552.24 | I550: 33537.73 | J550: =I550-H550 -> -14.51 | K550: =IF(F550=0,0,J550/F550) -> -0.0030690418 | L550: =SUMIFS('Registros manuales'!$D$5:$D$104,'Registros manuales'!$A$5:$A$104,A550,'Registros manuales'!$B$5:$B$104,B550,'Registros manuales'!$C$5:$C$104,C550) -> 0

Sheet Conciliación pipas
A1: Conciliación de compras: Reporte de mermas vs PIPAS DEL MES
A2: Periodo: Agosto 2026 · Generado: 22/09/2026 17:01 · Límite SAT: merma ≤ 0.5% de la venta
A4: Estación | B4: Producto | C4: Compras reporte mermas (L) | D4: Litros PIPAS DEL MES | E4: # Pipas | F4: Diferencia (L) mermas − pipas | G4: Estado | H4: Pipas no registradas | I4: Pipas con desfase | J4: Compras sin pipa | K4: Comentario
A5: ATB | B5: Regular | C5: Sin reporte | D5: =SUMIFS('Detalle pipas'!$G$5:$G$281,'Detalle pipas'!$A$5:$A$281,A5,'Detalle pipas'!$B$5:$B$281,B5,'Detalle pipas'!$M$5:$M$281,"Sí") -> 87211 | E5: =COUNTIFS('Detalle pipas'!$A$5:$A$281,A5,'Detalle pipas'!$B$5:$B$281,B5,'Detalle pipas'!$M$5:$M$281,"Sí") -> 3 | F5: =IF(ISNUMBER(C5),C5-D5,"") | G5: =IF(NOT(ISNUMBER(C5)),"SIN REPORTE",IF(ABS(F5)<=Parámetros!$C$8*MAX(1,E5),"CUADRA","NO CUADRA")) -> SIN REPORTE | H5: =COUNTIFS('Detalle pipas'!$A$5:$A$281,A5,'Detalle pipas'!$B$5:$B$281,B5,'Detalle pipas'!$L$5:$L$281,"NO REGISTRADA*") -> 0 | I5: =COUNTIFS('Detalle pipas'!$A$5:$A$281,A5,'Detalle pipas'!$B$5:$B$281,B5,'Detalle pipas'!$L$5:$L$281,"Registrada con desfase*") -> 0 | J5: =COUNTIFS('Compras sin pipa'!$A$5:$A$5,A5,'Compras sin pipa'!$B$5:$B$5,B5)+COUNTIFS('Registros manuales'!$A$5:$A$104,A5,'Registros manuales'!$B$5:$B$104,B5,'Registros manuales'!$G$5:$G$104,"SIN PIPA*") -> 0 | K5: =IF(COUNTIFS('Detalle pipas'!$A$5:$A$281,A5,'Detalle pipas'!$B$5:$B$281,B5,'Detalle pipas'!$L$5:$L$281,"REGISTRO MANUAL*")>0,"Incluye "&COUNTIFS('Detalle pipas'!$A$5:$A$281,A5,'Detalle pipas'!$B$5:$B$281,B5,'Detalle pipas'!$L$5:$L$281,"REGISTRO MANUAL*")&" registro(s) manual(es) · ","")&IF(G5="SIN REPORTE","Falta el CSV de mermas de esta estación/producto",IF(G5="CUADRA",IF(I5>0,"Cuadra en el mes; hay pipas registradas en otro día (ver Detalle pipas)","Todo en orden"),"Revisar: "&H5&" pipa(s) sin registrar y "&J5&" compra(s) sin pipa"))&IF(COUNTIFS('Detalle pipas'!$A$5:$A$281,A5,'Detalle pipas'!$B$5:$B$281,B5,'Detalle pipas'!$M$5:$M$281,"No")>0," · "&COUNTIFS('Detalle pipas'!$A$5:$A$281,A5,'Detalle pipas'!$B$5:$B$281,B5,'Detalle pipas'!$M$5:$M$281,"No")&" pipa(s) antes del inicio del reporte (no se cuentan)","") -> Falta el CSV de mermas de esta estación/producto
A6: ATB | B6: Premium | C6: Sin reporte | D6: =SUMIFS('Detalle pipas'!$G$5:$G$281,'Detalle pipas'!$A$5:$A$281,A6,'Detalle pipas'!$B$5:$B$281,B6,'Detalle pipas'!$M$5:$M$281,"Sí") -> 10198 | E6: =COUNTIFS('Detalle pipas'!$A$5:$A$281,A6,'Detalle pipas'!$B$5:$B$281,B6,'Detalle pipas'!$M$5:$M$281,"Sí") -> 1 | F6: =IF(ISNUMBER(C6),C6-D6,"") | G6: =IF(NOT(ISNUMBER(C6)),"SIN REPORTE",IF(ABS(F6)<=Parámetros!$C$8*MAX(1,E6),"CUADRA","NO CUADRA")) -> SIN REPORTE | H6: =COUNTIFS('Detalle pipas'!$A$5:$A$281,A6,'Detalle pipas'!$B$5:$B$281,B6,'Detalle pipas'!$L$5:$L$281,"NO REGISTRADA*") -> 0 | I6: =COUNTIFS('Detalle pipas'!$A$5:$A$281,A6,'Detalle pipas'!$B$5:$B$281,B6,'Detalle pipas'!$L$5:$L$281,"Registrada con desfase*") -> 0 | J6: =COUNTIFS('Compras sin pipa'!$A$5:$A$5,A6,'Compras sin pipa'!$B$5:$B$5,B6)+COUNTIFS('Registros manuales'!$A$5:$A$104,A6,'Registros manuales'!$B$5:$B$104,B6,'Registros manuales'!$G$5:$G$104,"SIN PIPA*") -> 0 | K6: =IF(COUNTIFS('Detalle pipas'!$A$5:$A$281,A6,'Detalle pipas'!$B$5:$B$281,B6,'Detalle pipas'!$L$5:$L$281,"REGISTRO MANUAL*")>0,"Incluye "&COUNTIFS('Detalle pipas'!$A$5:$A$281,A6,'Detalle pipas'!$B$5:$B$281,B6,'Detalle pipas'!$L$5:$L$281,"REGISTRO MANUAL*")&" registro(s) manual(es) · ","")&IF(G6="SIN REPORTE","Falta el CSV de mermas de esta estación/producto",IF(G6="CUADRA",IF(I6>0,"Cuadra en el mes; hay pipas registradas en otro día (ver Detalle pipas)","Todo en orden"),"Revisar: "&H6&" pipa(s) sin registrar y "&J6&" compra(s) sin pipa"))&IF(COUNTIFS('Detalle pipas'!$A$5:$A$281,A6,'Detalle pipas'!$B$5:$B$281,B6,'Detalle pipas'!$M$5:$M$281,"No")>0," · "&COUNTIFS('Detalle pipas'!$A$5:$A$281,A6,'Detalle pipas'!$B$5:$B$281,B6,'Detalle pipas'!$M$5:$M$281,"No")&" pipa(s) antes del inicio del reporte (no se cuentan)","") -> Falta el CSV de mermas de esta estación/producto
A7: ATB | B7: Diesel | C7: Sin reporte | D7: =SUMIFS('Detalle pipas'!$G$5:$G$281,'Detalle pipas'!$A$5:$A$281,A7,'Detalle pipas'!$B$5:$B$281,B7,'Detalle pipas'!$M$5:$M$281,"Sí") -> 66767 | E7: =COUNTIFS('Detalle pipas'!$A$5:$A$281,A7,'Detalle pipas'!$B$5:$B$281,B7,'Detalle pipas'!$M$5:$M$281,"Sí") -> 2 | F7: =IF(ISNUMBER(C7),C7-D7,"") | G7: =IF(NOT(ISNUMBER(C7)),"SIN REPORTE",IF(ABS(F7)<=Parámetros!$C$8*MAX(1,E7),"CUADRA","NO CUADRA")) -> SIN REPORTE | H7: =COUNTIFS('Detalle pipas'!$A$5:$A$281,A7,'Detalle pipas'!$B$5:$B$281,B7,'Detalle pipas'!$L$5:$L$281,"NO REGISTRADA*") -> 0 | I7: =COUNTIFS('Detalle pipas'!$A$5:$A$281,A7,'Detalle pipas'!$B$5:$B$281,B7,'Detalle pipas'!$L$5:$L$281,"Registrada con desfase*") -> 0 | J7: =COUNTIFS('Compras sin pipa'!$A$5:$A$5,A7,'Compras sin pipa'!$B$5:$B$5,B7)+COUNTIFS('Registros manuales'!$A$5:$A$104,A7,'Registros manuales'!$B$5:$B$104,B7,'Registros manuales'!$G$5:$G$104,"SIN PIPA*") -> 0 | K7: =IF(COUNTIFS('Detalle pipas'!$A$5:$A$281,A7,'Detalle pipas'!$B$5:$B$281,B7,'Detalle pipas'!$L$5:$L$281,"REGISTRO MANUAL*")>0,"Incluye "&COUNTIFS('Detalle pipas'!$A$5:$A$281,A7,'Detalle pipas'!$B$5:$B$281,B7,'Detalle pipas'!$L$5:$L$281,"REGISTRO MANUAL*")&" registro(s) manual(es) · ","")&IF(G7="SIN REPORTE","Falta el CSV de mermas de esta estación/producto",IF(G7="CUADRA",IF(I7>0,"Cuadra en el mes; hay pipas registradas en otro día (ver Detalle pipas)","Todo en orden"),"Revisar: "&H7&" pipa(s) sin registrar y "&J7&" compra(s) sin pipa"))&IF(COUNTIFS('Detalle pipas'!$A$5:$A$281,A7,'Detalle pipas'!$B$5:$B$281,B7,'Detalle pipas'!$M$5:$M$281,"No")>0," · "&COUNTIFS('Detalle pipas'!$A$5:$A$281,A7,'Detalle pipas'!$B$5:$B$281,B7,'Detalle pipas'!$M$5:$M$281,"No")&" pipa(s) antes del inicio del reporte (no se cuentan)","") -> Falta el CSV de mermas de esta estación/producto
A8: ATP | B8: Regular | C8: Sin reporte | D8: =SUMIFS('Detalle pipas'!$G$5:$G$281,'Detalle pipas'!$A$5:$A$281,A8,'Detalle pipas'!$B$5:$B$281,B8,'Detalle pipas'!$M$5:$M$281,"Sí") -> 147203 | E8: =COUNTIFS('Detalle pipas'!$A$5:$A$281,A8,'Detalle pipas'!$B$5:$B$281,B8,'Detalle pipas'!$M$5:$M$281,"Sí") -> 5 | F8: =IF(ISNUMBER(C8),C8-D8,"") | G8: =IF(NOT(ISNUMBER(C8)),"SIN REPORTE",IF(ABS(F8)<=Parámetros!$C$8*MAX(1,E8),"CUADRA","NO CUADRA")) -> SIN REPORTE | H8: =COUNTIFS('Detalle pipas'!$A$5:$A$281,A8,'Detalle pipas'!$B$5:$B$281,B8,'Detalle pipas'!$L$5:$L$281,"NO REGISTRADA*") -> 0 | I8: =COUNTIFS('Detalle pipas'!$A$5:$A$281,A8,'Detalle pipas'!$B$5:$B$281,B8,'Detalle pipas'!$L$5:$L$281,"Registrada con desfase*") -> 0 | J8: =COUNTIFS('Compras sin pipa'!$A$5:$A$5,A8,'Compras sin pipa'!$B$5:$B$5,B8)+COUNTIFS('Registros manuales'!$A$5:$A$104,A8,'Registros manuales'!$B$5:$B$104,B8,'Registros manuales'!$G$5:$G$104,"SIN PIPA*") -> 0 | K8: =IF(COUNTIFS('Detalle pipas'!$A$5:$A$281,A8,'Detalle pipas'!$B$5:$B$281,B8,'Detalle pipas'!$L$5:$L$281,"REGISTRO MANUAL*")>0,"Incluye "&COUNTIFS('Detalle pipas'!$A$5:$A$281,A8,'Detalle pipas'!$B$5:$B$281,B8,'Detalle pipas'!$L$5:$L$281,"REGISTRO MANUAL*")&" registro(s) manual(es) · ","")&IF(G8="SIN REPORTE","Falta el CSV de mermas de esta estación/producto",IF(G8="CUADRA",IF(I8>0,"Cuadra en el mes; hay pipas registradas en otro día (ver Detalle pipas)","Todo en orden"),"Revisar: "&H8&" pipa(s) sin registrar y "&J8&" compra(s) sin pipa"))&IF(COUNTIFS('Detalle pipas'!$A$5:$A$281,A8,'Detalle pipas'!$B$5:$B$281,B8,'Detalle pipas'!$M$5:$M$281,"No")>0," · "&COUNTIFS('Detalle pipas'!$A$5:$A$281,A8,'Detalle pipas'!$B$5:$B$281,B8,'Detalle pipas'!$M$5:$M$281,"No")&" pipa(s) antes del inicio del reporte (no se cuentan)","") -> Falta el CSV de mermas de esta estación/producto
A9: ATP | B9: Premium | C9: Sin reporte | D9: =SUMIFS('Detalle pipas'!$G$5:$G$281,'Detalle pipas'!$A$5:$A$281,A9,'Detalle pipas'!$B$5:$B$281,B9,'Detalle pipas'!$M$5:$M$281,"Sí") -> 10139 | E9: =COUNTIFS('Detalle pipas'!$A$5:$A$281,A9,'Detalle pipas'!$B$5:$B$281,B9,'Detalle pipas'!$M$5:$M$281,"Sí") -> 1 | F9: =IF(ISNUMBER(C9),C9-D9,"") | G9: =IF(NOT(ISNUMBER(C9)),"SIN REPORTE",IF(ABS(F9)<=Parámetros!$C$8*MAX(1,E9),"CUADRA","NO CUADRA")) -> SIN REPORTE | H9: =COUNTIFS('Detalle pipas'!$A$5:$A$281,A9,'Detalle pipas'!$B$5:$B$281,B9,'Detalle pipas'!$L$5:$L$281,"NO REGISTRADA*") -> 0 | I9: =COUNTIFS('Detalle pipas'!$A$5:$A$281,A9,'Detalle pipas'!$B$5:$B$281,B9,'Detalle pipas'!$L$5:$L$281,"Registrada con desfase*") -> 0 | J9: =COUNTIFS('Compras sin pipa'!$A$5:$A$5,A9,'Compras sin pipa'!$B$5:$B$5,B9)+COUNTIFS('Registros manuales'!$A$5:$A$104,A9,'Registros manuales'!$B$5:$B$104,B9,'Registros manuales'!$G$5:$G$104,"SIN PIPA*") -> 0 | K9: =IF(COUNTIFS('Detalle pipas'!$A$5:$A$281,A9,'Detalle pipas'!$B$5:$B$281,B9,'Detalle pipas'!$L$5:$L$281,"REGISTRO MANUAL*")>0,"Incluye "&COUNTIFS('Detalle pipas'!$A$5:$A$281,A9,'Detalle pipas'!$B$5:$B$281,B9,'Detalle pipas'!$L$5:$L$281,"REGISTRO MANUAL*")&" registro(s) manual(es) · ","")&IF(G9="SIN REPORTE","Falta el CSV de mermas de esta estación/producto",IF(G9="CUADRA",IF(I9>0,"Cuadra en el mes; hay pipas registradas en otro día (ver Detalle pipas)","Todo en orden"),"Revisar: "&H9&" pipa(s) sin registrar y "&J9&" compra(s) sin pipa"))&IF(COUNTIFS('Detalle pipas'!$A$5:$A$281,A9,'Detalle pipas'!$B$5:$B$281,B9,'Detalle pipas'!$M$5:$M$281,"No")>0," · "&COUNTIFS('Detalle pipas'!$A$5:$A$281,A9,'Detalle pipas'!$B$5:$B$281,B9,'Detalle pipas'!$M$5:$M$281,"No")&" pipa(s) antes del inicio del reporte (no se cuentan)","") -> Falta el CSV de mermas de esta estación/producto
A10: ATP | B10: Diesel | C10: Sin reporte | D10: =SUMIFS('Detalle pipas'!$G$5:$G$281,'Detalle pipas'!$A$5:$A$281,A10,'Detalle pipas'!$B$5:$B$281,B10,'Detalle pipas'!$M$5:$M$281,"Sí") -> 67038 | E10: =COUNTIFS('Detalle pipas'!$A$5:$A$281,A10,'Detalle pipas'!$B$5:$B$281,B10,'Detalle pipas'!$M$5:$M$281,"Sí") -> 2 | F10: =IF(ISNUMBER(C10),C10-D10,"") | G10: =IF(NOT(ISNUMBER(C10)),"SIN REPORTE",IF(ABS(F10)<=Parámetros!$C$8*MAX(1,E10),"CUADRA","NO CUADRA")) -> SIN REPORTE | H10: =COUNTIFS('Detalle pipas'!$A$5:$A$281,A10,'Detalle pipas'!$B$5:$B$281,B10,'Detalle pipas'!$L$5:$L$281,"NO REGISTRADA*") -> 0 | I10: =COUNTIFS('Detalle pipas'!$A$5:$A$281,A10,'Detalle pipas'!$B$5:$B$281,B10,'Detalle pipas'!$L$5:$L$281,"Registrada con desfase*") -> 0 | J10: =COUNTIFS('Compras sin pipa'!$A$5:$A$5,A10,'Compras sin pipa'!$B$5:$B$5,B10)+COUNTIFS('Registros manuales'!$A$5:$A$104,A10,'Registros manuales'!$B$5:$B$104,B10,'Registros manuales'!$G$5:$G$104,"SIN PIPA*") -> 0 | K10: =IF(COUNTIFS('Detalle pipas'!$A$5:$A$281,A10,'Detalle pipas'!$B$5:$B$281,B10,'Detalle pipas'!$L$5:$L$281,"REGISTRO MANUAL*")>0,"Incluye "&COUNTIFS('Detalle pipas'!$A$5:$A$281,A10,'Detalle pipas'!$B$5:$B$281,B10,'Detalle pipas'!$L$5:$L$281,"REGISTRO MANUAL*")&" registro(s) manual(es) · ","")&IF(G10="SIN REPORTE","Falta el CSV de mermas de esta estación/producto",IF(G10="CUADRA",IF(I10>0,"Cuadra en el mes; hay pipas registradas en otro día (ver Detalle pipas)","Todo en orden"),"Revisar: "&H10&" pipa(s) sin registrar y "&J10&" compra(s) sin pipa"))&IF(COUNTIFS('Detalle pipas'!$A$5:$A$281,A10,'Detalle pipas'!$B$5:$B$281,B10,'Detalle pipas'!$M$5:$M$281,"No")>0," · "&COUNTIFS('Detalle pipas'!$A$5:$A$281,A10,'Detalle pipas'!$B$5:$B$281,B10,'Detalle pipas'!$M$5:$M$281,"No")&" pipa(s) antes del inicio del reporte (no se cuentan)","") -> Falta el CSV de mermas de esta estación/producto
A11: AVE FENIX | B11: Regular | C11: Sin reporte | D11: =SUMIFS('Detalle pipas'!$G$5:$G$281,'Detalle pipas'!$A$5:$A$281,A11,'Detalle pipas'!$B$5:$B$281,B11,'Detalle pipas'!$M$5:$M$281,"Sí") -> 342901 | E11: =COUNTIFS('Detalle pipas'!$A$5:$A$281,A11,'Detalle pipas'!$B$5:$B$281,B11,'Detalle pipas'!$M$5:$M$281,"Sí") -> 11 | F11: =IF(ISNUMBER(C11),C11-D11,"") | G11: =IF(NOT(ISNUMBER(C11)),"SIN REPORTE",IF(ABS(F11)<=Parámetros!$C$8*MAX(1,E11),"CUADRA","NO CUADRA")) -> SIN REPORTE | H11: =COUNTIFS('Detalle pipas'!$A$5:$A$281,A11,'Detalle pipas'!$B$5:$B$281,B11,'Detalle pipas'!$L$5:$L$281,"NO REGISTRADA*") -> 0 | I11: =COUNTIFS('Detalle pipas'!$A$5:$A$281,A11,'Detalle pipas'!$B$5:$B$281,B11,'Detalle pipas'!$L$5:$L$281,"Registrada con desfase*") -> 0 | J11: =COUNTIFS('Compras sin pipa'!$A$5:$A$5,A11,'Compras sin pipa'!$B$5:$B$5,B11)+COUNTIFS('Registros manuales'!$A$5:$A$104,A11,'Registros manuales'!$B$5:$B$104,B11,'Registros manuales'!$G$5:$G$104,"SIN PIPA*") -> 0 | K11: =IF(COUNTIFS('Detalle pipas'!$A$5:$A$281,A11,'Detalle pipas'!$B$5:$B$281,B11,'Detalle pipas'!$L$5:$L$281,"REGISTRO MANUAL*")>0,"Incluye "&COUNTIFS('Detalle pipas'!$A$5:$A$281,A11,'Detalle pipas'!$B$5:$B$281,B11,'Detalle pipas'!$L$5:$L$281,"REGISTRO MANUAL*")&" registro(s) manual(es) · ","")&IF(G11="SIN REPORTE","Falta el CSV de mermas de esta estación/producto",IF(G11="CUADRA",IF(I11>0,"Cuadra en el mes; hay pipas registradas en otro día (ver Detalle pipas)","Todo en orden"),"Revisar: "&H11&" pipa(s) sin registrar y "&J11&" compra(s) sin pipa"))&IF(COUNTIFS('Detalle pipas'!$A$5:$A$281,A11,'Detalle pipas'!$B$5:$B$281,B11,'Detalle pipas'!$M$5:$M$281,"No")>0," · "&COUNTIFS('Detalle pipas'!$A$5:$A$281,A11,'Detalle pipas'!$B$5:$B$281,B11,'Detalle pipas'!$M$5:$M$281,"No")&" pipa(s) antes del inicio del reporte (no se cuentan)","") -> Falta el CSV de mermas de esta estación/producto
A12: AVE FENIX | B12: Premium | C12: Sin reporte | D12: =SUMIFS('Detalle pipas'!$G$5:$G$281,'Detalle pipas'!$A$5:$A$281,A12,'Detalle pipas'!$B$5:$B$281,B12,'Detalle pipas'!$M$5:$M$281,"Sí") -> 124189 | E12: =COUNTIFS('Detalle pipas'!$A$5:$A$281,A12,'Detalle pipas'!$B$5:$B$281,B12,'Detalle pipas'!$M$5:$M$281,"Sí") -> 4 | F12: =IF(ISNUMBER(C12),C12-D12,"") | G12: =IF(NOT(ISNUMBER(C12)),"SIN REPORTE",IF(ABS(F12)<=Parámetros!$C$8*MAX(1,E12),"CUADRA","NO CUADRA")) -> SIN REPORTE | H12: =COUNTIFS('Detalle pipas'!$A$5:$A$281,A12,'Detalle pipas'!$B$5:$B$281,B12,'Detalle pipas'!$L$5:$L$281,"NO REGISTRADA*") -> 0 | I12: =COUNTIFS('Detalle pipas'!$A$5:$A$281,A12,'Detalle pipas'!$B$5:$B$281,B12,'Detalle pipas'!$L$5:$L$281,"Registrada con desfase*") -> 0 | J12: =COUNTIFS('Compras sin pipa'!$A$5:$A$5,A12,'Compras sin pipa'!$B$5:$B$5,B12)+COUNTIFS('Registros manuales'!$A$5:$A$104,A12,'Registros manuales'!$B$5:$B$104,B12,'Registros manuales'!$G$5:$G$104,"SIN PIPA*") -> 0 | K12: =IF(COUNTIFS('Detalle pipas'!$A$5:$A$281,A12,'Detalle pipas'!$B$5:$B$281,B12,'Detalle pipas'!$L$5:$L$281,"REGISTRO MANUAL*")>0,"Incluye "&COUNTIFS('Detalle pipas'!$A$5:$A$281,A12,'Detalle pipas'!$B$5:$B$281,B12,'Detalle pipas'!$L$5:$L$281,"REGISTRO MANUAL*")&" registro(s) manual(es) · ","")&IF(G12="SIN REPORTE","Falta el CSV de mermas de esta estación/producto",IF(G12="CUADRA",IF(I12>0,"Cuadra en el mes; hay pipas registradas en otro día (ver Detalle pipas)","Todo en orden"),"Revisar: "&H12&" pipa(s) sin registrar y "&J12&" compra(s) sin pipa"))&IF(COUNTIFS('Detalle pipas'!$A$5:$A$281,A12,'Detalle pipas'!$B$5:$B$281,B12,'Detalle pipas'!$M$5:$M$281,"No")>0," · "&COUNTIFS('Detalle pipas'!$A$5:$A$281,A12,'Detalle pipas'!$B$5:$B$281,B12,'Detalle pipas'!$M$5:$M$281,"No")&" pipa(s) antes del inicio del reporte (no se cuentan)","") -> Falta el CSV de mermas de esta estación/producto
A13: AVE FENIX | B13: Diesel | C13: Sin reporte | D13: =SUMIFS('Detalle pipas'!$G$5:$G$281,'Detalle pipas'!$A$5:$A$281,A13,'Detalle pipas'!$B$5:$B$281,B13,'Detalle pipas'!$M$5:$M$281,"Sí") -> 188295 | E13: =COUNTIFS('Detalle pipas'!$A$5:$A$281,A13,'Detalle pipas'!$B$5:$B$281,B13,'Detalle pipas'!$M$5:$M$281,"Sí") -> 6 | F13: =IF(ISNUMBER(C13),C13-D13,"") | G13: =IF(NOT(ISNUMBER(C13)),"SIN REPORTE",IF(ABS(F13)<=Parámetros!$C$8*MAX(1,E13),"CUADRA","NO CUADRA")) -> SIN REPORTE | H13: =COUNTIFS('Detalle pipas'!$A$5:$A$281,A13,'Detalle pipas'!$B$5:$B$281,B13,'Detalle pipas'!$L$5:$L$281,"NO REGISTRADA*") -> 0 | I13: =COUNTIFS('Detalle pipas'!$A$5:$A$281,A13,'Detalle pipas'!$B$5:$B$281,B13,'Detalle pipas'!$L$5:$L$281,"Registrada con desfase*") -> 0 | J13: =COUNTIFS('Compras sin pipa'!$A$5:$A$5,A13,'Compras sin pipa'!$B$5:$B$5,B13)+COUNTIFS('Registros manuales'!$A$5:$A$104,A13,'Registros manuales'!$B$5:$B$104,B13,'Registros manuales'!$G$5:$G$104,"SIN PIPA*") -> 0 | K13: =IF(COUNTIFS('Detalle pipas'!$A$5:$A$281,A13,'Detalle pipas'!$B$5:$B$281,B13,'Detalle pipas'!$L$5:$L$281,"REGISTRO MANUAL*")>0,"Incluye "&COUNTIFS('Detalle pipas'!$A$5:$A$281,A13,'Detalle pipas'!$B$5:$B$281,B13,'Detalle pipas'!$L$5:$L$281,"REGISTRO MANUAL*")&" registro(s) manual(es) · ","")&IF(G13="SIN REPORTE","Falta el CSV de mermas de esta estación/producto",IF(G13="CUADRA",IF(I13>0,"Cuadra en el mes; hay pipas registradas en otro día (ver Detalle pipas)","Todo en orden"),"Revisar: "&H13&" pipa(s) sin registrar y "&J13&" compra(s) sin pipa"))&IF(COUNTIFS('Detalle pipas'!$A$5:$A$281,A13,'Detalle pipas'!$B$5:$B$281,B13,'Detalle pipas'!$M$5:$M$281,"No")>0," · "&COUNTIFS('Detalle pipas'!$A$5:$A$281,A13,'Detalle pipas'!$B$5:$B$281,B13,'Detalle pipas'!$M$5:$M$281,"No")&" pipa(s) antes del inicio del reporte (no se cuentan)","") -> Falta el CSV de mermas de esta estación/producto
A14: AURORA | B14: Regular | C14: ='Mermas mensual'!D5 -> 643188 | D14: =SUMIFS('Detalle pipas'!$G$5:$G$281,'Detalle pipas'!$A$5:$A$281,A14,'Detalle pipas'!$B$5:$B$281,B14,'Detalle pipas'!$M$5:$M$281,"Sí") -> 676653 | E14: =COUNTIFS('Detalle pipas'!$A$5:$A$281,A14,'Detalle pipas'!$B$5:$B$281,B14,'Detalle pipas'!$M$5:$M$281,"Sí") -> 20 | F14: =IF(ISNUMBER(C14),C14-D14,"") -> -33465 | G14: =IF(NOT(ISNUMBER(C14)),"SIN REPORTE",IF(ABS(F14)<=Parámetros!$C$8*MAX(1,E14),"CUADRA","NO CUADRA")) -> NO CUADRA | H14: =COUNTIFS('Detalle pipas'!$A$5:$A$281,A14,'Detalle pipas'!$B$5:$B$281,B14,'Detalle pipas'!$L$5:$L$281,"NO REGISTRADA*") -> 1 | I14: =COUNTIFS('Detalle pipas'!$A$5:$A$281,A14,'Detalle pipas'!$B$5:$B$281,B14,'Detalle pipas'!$L$5:$L$281,"Registrada con desfase*") -> 7 | J14: =COUNTIFS('Compras sin pipa'!$A$5:$A$5,A14,'Compras sin pipa'!$B$5:$B$5,B14)+COUNTIFS('Registros manuales'!$A$5:$A$104,A14,'Registros manuales'!$B$5:$B$104,B14,'Registros manuales'!$G$5:$G$104,"SIN PIPA*") -> 0 | K14: =IF(COUNTIFS('Detalle pipas'!$A$5:$A$281,A14,'Detalle pipas'!$B$5:$B$281,B14,'Detalle pipas'!$L$5:$L$281,"REGISTRO MANUAL*")>0,"Incluye "&COUNTIFS('Detalle pipas'!$A$5:$A$281,A14,'Detalle pipas'!$B$5:$B$281,B14,'Detalle pipas'!$L$5:$L$281,"REGISTRO MANUAL*")&" registro(s) manual(es) · ","")&IF(G14="SIN REPORTE","Falta el CSV de mermas de esta estación/producto",IF(G14="CUADRA",IF(I14>0,"Cuadra en el mes; hay pipas registradas en otro día (ver Detalle pipas)","Todo en orden"),"Revisar: "&H14&" pipa(s) sin registrar y "&J14&" compra(s) sin pipa"))&IF(COUNTIFS('Detalle pipas'!$A$5:$A$281,A14,'Detalle pipas'!$B$5:$B$281,B14,'Detalle pipas'!$M$5:$M$281,"No")>0," · "&COUNTIFS('Detalle pipas'!$A$5:$A$281,A14,'Detalle pipas'!$B$5:$B$281,B14,'Detalle pipas'!$M$5:$M$281,"No")&" pipa(s) antes del inicio del reporte (no se cuentan)","") -> Revisar: 1 pipa(s) sin registrar y 0 compra(s) sin pipa
A15: AURORA | B15: Premium | C15: ='Mermas mensual'!D6 -> 72049 | D15: =SUMIFS('Detalle pipas'!$G$5:$G$281,'Detalle pipas'!$A$5:$A$281,A15,'Detalle pipas'!$B$5:$B$281,B15,'Detalle pipas'!$M$5:$M$281,"Sí") -> 72049 | E15: =COUNTIFS('Detalle pipas'!$A$5:$A$281,A15,'Detalle pipas'!$B$5:$B$281,B15,'Detalle pipas'!$M$5:$M$281,"Sí") -> 2 | F15: =IF(ISNUMBER(C15),C15-D15,"") -> 0 | G15: =IF(NOT(ISNUMBER(C15)),"SIN REPORTE",IF(ABS(F15)<=Parámetros!$C$8*MAX(1,E15),"CUADRA","NO CUADRA")) -> CUADRA | H15: =COUNTIFS('Detalle pipas'!$A$5:$A$281,A15,'Detalle pipas'!$B$5:$B$281,B15,'Detalle pipas'!$L$5:$L$281,"NO REGISTRADA*") -> 0 | I15: =COUNTIFS('Detalle pipas'!$A$5:$A$281,A15,'Detalle pipas'!$B$5:$B$281,B15,'Detalle pipas'!$L$5:$L$281,"Registrada con desfase*") -> 2 | J15: =COUNTIFS('Compras sin pipa'!$A$5:$A$5,A15,'Compras sin pipa'!$B$5:$B$5,B15)+COUNTIFS('Registros manuales'!$A$5:$A$104,A15,'Registros manuales'!$B$5:$B$104,B15,'Registros manuales'!$G$5:$G$104,"SIN PIPA*") -> 0 | K15: =IF(COUNTIFS('Detalle pipas'!$A$5:$A$281,A15,'Detalle pipas'!$B$5:$B$281,B15,'Detalle pipas'!$L$5:$L$281,"REGISTRO MANUAL*")>0,"Incluye "&COUNTIFS('Detalle pipas'!$A$5:$A$281,A15,'Detalle pipas'!$B$5:$B$281,B15,'Detalle pipas'!$L$5:$L$281,"REGISTRO MANUAL*")&" registro(s) manual(es) · ","")&IF(G15="SIN REPORTE","Falta el CSV de mermas de esta estación/producto",IF(G15="CUADRA",IF(I15>0,"Cuadra en el mes; hay pipas registradas en otro día (ver Detalle pipas)","Todo en orden"),"Revisar: "&H15&" pipa(s) sin registrar y "&J15&" compra(s) sin pipa"))&IF(COUNTIFS('Detalle pipas'!$A$5:$A$281,A15,'Detalle pipas'!$B$5:$B$281,B15,'Detalle pipas'!$M$5:$M$281,"No")>0," · "&COUNTIFS('Detalle pipas'!$A$5:$A$281,A15,'Detalle pipas'!$B$5:$B$281,B15,'Detalle pipas'!$M$5:$M$281,"No")&" pipa(s) antes del inicio del reporte (no se cuentan)","") -> Cuadra en el mes; hay pipas registradas en otro día (ver Detalle pipas)
A16: AURORA | B16: Diesel | C16: ='Mermas mensual'!D7 -> 287001 | D16: =SUMIFS('Detalle pipas'!$G$5:$G$281,'Detalle pipas'!$A$5:$A$281,A16,'Detalle pipas'!$B$5:$B$281,B16,'Detalle pipas'!$M$5:$M$281,"Sí") -> 287001 | E16: =COUNTIFS('Detalle pipas'!$A$5:$A$281,A16,'Detalle pipas'!$B$5:$B$281,B16,'Detalle pipas'!$M$5:$M$281,"Sí") -> 8 | F16: =IF(ISNUMBER(C16),C16-D16,"") -> 0 | G16: =IF(NOT(ISNUMBER(C16)),"SIN REPORTE",IF(ABS(F16)<=Parámetros!$C$8*MAX(1,E16),"CUADRA","NO CUADRA")) -> CUADRA | H16: =COUNTIFS('Detalle pipas'!$A$5:$A$281,A16,'Detalle pipas'!$B$5:$B$281,B16,'Detalle pipas'!$L$5:$L$281,"NO REGISTRADA*") -> 0 | I16: =COUNTIFS('Detalle pipas'!$A$5:$A$281,A16,'Detalle pipas'!$B$5:$B$281,B16,'Detalle pipas'!$L$5:$L$281,"Registrada con desfase*") -> 3 | J16: =COUNTIFS('Compras sin pipa'!$A$5:$A$5,A16,'Compras sin pipa'!$B$5:$B$5,B16)+COUNTIFS('Registros manuales'!$A$5:$A$104,A16,'Registros manuales'!$B$5:$B$104,B16,'Registros manuales'!$G$5:$G$104,"SIN PIPA*") -> 0 | K16: =IF(COUNTIFS('Detalle pipas'!$A$5:$A$281,A16,'Detalle pipas'!$B$5:$B$281,B16,'Detalle pipas'!$L$5:$L$281,"REGISTRO MANUAL*")>0,"Incluye "&COUNTIFS('Detalle pipas'!$A$5:$A$281,A16,'Detalle pipas'!$B$5:$B$281,B16,'Detalle pipas'!$L$5:$L$281,"REGISTRO MANUAL*")&" registro(s) manual(es) · ","")&IF(G16="SIN REPORTE","Falta el CSV de mermas de esta estación/producto",IF(G16="CUADRA",IF(I16>0,"Cuadra en el mes; hay pipas registradas en otro día (ver Detalle pipas)","Todo en orden"),"Revisar: "&H16&" pipa(s) sin registrar y "&J16&" compra(s) sin pipa"))&IF(COUNTIFS('Detalle pipas'!$A$5:$A$281,A16,'Detalle pipas'!$B$5:$B$281,B16,'Detalle pipas'!$M$5:$M$281,"No")>0," · "&COUNTIFS('Detalle pipas'!$A$5:$A$281,A16,'Detalle pipas'!$B$5:$B$281,B16,'Detalle pipas'!$M$5:$M$281,"No")&" pipa(s) antes del inicio del reporte (no se cuentan)","") -> Cuadra en el mes; hay pipas registradas en otro día (ver Detalle pipas)
A17: COMBULUB | B17: Regular | C17: Sin reporte | D17: =SUMIFS('Detalle pipas'!$G$5:$G$281,'Detalle pipas'!$A$5:$A$281,A17,'Detalle pipas'!$B$5:$B$281,B17,'Detalle pipas'!$M$5:$M$281,"Sí") -> 79772 | E17: =COUNTIFS('Detalle pipas'!$A$5:$A$281,A17,'Detalle pipas'!$B$5:$B$281,B17,'Detalle pipas'!$M$5:$M$281,"Sí") -> 4 | F17: =IF(ISNUMBER(C17),C17-D17,"") | G17: =IF(NOT(ISNUMBER(C17)),"SIN REPORTE",IF(ABS(F17)<=Parámetros!$C$8*MAX(1,E17),"CUADRA","NO CUADRA")) -> SIN REPORTE | H17: =COUNTIFS('Detalle pipas'!$A$5:$A$281,A17,'Detalle pipas'!$B$5:$B$281,B17,'Detalle pipas'!$L$5:$L$281,"NO REGISTRADA*") -> 0 | I17: =COUNTIFS('Detalle pipas'!$A$5:$A$281,A17,'Detalle pipas'!$B$5:$B$281,B17,'Detalle pipas'!$L$5:$L$281,"Registrada con desfase*") -> 0 | J17: =COUNTIFS('Compras sin pipa'!$A$5:$A$5,A17,'Compras sin pipa'!$B$5:$B$5,B17)+COUNTIFS('Registros manuales'!$A$5:$A$104,A17,'Registros manuales'!$B$5:$B$104,B17,'Registros manuales'!$G$5:$G$104,"SIN PIPA*") -> 0 | K17: =IF(COUNTIFS('Detalle pipas'!$A$5:$A$281,A17,'Detalle pipas'!$B$5:$B$281,B17,'Detalle pipas'!$L$5:$L$281,"REGISTRO MANUAL*")>0,"Incluye "&COUNTIFS('Detalle pipas'!$A$5:$A$281,A17,'Detalle pipas'!$B$5:$B$281,B17,'Detalle pipas'!$L$5:$L$281,"REGISTRO MANUAL*")&" registro(s) manual(es) · ","")&IF(G17="SIN REPORTE","Falta el CSV de mermas de esta estación/producto",IF(G17="CUADRA",IF(I17>0,"Cuadra en el mes; hay pipas registradas en otro día (ver Detalle pipas)","Todo en orden"),"Revisar: "&H17&" pipa(s) sin registrar y "&J17&" compra(s) sin pipa"))&IF(COUNTIFS('Detalle pipas'!$A$5:$A$281,A17,'Detalle pipas'!$B$5:$B$281,B17,'Detalle pipas'!$M$5:$M$281,"No")>0," · "&COUNTIFS('Detalle pipas'!$A$5:$A$281,A17,'Detalle pipas'!$B$5:$B$281,B17,'Detalle pipas'!$M$5:$M$281,"No")&" pipa(s) antes del inicio del reporte (no se cuentan)","") -> Falta el CSV de mermas de esta estación/producto
A18: COMBULUB | B18: Premium | C18: Sin reporte | D18: =SUMIFS('Detalle pipas'!$G$5:$G$281,'Detalle pipas'!$A$5:$A$281,A18,'Detalle pipas'!$B$5:$B$281,B18,'Detalle pipas'!$M$5:$M$281,"Sí") -> 10087 | E18: =COUNTIFS('Detalle pipas'!$A$5:$A$281,A18,'Detalle pipas'!$B$5:$B$281,B18,'Detalle pipas'!$M$5:$M$281,"Sí") -> 1 | F18: =IF(ISNUMBER(C18),C18-D18,"") | G18: =IF(NOT(ISNUMBER(C18)),"SIN REPORTE",IF(ABS(F18)<=Parámetros!$C$8*MAX(1,E18),"CUADRA","NO CUADRA")) -> SIN REPORTE | H18: =COUNTIFS('Detalle pipas'!$A$5:$A$281,A18,'Detalle pipas'!$B$5:$B$281,B18,'Detalle pipas'!$L$5:$L$281,"NO REGISTRADA*") -> 0 | I18: =COUNTIFS('Detalle pipas'!$A$5:$A$281,A18,'Detalle pipas'!$B$5:$B$281,B18,'Detalle pipas'!$L$5:$L$281,"Registrada con desfase*") -> 0 | J18: =COUNTIFS('Compras sin pipa'!$A$5:$A$5,A18,'Compras sin pipa'!$B$5:$B$5,B18)+COUNTIFS('Registros manuales'!$A$5:$A$104,A18,'Registros manuales'!$B$5:$B$104,B18,'Registros manuales'!$G$5:$G$104,"SIN PIPA*") -> 0 | K18: =IF(COUNTIFS('Detalle pipas'!$A$5:$A$281,A18,'Detalle pipas'!$B$5:$B$281,B18,'Detalle pipas'!$L$5:$L$281,"REGISTRO MANUAL*")>0,"Incluye "&COUNTIFS('Detalle pipas'!$A$5:$A$281,A18,'Detalle pipas'!$B$5:$B$281,B18,'Detalle pipas'!$L$5:$L$281,"REGISTRO MANUAL*")&" registro(s) manual(es) · ","")&IF(G18="SIN REPORTE","Falta el CSV de mermas de esta estación/producto",IF(G18="CUADRA",IF(I18>0,"Cuadra en el mes; hay pipas registradas en otro día (ver Detalle pipas)","Todo en orden"),"Revisar: "&H18&" pipa(s) sin registrar y "&J18&" compra(s) sin pipa"))&IF(COUNTIFS('Detalle pipas'!$A$5:$A$281,A18,'Detalle pipas'!$B$5:$B$281,B18,'Detalle pipas'!$M$5:$M$281,"No")>0," · "&COUNTIFS('Detalle pipas'!$A$5:$A$281,A18,'Detalle pipas'!$B$5:$B$281,B18,'Detalle pipas'!$M$5:$M$281,"No")&" pipa(s) antes del inicio del reporte (no se cuentan)","") -> Falta el CSV de mermas de esta estación/producto
A19: COMBULUB | B19: Diesel | C19: Sin reporte | D19: =SUMIFS('Detalle pipas'!$G$5:$G$281,'Detalle pipas'!$A$5:$A$281,A19,'Detalle pipas'!$B$5:$B$281,B19,'Detalle pipas'!$M$5:$M$281,"Sí") -> 89916 | E19: =COUNTIFS('Detalle pipas'!$A$5:$A$281,A19,'Detalle pipas'!$B$5:$B$281,B19,'Detalle pipas'!$M$5:$M$281,"Sí") -> 4 | F19: =IF(ISNUMBER(C19),C19-D19,"") | G19: =IF(NOT(ISNUMBER(C19)),"SIN REPORTE",IF(ABS(F19)<=Parámetros!$C$8*MAX(1,E19),"CUADRA","NO CUADRA")) -> SIN REPORTE | H19: =COUNTIFS('Detalle pipas'!$A$5:$A$281,A19,'Detalle pipas'!$B$5:$B$281,B19,'Detalle pipas'!$L$5:$L$281,"NO REGISTRADA*") -> 0 | I19: =COUNTIFS('Detalle pipas'!$A$5:$A$281,A19,'Detalle pipas'!$B$5:$B$281,B19,'Detalle pipas'!$L$5:$L$281,"Registrada con desfase*") -> 0 | J19: =COUNTIFS('Compras sin pipa'!$A$5:$A$5,A19,'Compras sin pipa'!$B$5:$B$5,B19)+COUNTIFS('Registros manuales'!$A$5:$A$104,A19,'Registros manuales'!$B$5:$B$104,B19,'Registros manuales'!$G$5:$G$104,"SIN PIPA*") -> 0 | K19: =IF(COUNTIFS('Detalle pipas'!$A$5:$A$281,A19,'Detalle pipas'!$B$5:$B$281,B19,'Detalle pipas'!$L$5:$L$281,"REGISTRO MANUAL*")>0,"Incluye "&COUNTIFS('Detalle pipas'!$A$5:$A$281,A19,'Detalle pipas'!$B$5:$B$281,B19,'Detalle pipas'!$L$5:$L$281,"REGISTRO MANUAL*")&" registro(s) manual(es) · ","")&IF(G19="SIN REPORTE","Falta el CSV de mermas de esta estación/producto",IF(G19="CUADRA",IF(I19>0,"Cuadra en el mes; hay pipas registradas en otro día (ver Detalle pipas)","Todo en orden"),"Revisar: "&H19&" pipa(s) sin registrar y "&J19&" compra(s) sin pipa"))&IF(COUNTIFS('Detalle pipas'!$A$5:$A$281,A19,'Detalle pipas'!$B$5:$B$281,B19,'Detalle pipas'!$M$5:$M$281,"No")>0," · "&COUNTIFS('Detalle pipas'!$A$5:$A$281,A19,'Detalle pipas'!$B$5:$B$281,B19,'Detalle pipas'!$M$5:$M$281,"No")&" pipa(s) antes del inicio del reporte (no se cuentan)","") -> Falta el CSV de mermas de esta estación/producto
A20: HUEHUETOCA | B20: Regular | C20: ='Mermas mensual'!D8 -> 512270 | D20: =SUMIFS('Detalle pipas'!$G$5:$G$281,'Detalle pipas'!$A$5:$A$281,A20,'Detalle pipas'!$B$5:$B$281,B20,'Detalle pipas'!$M$5:$M$281,"Sí") -> 512270 | E20: =COUNTIFS('Detalle pipas'!$A$5:$A$281,A20,'Detalle pipas'!$B$5:$B$281,B20,'Detalle pipas'!$M$5:$M$281,"Sí") -> 17 | F20: =IF(ISNUMBER(C20),C20-D20,"") -> 0 | G20: =IF(NOT(ISNUMBER(C20)),"SIN REPORTE",IF(ABS(F20)<=Parámetros!$C$8*MAX(1,E20),"CUADRA","NO CUADRA")) -> CUADRA | H20: =COUNTIFS('Detalle pipas'!$A$5:$A$281,A20,'Detalle pipas'!$B$5:$B$281,B20,'Detalle pipas'!$L$5:$L$281,"NO REGISTRADA*") -> 0 | I20: =COUNTIFS('Detalle pipas'!$A$5:$A$281,A20,'Detalle pipas'!$B$5:$B$281,B20,'Detalle pipas'!$L$5:$L$281,"Registrada con desfase*") -> 2 | J20: =COUNTIFS('Compras sin pipa'!$A$5:$A$5,A20,'Compras sin pipa'!$B$5:$B$5,B20)+COUNTIFS('Registros manuales'!$A$5:$A$104,A20,'Registros manuales'!$B$5:$B$104,B20,'Registros manuales'!$G$5:$G$104,"SIN PIPA*") -> 0 | K20: =IF(COUNTIFS('Detalle pipas'!$A$5:$A$281,A20,'Detalle pipas'!$B$5:$B$281,B20,'Detalle pipas'!$L$5:$L$281,"REGISTRO MANUAL*")>0,"Incluye "&COUNTIFS('Detalle pipas'!$A$5:$A$281,A20,'Detalle pipas'!$B$5:$B$281,B20,'Detalle pipas'!$L$5:$L$281,"REGISTRO MANUAL*")&" registro(s) manual(es) · ","")&IF(G20="SIN REPORTE","Falta el CSV de mermas de esta estación/producto",IF(G20="CUADRA",IF(I20>0,"Cuadra en el mes; hay pipas registradas en otro día (ver Detalle pipas)","Todo en orden"),"Revisar: "&H20&" pipa(s) sin registrar y "&J20&" compra(s) sin pipa"))&IF(COUNTIFS('Detalle pipas'!$A$5:$A$281,A20,'Detalle pipas'!$B$5:$B$281,B20,'Detalle pipas'!$M$5:$M$281,"No")>0," · "&COUNTIFS('Detalle pipas'!$A$5:$A$281,A20,'Detalle pipas'!$B$5:$B$281,B20,'Detalle pipas'!$M$5:$M$281,"No")&" pipa(s) antes del inicio del reporte (no se cuentan)","") -> Cuadra en el mes; hay pipas registradas en otro día (ver Detalle pipas)
A21: HUEHUETOCA | B21: Premium | C21: ='Mermas mensual'!D9 -> 60101 | D21: =SUMIFS('Detalle pipas'!$G$5:$G$281,'Detalle pipas'!$A$5:$A$281,A21,'Detalle pipas'!$B$5:$B$281,B21,'Detalle pipas'!$M$5:$M$281,"Sí") -> 60101 | E21: =COUNTIFS('Detalle pipas'!$A$5:$A$281,A21,'Detalle pipas'!$B$5:$B$281,B21,'Detalle pipas'!$M$5:$M$281,"Sí") -> 3 | F21: =IF(ISNUMBER(C21),C21-D21,"") -> 0 | G21: =IF(NOT(ISNUMBER(C21)),"SIN REPORTE",IF(ABS(F21)<=Parámetros!$C$8*MAX(1,E21),"CUADRA","NO CUADRA")) -> CUADRA | H21: =COUNTIFS('Detalle pipas'!$A$5:$A$281,A21,'Detalle pipas'!$B$5:$B$281,B21,'Detalle pipas'!$L$5:$L$281,"NO REGISTRADA*") -> 0 | I21: =COUNTIFS('Detalle pipas'!$A$5:$A$281,A21,'Detalle pipas'!$B$5:$B$281,B21,'Detalle pipas'!$L$5:$L$281,"Registrada con desfase*") -> 0 | J21: =COUNTIFS('Compras sin pipa'!$A$5:$A$5,A21,'Compras sin pipa'!$B$5:$B$5,B21)+COUNTIFS('Registros manuales'!$A$5:$A$104,A21,'Registros manuales'!$B$5:$B$104,B21,'Registros manuales'!$G$5:$G$104,"SIN PIPA*") -> 0 | K21: =IF(COUNTIFS('Detalle pipas'!$A$5:$A$281,A21,'Detalle pipas'!$B$5:$B$281,B21,'Detalle pipas'!$L$5:$L$281,"REGISTRO MANUAL*")>0,"Incluye "&COUNTIFS('Detalle pipas'!$A$5:$A$281,A21,'Detalle pipas'!$B$5:$B$281,B21,'Detalle pipas'!$L$5:$L$281,"REGISTRO MANUAL*")&" registro(s) manual(es) · ","")&IF(G21="SIN REPORTE","Falta el CSV de mermas de esta estación/producto",IF(G21="CUADRA",IF(I21>0,"Cuadra en el mes; hay pipas registradas en otro día (ver Detalle pipas)","Todo en orden"),"Revisar: "&H21&" pipa(s) sin registrar y "&J21&" compra(s) sin pipa"))&IF(COUNTIFS('Detalle pipas'!$A$5:$A$281,A21,'Detalle pipas'!$B$5:$B$281,B21,'Detalle pipas'!$M$5:$M$281,"No")>0," · "&COUNTIFS('Detalle pipas'!$A$5:$A$281,A21,'Detalle pipas'!$B$5:$B$281,B21,'Detalle pipas'!$M$5:$M$281,"No")&" pipa(s) antes del inicio del reporte (no se cuentan)","") -> Todo en orden
A22: HUEHUETOCA | B22: Diesel | C22: ='Mermas mensual'!D10 -> 272939 | D22: =SUMIFS('Detalle pipas'!$G$5:$G$281,'Detalle pipas'!$A$5:$A$281,A22,'Detalle pipas'!$B$5:$B$281,B22,'Detalle pipas'!$M$5:$M$281,"Sí") -> 272939 | E22: =COUNTIFS('Detalle pipas'!$A$5:$A$281,A22,'Detalle pipas'!$B$5:$B$281,B22,'Detalle pipas'!$M$5:$M$281,"Sí") -> 9 | F22: =IF(ISNUMBER(C22),C22-D22,"") -> 0 | G22: =IF(NOT(ISNUMBER(C22)),"SIN REPORTE",IF(ABS(F22)<=Parámetros!$C$8*MAX(1,E22),"CUADRA","NO CUADRA")) -> CUADRA | H22: =COUNTIFS('Detalle pipas'!$A$5:$A$281,A22,'Detalle pipas'!$B$5:$B$281,B22,'Detalle pipas'!$L$5:$L$281,"NO REGISTRADA*") -> 0 | I22: =COUNTIFS('Detalle pipas'!$A$5:$A$281,A22,'Detalle pipas'!$B$5:$B$281,B22,'Detalle pipas'!$L$5:$L$281,"Registrada con desfase*") -> 2 | J22: =COUNTIFS('Compras sin pipa'!$A$5:$A$5,A22,'Compras sin pipa'!$B$5:$B$5,B22)+COUNTIFS('Registros manuales'!$A$5:$A$104,A22,'Registros manuales'!$B$5:$B$104,B22,'Registros manuales'!$G$5:$G$104,"SIN PIPA*") -> 0 | K22: =IF(COUNTIFS('Detalle pipas'!$A$5:$A$281,A22,'Detalle pipas'!$B$5:$B$281,B22,'Detalle pipas'!$L$5:$L$281,"REGISTRO MANUAL*")>0,"Incluye "&COUNTIFS('Detalle pipas'!$A$5:$A$281,A22,'Detalle pipas'!$B$5:$B$281,B22,'Detalle pipas'!$L$5:$L$281,"REGISTRO MANUAL*")&" registro(s) manual(es) · ","")&IF(G22="SIN REPORTE","Falta el CSV de mermas de esta estación/producto",IF(G22="CUADRA",IF(I22>0,"Cuadra en el mes; hay pipas registradas en otro día (ver Detalle pipas)","Todo en orden"),"Revisar: "&H22&" pipa(s) sin registrar y "&J22&" compra(s) sin pipa"))&IF(COUNTIFS('Detalle pipas'!$A$5:$A$281,A22,'Detalle pipas'!$B$5:$B$281,B22,'Detalle pipas'!$M$5:$M$281,"No")>0," · "&COUNTIFS('Detalle pipas'!$A$5:$A$281,A22,'Detalle pipas'!$B$5:$B$281,B22,'Detalle pipas'!$M$5:$M$281,"No")&" pipa(s) antes del inicio del reporte (no se cuentan)","") -> Cuadra en el mes; hay pipas registradas en otro día (ver Detalle pipas)
A23: QL | B23: Regular | C23: ='Mermas mensual'!D11 -> 579699 | D23: =SUMIFS('Detalle pipas'!$G$5:$G$281,'Detalle pipas'!$A$5:$A$281,A23,'Detalle pipas'!$B$5:$B$281,B23,'Detalle pipas'!$M$5:$M$281,"Sí") -> 579699 | E23: =COUNTIFS('Detalle pipas'!$A$5:$A$281,A23,'Detalle pipas'!$B$5:$B$281,B23,'Detalle pipas'!$M$5:$M$281,"Sí") -> 20 | F23: =IF(ISNUMBER(C23),C23-D23,"") -> 0 | G23: =IF(NOT(ISNUMBER(C23)),"SIN REPORTE",IF(ABS(F23)<=Parámetros!$C$8*MAX(1,E23),"CUADRA","NO CUADRA")) -> CUADRA | H23: =COUNTIFS('Detalle pipas'!$A$5:$A$281,A23,'Detalle pipas'!$B$5:$B$281,B23,'Detalle pipas'!$L$5:$L$281,"NO REGISTRADA*") -> 0 | I23: =COUNTIFS('Detalle pipas'!$A$5:$A$281,A23,'Detalle pipas'!$B$5:$B$281,B23,'Detalle pipas'!$L$5:$L$281,"Registrada con desfase*") -> 0 | J23: =COUNTIFS('Compras sin pipa'!$A$5:$A$5,A23,'Compras sin pipa'!$B$5:$B$5,B23)+COUNTIFS('Registros manuales'!$A$5:$A$104,A23,'Registros manuales'!$B$5:$B$104,B23,'Registros manuales'!$G$5:$G$104,"SIN PIPA*") -> 0 | K23: =IF(COUNTIFS('Detalle pipas'!$A$5:$A$281,A23,'Detalle pipas'!$B$5:$B$281,B23,'Detalle pipas'!$L$5:$L$281,"REGISTRO MANUAL*")>0,"Incluye "&COUNTIFS('Detalle pipas'!$A$5:$A$281,A23,'Detalle pipas'!$B$5:$B$281,B23,'Detalle pipas'!$L$5:$L$281,"REGISTRO MANUAL*")&" registro(s) manual(es) · ","")&IF(G23="SIN REPORTE","Falta el CSV de mermas de esta estación/producto",IF(G23="CUADRA",IF(I23>0,"Cuadra en el mes; hay pipas registradas en otro día (ver Detalle pipas)","Todo en orden"),"Revisar: "&H23&" pipa(s) sin registrar y "&J23&" compra(s) sin pipa"))&IF(COUNTIFS('Detalle pipas'!$A$5:$A$281,A23,'Detalle pipas'!$B$5:$B$281,B23,'Detalle pipas'!$M$5:$M$281,"No")>0," · "&COUNTIFS('Detalle pipas'!$A$5:$A$281,A23,'Detalle pipas'!$B$5:$B$281,B23,'Detalle pipas'!$M$5:$M$281,"No")&" pipa(s) antes del inicio del reporte (no se cuentan)","") -> Todo en orden
A24: QL | B24: Premium | C24: ='Mermas mensual'!D12 -> 300298 | D24: =SUMIFS('Detalle pipas'!$G$5:$G$281,'Detalle pipas'!$A$5:$A$281,A24,'Detalle pipas'!$B$5:$B$281,B24,'Detalle pipas'!$M$5:$M$281,"Sí") -> 300298 | E24: =COUNTIFS('Detalle pipas'!$A$5:$A$281,A24,'Detalle pipas'!$B$5:$B$281,B24,'Detalle pipas'!$M$5:$M$281,"Sí") -> 9 | F24: =IF(ISNUMBER(C24),C24-D24,"") -> 0 | G24: =IF(NOT(ISNUMBER(C24)),"SIN REPORTE",IF(ABS(F24)<=Parámetros!$C$8*MAX(1,E24),"CUADRA","NO CUADRA")) -> CUADRA | H24: =COUNTIFS('Detalle pipas'!$A$5:$A$281,A24,'Detalle pipas'!$B$5:$B$281,B24,'Detalle pipas'!$L$5:$L$281,"NO REGISTRADA*") -> 0 | I24: =COUNTIFS('Detalle pipas'!$A$5:$A$281,A24,'Detalle pipas'!$B$5:$B$281,B24,'Detalle pipas'!$L$5:$L$281,"Registrada con desfase*") -> 0 | J24: =COUNTIFS('Compras sin pipa'!$A$5:$A$5,A24,'Compras sin pipa'!$B$5:$B$5,B24)+COUNTIFS('Registros manuales'!$A$5:$A$104,A24,'Registros manuales'!$B$5:$B$104,B24,'Registros manuales'!$G$5:$G$104,"SIN PIPA*") -> 0 | K24: =IF(COUNTIFS('Detalle pipas'!$A$5:$A$281,A24,'Detalle pipas'!$B$5:$B$281,B24,'Detalle pipas'!$L$5:$L$281,"REGISTRO MANUAL*")>0,"Incluye "&COUNTIFS('Detalle pipas'!$A$5:$A$281,A24,'Detalle pipas'!$B$5:$B$281,B24,'Detalle pipas'!$L$5:$L$281,"REGISTRO MANUAL*")&" registro(s) manual(es) · ","")&IF(G24="SIN REPORTE","Falta el CSV de mermas de esta estación/producto",IF(G24="CUADRA",IF(I24>0,"Cuadra en el mes; hay pipas registradas en otro día (ver Detalle pipas)","Todo en orden"),"Revisar: "&H24&" pipa(s) sin registrar y "&J24&" compra(s) sin pipa"))&IF(COUNTIFS('Detalle pipas'!$A$5:$A$281,A24,'Detalle pipas'!$B$5:$B$281,B24,'Detalle pipas'!$M$5:$M$281,"No")>0," · "&COUNTIFS('Detalle pipas'!$A$5:$A$281,A24,'Detalle pipas'!$B$5:$B$281,B24,'Detalle pipas'!$M$5:$M$281,"No")&" pipa(s) antes del inicio del reporte (no se cuentan)","") -> Todo en orden
A25: QL | B25: Diesel | C25: ='Mermas mensual'!D13 -> 877365 | D25: =SUMIFS('Detalle pipas'!$G$5:$G$281,'Detalle pipas'!$A$5:$A$281,A25,'Detalle pipas'!$B$5:$B$281,B25,'Detalle pipas'!$M$5:$M$281,"Sí") -> 877365 | E25: =COUNTIFS('Detalle pipas'!$A$5:$A$281,A25,'Detalle pipas'!$B$5:$B$281,B25,'Detalle pipas'!$M$5:$M$281,"Sí") -> 27 | F25: =IF(ISNUMBER(C25),C25-D25,"") -> 0 | G25: =IF(NOT(ISNUMBER(C25)),"SIN REPORTE",IF(ABS(F25)<=Parámetros!$C$8*MAX(1,E25),"CUADRA","NO CUADRA")) -> CUADRA | H25: =COUNTIFS('Detalle pipas'!$A$5:$A$281,A25,'Detalle pipas'!$B$5:$B$281,B25,'Detalle pipas'!$L$5:$L$281,"NO REGISTRADA*") -> 0 | I25: =COUNTIFS('Detalle pipas'!$A$5:$A$281,A25,'Detalle pipas'!$B$5:$B$281,B25,'Detalle pipas'!$L$5:$L$281,"Registrada con desfase*") -> 0 | J25: =COUNTIFS('Compras sin pipa'!$A$5:$A$5,A25,'Compras sin pipa'!$B$5:$B$5,B25)+COUNTIFS('Registros manuales'!$A$5:$A$104,A25,'Registros manuales'!$B$5:$B$104,B25,'Registros manuales'!$G$5:$G$104,"SIN PIPA*") -> 0 | K25: =IF(COUNTIFS('Detalle pipas'!$A$5:$A$281,A25,'Detalle pipas'!$B$5:$B$281,B25,'Detalle pipas'!$L$5:$L$281,"REGISTRO MANUAL*")>0,"Incluye "&COUNTIFS('Detalle pipas'!$A$5:$A$281,A25,'Detalle pipas'!$B$5:$B$281,B25,'Detalle pipas'!$L$5:$L$281,"REGISTRO MANUAL*")&" registro(s) manual(es) · ","")&IF(G25="SIN REPORTE","Falta el CSV de mermas de esta estación/producto",IF(G25="CUADRA",IF(I25>0,"Cuadra en el mes; hay pipas registradas en otro día (ver Detalle pipas)","Todo en orden"),"Revisar: "&H25&" pipa(s) sin registrar y "&J25&" compra(s) sin pipa"))&IF(COUNTIFS('Detalle pipas'!$A$5:$A$281,A25,'Detalle pipas'!$B$5:$B$281,B25,'Detalle pipas'!$M$5:$M$281,"No")>0," · "&COUNTIFS('Detalle pipas'!$A$5:$A$281,A25,'Detalle pipas'!$B$5:$B$281,B25,'Detalle pipas'!$M$5:$M$281,"No")&" pipa(s) antes del inicio del reporte (no se cuentan)","") -> Todo en orden
A26: IXTAZACUALA | B26: Regular | C26: ='Mermas mensual'!D14 -> 332823 | D26: =SUMIFS('Detalle pipas'!$G$5:$G$281,'Detalle pipas'!$A$5:$A$281,A26,'Detalle pipas'!$B$5:$B$281,B26,'Detalle pipas'!$M$5:$M$281,"Sí") -> 332823 | E26: =COUNTIFS('Detalle pipas'!$A$5:$A$281,A26,'Detalle pipas'!$B$5:$B$281,B26,'Detalle pipas'!$M$5:$M$281,"Sí") -> 11 | F26: =IF(ISNUMBER(C26),C26-D26,"") -> 0 | G26: =IF(NOT(ISNUMBER(C26)),"SIN REPORTE",IF(ABS(F26)<=Parámetros!$C$8*MAX(1,E26),"CUADRA","NO CUADRA")) -> CUADRA | H26: =COUNTIFS('Detalle pipas'!$A$5:$A$281,A26,'Detalle pipas'!$B$5:$B$281,B26,'Detalle pipas'!$L$5:$L$281,"NO REGISTRADA*") -> 0 | I26: =COUNTIFS('Detalle pipas'!$A$5:$A$281,A26,'Detalle pipas'!$B$5:$B$281,B26,'Detalle pipas'!$L$5:$L$281,"Registrada con desfase*") -> 0 | J26: =COUNTIFS('Compras sin pipa'!$A$5:$A$5,A26,'Compras sin pipa'!$B$5:$B$5,B26)+COUNTIFS('Registros manuales'!$A$5:$A$104,A26,'Registros manuales'!$B$5:$B$104,B26,'Registros manuales'!$G$5:$G$104,"SIN PIPA*") -> 0 | K26: =IF(COUNTIFS('Detalle pipas'!$A$5:$A$281,A26,'Detalle pipas'!$B$5:$B$281,B26,'Detalle pipas'!$L$5:$L$281,"REGISTRO MANUAL*")>0,"Incluye "&COUNTIFS('Detalle pipas'!$A$5:$A$281,A26,'Detalle pipas'!$B$5:$B$281,B26,'Detalle pipas'!$L$5:$L$281,"REGISTRO MANUAL*")&" registro(s) manual(es) · ","")&IF(G26="SIN REPORTE","Falta el CSV de mermas de esta estación/producto",IF(G26="CUADRA",IF(I26>0,"Cuadra en el mes; hay pipas registradas en otro día (ver Detalle pipas)","Todo en orden"),"Revisar: "&H26&" pipa(s) sin registrar y "&J26&" compra(s) sin pipa"))&IF(COUNTIFS('Detalle pipas'!$A$5:$A$281,A26,'Detalle pipas'!$B$5:$B$281,B26,'Detalle pipas'!$M$5:$M$281,"No")>0," · "&COUNTIFS('Detalle pipas'!$A$5:$A$281,A26,'Detalle pipas'!$B$5:$B$281,B26,'Detalle pipas'!$M$5:$M$281,"No")&" pipa(s) antes del inicio del reporte (no se cuentan)","") -> Todo en orden · 2 pipa(s) antes del inicio del reporte (no se cuentan)
A27: IXTAZACUALA | B27: Premium | C27: ='Mermas mensual'!D15 -> 59834 | D27: =SUMIFS('Detalle pipas'!$G$5:$G$281,'Detalle pipas'!$A$5:$A$281,A27,'Detalle pipas'!$B$5:$B$281,B27,'Detalle pipas'!$M$5:$M$281,"Sí") -> 59834 | E27: =COUNTIFS('Detalle pipas'!$A$5:$A$281,A27,'Detalle pipas'!$B$5:$B$281,B27,'Detalle pipas'!$M$5:$M$281,"Sí") -> 2 | F27: =IF(ISNUMBER(C27),C27-D27,"") -> 0 | G27: =IF(NOT(ISNUMBER(C27)),"SIN REPORTE",IF(ABS(F27)<=Parámetros!$C$8*MAX(1,E27),"CUADRA","NO CUADRA")) -> CUADRA | H27: =COUNTIFS('Detalle pipas'!$A$5:$A$281,A27,'Detalle pipas'!$B$5:$B$281,B27,'Detalle pipas'!$L$5:$L$281,"NO REGISTRADA*") -> 0 | I27: =COUNTIFS('Detalle pipas'!$A$5:$A$281,A27,'Detalle pipas'!$B$5:$B$281,B27,'Detalle pipas'!$L$5:$L$281,"Registrada con desfase*") -> 0 | J27: =COUNTIFS('Compras sin pipa'!$A$5:$A$5,A27,'Compras sin pipa'!$B$5:$B$5,B27)+COUNTIFS('Registros manuales'!$A$5:$A$104,A27,'Registros manuales'!$B$5:$B$104,B27,'Registros manuales'!$G$5:$G$104,"SIN PIPA*") -> 0 | K27: =IF(COUNTIFS('Detalle pipas'!$A$5:$A$281,A27,'Detalle pipas'!$B$5:$B$281,B27,'Detalle pipas'!$L$5:$L$281,"REGISTRO MANUAL*")>0,"Incluye "&COUNTIFS('Detalle pipas'!$A$5:$A$281,A27,'Detalle pipas'!$B$5:$B$281,B27,'Detalle pipas'!$L$5:$L$281,"REGISTRO MANUAL*")&" registro(s) manual(es) · ","")&IF(G27="SIN REPORTE","Falta el CSV de mermas de esta estación/producto",IF(G27="CUADRA",IF(I27>0,"Cuadra en el mes; hay pipas registradas en otro día (ver Detalle pipas)","Todo en orden"),"Revisar: "&H27&" pipa(s) sin registrar y "&J27&" compra(s) sin pipa"))&IF(COUNTIFS('Detalle pipas'!$A$5:$A$281,A27,'Detalle pipas'!$B$5:$B$281,B27,'Detalle pipas'!$M$5:$M$281,"No")>0," · "&COUNTIFS('Detalle pipas'!$A$5:$A$281,A27,'Detalle pipas'!$B$5:$B$281,B27,'Detalle pipas'!$M$5:$M$281,"No")&" pipa(s) antes del inicio del reporte (no se cuentan)","") -> Todo en orden
A28: IXTAZACUALA | B28: Diesel | C28: ='Mermas mensual'!D16 -> 303295 | D28: =SUMIFS('Detalle pipas'!$G$5:$G$281,'Detalle pipas'!$A$5:$A$281,A28,'Detalle pipas'!$B$5:$B$281,B28,'Detalle pipas'!$M$5:$M$281,"Sí") -> 303295 | E28: =COUNTIFS('Detalle pipas'!$A$5:$A$281,A28,'Detalle pipas'!$B$5:$B$281,B28,'Detalle pipas'!$M$5:$M$281,"Sí") -> 12 | F28: =IF(ISNUMBER(C28),C28-D28,"") -> 0 | G28: =IF(NOT(ISNUMBER(C28)),"SIN REPORTE",IF(ABS(F28)<=Parámetros!$C$8*MAX(1,E28),"CUADRA","NO CUADRA")) -> CUADRA | H28: =COUNTIFS('Detalle pipas'!$A$5:$A$281,A28,'Detalle pipas'!$B$5:$B$281,B28,'Detalle pipas'!$L$5:$L$281,"NO REGISTRADA*") -> 0 | I28: =COUNTIFS('Detalle pipas'!$A$5:$A$281,A28,'Detalle pipas'!$B$5:$B$281,B28,'Detalle pipas'!$L$5:$L$281,"Registrada con desfase*") -> 0 | J28: =COUNTIFS('Compras sin pipa'!$A$5:$A$5,A28,'Compras sin pipa'!$B$5:$B$5,B28)+COUNTIFS('Registros manuales'!$A$5:$A$104,A28,'Registros manuales'!$B$5:$B$104,B28,'Registros manuales'!$G$5:$G$104,"SIN PIPA*") -> 0 | K28: =IF(COUNTIFS('Detalle pipas'!$A$5:$A$281,A28,'Detalle pipas'!$B$5:$B$281,B28,'Detalle pipas'!$L$5:$L$281,"REGISTRO MANUAL*")>0,"Incluye "&COUNTIFS('Detalle pipas'!$A$5:$A$281,A28,'Detalle pipas'!$B$5:$B$281,B28,'Detalle pipas'!$L$5:$L$281,"REGISTRO MANUAL*")&" registro(s) manual(es) · ","")&IF(G28="SIN REPORTE","Falta el CSV de mermas de esta estación/producto",IF(G28="CUADRA",IF(I28>0,"Cuadra en el mes; hay pipas registradas en otro día (ver Detalle pipas)","Todo en orden"),"Revisar: "&H28&" pipa(s) sin registrar y "&J28&" compra(s) sin pipa"))&IF(COUNTIFS('Detalle pipas'!$A$5:$A$281,A28,'Detalle pipas'!$B$5:$B$281,B28,'Detalle pipas'!$M$5:$M$281,"No")>0," · "&COUNTIFS('Detalle pipas'!$A$5:$A$281,A28,'Detalle pipas'!$B$5:$B$281,B28,'Detalle pipas'!$M$5:$M$281,"No")&" pipa(s) antes del inicio del reporte (no se cuentan)","") -> Todo en orden
A29: TREHER | B29: Regular | C29: ='Mermas mensual'!D17 -> 299705 | D29: =SUMIFS('Detalle pipas'!$G$5:$G$281,'Detalle pipas'!$A$5:$A$281,A29,'Detalle pipas'!$B$5:$B$281,B29,'Detalle pipas'!$M$5:$M$281,"Sí") -> 299705 | E29: =COUNTIFS('Detalle pipas'!$A$5:$A$281,A29,'Detalle pipas'!$B$5:$B$281,B29,'Detalle pipas'!$M$5:$M$281,"Sí") -> 17 | F29: =IF(ISNUMBER(C29),C29-D29,"") -> 0 | G29: =IF(NOT(ISNUMBER(C29)),"SIN REPORTE",IF(ABS(F29)<=Parámetros!$C$8*MAX(1,E29),"CUADRA","NO CUADRA")) -> CUADRA | H29: =COUNTIFS('Detalle pipas'!$A$5:$A$281,A29,'Detalle pipas'!$B$5:$B$281,B29,'Detalle pipas'!$L$5:$L$281,"NO REGISTRADA*") -> 0 | I29: =COUNTIFS('Detalle pipas'!$A$5:$A$281,A29,'Detalle pipas'!$B$5:$B$281,B29,'Detalle pipas'!$L$5:$L$281,"Registrada con desfase*") -> 0 | J29: =COUNTIFS('Compras sin pipa'!$A$5:$A$5,A29,'Compras sin pipa'!$B$5:$B$5,B29)+COUNTIFS('Registros manuales'!$A$5:$A$104,A29,'Registros manuales'!$B$5:$B$104,B29,'Registros manuales'!$G$5:$G$104,"SIN PIPA*") -> 0 | K29: =IF(COUNTIFS('Detalle pipas'!$A$5:$A$281,A29,'Detalle pipas'!$B$5:$B$281,B29,'Detalle pipas'!$L$5:$L$281,"REGISTRO MANUAL*")>0,"Incluye "&COUNTIFS('Detalle pipas'!$A$5:$A$281,A29,'Detalle pipas'!$B$5:$B$281,B29,'Detalle pipas'!$L$5:$L$281,"REGISTRO MANUAL*")&" registro(s) manual(es) · ","")&IF(G29="SIN REPORTE","Falta el CSV de mermas de esta estación/producto",IF(G29="CUADRA",IF(I29>0,"Cuadra en el mes; hay pipas registradas en otro día (ver Detalle pipas)","Todo en orden"),"Revisar: "&H29&" pipa(s) sin registrar y "&J29&" compra(s) sin pipa"))&IF(COUNTIFS('Detalle pipas'!$A$5:$A$281,A29,'Detalle pipas'!$B$5:$B$281,B29,'Detalle pipas'!$M$5:$M$281,"No")>0," · "&COUNTIFS('Detalle pipas'!$A$5:$A$281,A29,'Detalle pipas'!$B$5:$B$281,B29,'Detalle pipas'!$M$5:$M$281,"No")&" pipa(s) antes del inicio del reporte (no se cuentan)","") -> Todo en orden · 1 pipa(s) antes del inicio del reporte (no se cuentan)
A30: TREHER | B30: Premium | C30: ='Mermas mensual'!D18 -> 39894 | D30: =SUMIFS('Detalle pipas'!$G$5:$G$281,'Detalle pipas'!$A$5:$A$281,A30,'Detalle pipas'!$B$5:$B$281,B30,'Detalle pipas'!$M$5:$M$281,"Sí") -> 39894 | E30: =COUNTIFS('Detalle pipas'!$A$5:$A$281,A30,'Detalle pipas'!$B$5:$B$281,B30,'Detalle pipas'!$M$5:$M$281,"Sí") -> 2 | F30: =IF(ISNUMBER(C30),C30-D30,"") -> 0 | G30: =IF(NOT(ISNUMBER(C30)),"SIN REPORTE",IF(ABS(F30)<=Parámetros!$C$8*MAX(1,E30),"CUADRA","NO CUADRA")) -> CUADRA | H30: =COUNTIFS('Detalle pipas'!$A$5:$A$281,A30,'Detalle pipas'!$B$5:$B$281,B30,'Detalle pipas'!$L$5:$L$281,"NO REGISTRADA*") -> 0 | I30: =COUNTIFS('Detalle pipas'!$A$5:$A$281,A30,'Detalle pipas'!$B$5:$B$281,B30,'Detalle pipas'!$L$5:$L$281,"Registrada con desfase*") -> 0 | J30: =COUNTIFS('Compras sin pipa'!$A$5:$A$5,A30,'Compras sin pipa'!$B$5:$B$5,B30)+COUNTIFS('Registros manuales'!$A$5:$A$104,A30,'Registros manuales'!$B$5:$B$104,B30,'Registros manuales'!$G$5:$G$104,"SIN PIPA*") -> 0 | K30: =IF(COUNTIFS('Detalle pipas'!$A$5:$A$281,A30,'Detalle pipas'!$B$5:$B$281,B30,'Detalle pipas'!$L$5:$L$281,"REGISTRO MANUAL*")>0,"Incluye "&COUNTIFS('Detalle pipas'!$A$5:$A$281,A30,'Detalle pipas'!$B$5:$B$281,B30,'Detalle pipas'!$L$5:$L$281,"REGISTRO MANUAL*")&" registro(s) manual(es) · ","")&IF(G30="SIN REPORTE","Falta el CSV de mermas de esta estación/producto",IF(G30="CUADRA",IF(I30>0,"Cuadra en el mes; hay pipas registradas en otro día (ver Detalle pipas)","Todo en orden"),"Revisar: "&H30&" pipa(s) sin registrar y "&J30&" compra(s) sin pipa"))&IF(COUNTIFS('Detalle pipas'!$A$5:$A$281,A30,'Detalle pipas'!$B$5:$B$281,B30,'Detalle pipas'!$M$5:$M$281,"No")>0," · "&COUNTIFS('Detalle pipas'!$A$5:$A$281,A30,'Detalle pipas'!$B$5:$B$281,B30,'Detalle pipas'!$M$5:$M$281,"No")&" pipa(s) antes del inicio del reporte (no se cuentan)","") -> Todo en orden
A31: TREHER | B31: Diesel | C31: ='Mermas mensual'!D19 -> 265770 | D31: =SUMIFS('Detalle pipas'!$G$5:$G$281,'Detalle pipas'!$A$5:$A$281,A31,'Detalle pipas'!$B$5:$B$281,B31,'Detalle pipas'!$M$5:$M$281,"Sí") -> 265770 | E31: =COUNTIFS('Detalle pipas'!$A$5:$A$281,A31,'Detalle pipas'!$B$5:$B$281,B31,'Detalle pipas'!$M$5:$M$281,"Sí") -> 12 | F31: =IF(ISNUMBER(C31),C31-D31,"") -> 0 | G31: =IF(NOT(ISNUMBER(C31)),"SIN REPORTE",IF(ABS(F31)<=Parámetros!$C$8*MAX(1,E31),"CUADRA","NO CUADRA")) -> CUADRA | H31: =COUNTIFS('Detalle pipas'!$A$5:$A$281,A31,'Detalle pipas'!$B$5:$B$281,B31,'Detalle pipas'!$L$5:$L$281,"NO REGISTRADA*") -> 0 | I31: =COUNTIFS('Detalle pipas'!$A$5:$A$281,A31,'Detalle pipas'!$B$5:$B$281,B31,'Detalle pipas'!$L$5:$L$281,"Registrada con desfase*") -> 0 | J31: =COUNTIFS('Compras sin pipa'!$A$5:$A$5,A31,'Compras sin pipa'!$B$5:$B$5,B31)+COUNTIFS('Registros manuales'!$A$5:$A$104,A31,'Registros manuales'!$B$5:$B$104,B31,'Registros manuales'!$G$5:$G$104,"SIN PIPA*") -> 0 | K31: =IF(COUNTIFS('Detalle pipas'!$A$5:$A$281,A31,'Detalle pipas'!$B$5:$B$281,B31,'Detalle pipas'!$L$5:$L$281,"REGISTRO MANUAL*")>0,"Incluye "&COUNTIFS('Detalle pipas'!$A$5:$A$281,A31,'Detalle pipas'!$B$5:$B$281,B31,'Detalle pipas'!$L$5:$L$281,"REGISTRO MANUAL*")&" registro(s) manual(es) · ","")&IF(G31="SIN REPORTE","Falta el CSV de mermas de esta estación/producto",IF(G31="CUADRA",IF(I31>0,"Cuadra en el mes; hay pipas registradas en otro día (ver Detalle pipas)","Todo en orden"),"Revisar: "&H31&" pipa(s) sin registrar y "&J31&" compra(s) sin pipa"))&IF(COUNTIFS('Detalle pipas'!$A$5:$A$281,A31,'Detalle pipas'!$B$5:$B$281,B31,'Detalle pipas'!$M$5:$M$281,"No")>0," · "&COUNTIFS('Detalle pipas'!$A$5:$A$281,A31,'Detalle pipas'!$B$5:$B$281,B31,'Detalle pipas'!$M$5:$M$281,"No")&" pipa(s) antes del inicio del reporte (no se cuentan)","") -> Todo en orden · 1 pipa(s) antes del inicio del reporte (no se cuentan)
A32: TH | B32: Regular | C32: Sin reporte | D32: =SUMIFS('Detalle pipas'!$G$5:$G$281,'Detalle pipas'!$A$5:$A$281,A32,'Detalle pipas'!$B$5:$B$281,B32,'Detalle pipas'!$M$5:$M$281,"Sí") -> 293717 | E32: =COUNTIFS('Detalle pipas'!$A$5:$A$281,A32,'Detalle pipas'!$B$5:$B$281,B32,'Detalle pipas'!$M$5:$M$281,"Sí") -> 9 | F32: =IF(ISNUMBER(C32),C32-D32,"") | G32: =IF(NOT(ISNUMBER(C32)),"SIN REPORTE",IF(ABS(F32)<=Parámetros!$C$8*MAX(1,E32),"CUADRA","NO CUADRA")) -> SIN REPORTE | H32: =COUNTIFS('Detalle pipas'!$A$5:$A$281,A32,'Detalle pipas'!$B$5:$B$281,B32,'Detalle pipas'!$L$5:$L$281,"NO REGISTRADA*") -> 0 | I32: =COUNTIFS('Detalle pipas'!$A$5:$A$281,A32,'Detalle pipas'!$B$5:$B$281,B32,'Detalle pipas'!$L$5:$L$281,"Registrada con desfase*") -> 0 | J32: =COUNTIFS('Compras sin pipa'!$A$5:$A$5,A32,'Compras sin pipa'!$B$5:$B$5,B32)+COUNTIFS('Registros manuales'!$A$5:$A$104,A32,'Registros manuales'!$B$5:$B$104,B32,'Registros manuales'!$G$5:$G$104,"SIN PIPA*") -> 0 | K32: =IF(COUNTIFS('Detalle pipas'!$A$5:$A$281,A32,'Detalle pipas'!$B$5:$B$281,B32,'Detalle pipas'!$L$5:$L$281,"REGISTRO MANUAL*")>0,"Incluye "&COUNTIFS('Detalle pipas'!$A$5:$A$281,A32,'Detalle pipas'!$B$5:$B$281,B32,'Detalle pipas'!$L$5:$L$281,"REGISTRO MANUAL*")&" registro(s) manual(es) · ","")&IF(G32="SIN REPORTE","Falta el CSV de mermas de esta estación/producto",IF(G32="CUADRA",IF(I32>0,"Cuadra en el mes; hay pipas registradas en otro día (ver Detalle pipas)","Todo en orden"),"Revisar: "&H32&" pipa(s) sin registrar y "&J32&" compra(s) sin pipa"))&IF(COUNTIFS('Detalle pipas'!$A$5:$A$281,A32,'Detalle pipas'!$B$5:$B$281,B32,'Detalle pipas'!$M$5:$M$281,"No")>0," · "&COUNTIFS('Detalle pipas'!$A$5:$A$281,A32,'Detalle pipas'!$B$5:$B$281,B32,'Detalle pipas'!$M$5:$M$281,"No")&" pipa(s) antes del inicio del reporte (no se cuentan)","") -> Falta el CSV de mermas de esta estación/producto
A33: TH | B33: Premium | C33: Sin reporte | D33: =SUMIFS('Detalle pipas'!$G$5:$G$281,'Detalle pipas'!$A$5:$A$281,A33,'Detalle pipas'!$B$5:$B$281,B33,'Detalle pipas'!$M$5:$M$281,"Sí") -> 63535 | E33: =COUNTIFS('Detalle pipas'!$A$5:$A$281,A33,'Detalle pipas'!$B$5:$B$281,B33,'Detalle pipas'!$M$5:$M$281,"Sí") -> 3 | F33: =IF(ISNUMBER(C33),C33-D33,"") | G33: =IF(NOT(ISNUMBER(C33)),"SIN REPORTE",IF(ABS(F33)<=Parámetros!$C$8*MAX(1,E33),"CUADRA","NO CUADRA")) -> SIN REPORTE | H33: =COUNTIFS('Detalle pipas'!$A$5:$A$281,A33,'Detalle pipas'!$B$5:$B$281,B33,'Detalle pipas'!$L$5:$L$281,"NO REGISTRADA*") -> 0 | I33: =COUNTIFS('Detalle pipas'!$A$5:$A$281,A33,'Detalle pipas'!$B$5:$B$281,B33,'Detalle pipas'!$L$5:$L$281,"Registrada con desfase*") -> 0 | J33: =COUNTIFS('Compras sin pipa'!$A$5:$A$5,A33,'Compras sin pipa'!$B$5:$B$5,B33)+COUNTIFS('Registros manuales'!$A$5:$A$104,A33,'Registros manuales'!$B$5:$B$104,B33,'Registros manuales'!$G$5:$G$104,"SIN PIPA*") -> 0 | K33: =IF(COUNTIFS('Detalle pipas'!$A$5:$A$281,A33,'Detalle pipas'!$B$5:$B$281,B33,'Detalle pipas'!$L$5:$L$281,"REGISTRO MANUAL*")>0,"Incluye "&COUNTIFS('Detalle pipas'!$A$5:$A$281,A33,'Detalle pipas'!$B$5:$B$281,B33,'Detalle pipas'!$L$5:$L$281,"REGISTRO MANUAL*")&" registro(s) manual(es) · ","")&IF(G33="SIN REPORTE","Falta el CSV de mermas de esta estación/producto",IF(G33="CUADRA",IF(I33>0,"Cuadra en el mes; hay pipas registradas en otro día (ver Detalle pipas)","Todo en orden"),"Revisar: "&H33&" pipa(s) sin registrar y "&J33&" compra(s) sin pipa"))&IF(COUNTIFS('Detalle pipas'!$A$5:$A$281,A33,'Detalle pipas'!$B$5:$B$281,B33,'Detalle pipas'!$M$5:$M$281,"No")>0," · "&COUNTIFS('Detalle pipas'!$A$5:$A$281,A33,'Detalle pipas'!$B$5:$B$281,B33,'Detalle pipas'!$M$5:$M$281,"No")&" pipa(s) antes del inicio del reporte (no se cuentan)","") -> Falta el CSV de mermas de esta estación/producto
A34: TH | B34: Diesel | C34: Sin reporte | D34: =SUMIFS('Detalle pipas'!$G$5:$G$281,'Detalle pipas'!$A$5:$A$281,A34,'Detalle pipas'!$B$5:$B$281,B34,'Detalle pipas'!$M$5:$M$281,"Sí") -> 532049 | E34: =COUNTIFS('Detalle pipas'!$A$5:$A$281,A34,'Detalle pipas'!$B$5:$B$281,B34,'Detalle pipas'!$M$5:$M$281,"Sí") -> 17 | F34: =IF(ISNUMBER(C34),C34-D34,"") | G34: =IF(NOT(ISNUMBER(C34)),"SIN REPORTE",IF(ABS(F34)<=Parámetros!$C$8*MAX(1,E34),"CUADRA","NO CUADRA")) -> SIN REPORTE | H34: =COUNTIFS('Detalle pipas'!$A$5:$A$281,A34,'Detalle pipas'!$B$5:$B$281,B34,'Detalle pipas'!$L$5:$L$281,"NO REGISTRADA*") -> 0 | I34: =COUNTIFS('Detalle pipas'!$A$5:$A$281,A34,'Detalle pipas'!$B$5:$B$281,B34,'Detalle pipas'!$L$5:$L$281,"Registrada con desfase*") -> 0 | J34: =COUNTIFS('Compras sin pipa'!$A$5:$A$5,A34,'Compras sin pipa'!$B$5:$B$5,B34)+COUNTIFS('Registros manuales'!$A$5:$A$104,A34,'Registros manuales'!$B$5:$B$104,B34,'Registros manuales'!$G$5:$G$104,"SIN PIPA*") -> 0 | K34: =IF(COUNTIFS('Detalle pipas'!$A$5:$A$281,A34,'Detalle pipas'!$B$5:$B$281,B34,'Detalle pipas'!$L$5:$L$281,"REGISTRO MANUAL*")>0,"Incluye "&COUNTIFS('Detalle pipas'!$A$5:$A$281,A34,'Detalle pipas'!$B$5:$B$281,B34,'Detalle pipas'!$L$5:$L$281,"REGISTRO MANUAL*")&" registro(s) manual(es) · ","")&IF(G34="SIN REPORTE","Falta el CSV de mermas de esta estación/producto",IF(G34="CUADRA",IF(I34>0,"Cuadra en el mes; hay pipas registradas en otro día (ver Detalle pipas)","Todo en orden"),"Revisar: "&H34&" pipa(s) sin registrar y "&J34&" compra(s) sin pipa"))&IF(COUNTIFS('Detalle pipas'!$A$5:$A$281,A34,'Detalle pipas'!$B$5:$B$281,B34,'Detalle pipas'!$M$5:$M$281,"No")>0," · "&COUNTIFS('Detalle pipas'!$A$5:$A$281,A34,'Detalle pipas'!$B$5:$B$281,B34,'Detalle pipas'!$M$5:$M$281,"No")&" pipa(s) antes del inicio del reporte (no se cuentan)","") -> Falta el CSV de mermas de esta estación/producto
A35: TOREMEX | B35: Regular | C35: Sin reporte | D35: =SUMIFS('Detalle pipas'!$G$5:$G$281,'Detalle pipas'!$A$5:$A$281,A35,'Detalle pipas'!$B$5:$B$281,B35,'Detalle pipas'!$M$5:$M$281,"Sí") -> 192937 | E35: =COUNTIFS('Detalle pipas'!$A$5:$A$281,A35,'Detalle pipas'!$B$5:$B$281,B35,'Detalle pipas'!$M$5:$M$281,"Sí") -> 7 | F35: =IF(ISNUMBER(C35),C35-D35,"") | G35: =IF(NOT(ISNUMBER(C35)),"SIN REPORTE",IF(ABS(F35)<=Parámetros!$C$8*MAX(1,E35),"CUADRA","NO CUADRA")) -> SIN REPORTE | H35: =COUNTIFS('Detalle pipas'!$A$5:$A$281,A35,'Detalle pipas'!$B$5:$B$281,B35,'Detalle pipas'!$L$5:$L$281,"NO REGISTRADA*") -> 0 | I35: =COUNTIFS('Detalle pipas'!$A$5:$A$281,A35,'Detalle pipas'!$B$5:$B$281,B35,'Detalle pipas'!$L$5:$L$281,"Registrada con desfase*") -> 0 | J35: =COUNTIFS('Compras sin pipa'!$A$5:$A$5,A35,'Compras sin pipa'!$B$5:$B$5,B35)+COUNTIFS('Registros manuales'!$A$5:$A$104,A35,'Registros manuales'!$B$5:$B$104,B35,'Registros manuales'!$G$5:$G$104,"SIN PIPA*") -> 0 | K35: =IF(COUNTIFS('Detalle pipas'!$A$5:$A$281,A35,'Detalle pipas'!$B$5:$B$281,B35,'Detalle pipas'!$L$5:$L$281,"REGISTRO MANUAL*")>0,"Incluye "&COUNTIFS('Detalle pipas'!$A$5:$A$281,A35,'Detalle pipas'!$B$5:$B$281,B35,'Detalle pipas'!$L$5:$L$281,"REGISTRO MANUAL*")&" registro(s) manual(es) · ","")&IF(G35="SIN REPORTE","Falta el CSV de mermas de esta estación/producto",IF(G35="CUADRA",IF(I35>0,"Cuadra en el mes; hay pipas registradas en otro día (ver Detalle pipas)","Todo en orden"),"Revisar: "&H35&" pipa(s) sin registrar y "&J35&" compra(s) sin pipa"))&IF(COUNTIFS('Detalle pipas'!$A$5:$A$281,A35,'Detalle pipas'!$B$5:$B$281,B35,'Detalle pipas'!$M$5:$M$281,"No")>0," · "&COUNTIFS('Detalle pipas'!$A$5:$A$281,A35,'Detalle pipas'!$B$5:$B$281,B35,'Detalle pipas'!$M$5:$M$281,"No")&" pipa(s) antes del inicio del reporte (no se cuentan)","") -> Falta el CSV de mermas de esta estación/producto
A36: TOREMEX | B36: Premium | C36: Sin reporte | D36: =SUMIFS('Detalle pipas'!$G$5:$G$281,'Detalle pipas'!$A$5:$A$281,A36,'Detalle pipas'!$B$5:$B$281,B36,'Detalle pipas'!$M$5:$M$281,"Sí") -> 29973 | E36: =COUNTIFS('Detalle pipas'!$A$5:$A$281,A36,'Detalle pipas'!$B$5:$B$281,B36,'Detalle pipas'!$M$5:$M$281,"Sí") -> 2 | F36: =IF(ISNUMBER(C36),C36-D36,"") | G36: =IF(NOT(ISNUMBER(C36)),"SIN REPORTE",IF(ABS(F36)<=Parámetros!$C$8*MAX(1,E36),"CUADRA","NO CUADRA")) -> SIN REPORTE | H36: =COUNTIFS('Detalle pipas'!$A$5:$A$281,A36,'Detalle pipas'!$B$5:$B$281,B36,'Detalle pipas'!$L$5:$L$281,"NO REGISTRADA*") -> 0 | I36: =COUNTIFS('Detalle pipas'!$A$5:$A$281,A36,'Detalle pipas'!$B$5:$B$281,B36,'Detalle pipas'!$L$5:$L$281,"Registrada con desfase*") -> 0 | J36: =COUNTIFS('Compras sin pipa'!$A$5:$A$5,A36,'Compras sin pipa'!$B$5:$B$5,B36)+COUNTIFS('Registros manuales'!$A$5:$A$104,A36,'Registros manuales'!$B$5:$B$104,B36,'Registros manuales'!$G$5:$G$104,"SIN PIPA*") -> 0 | K36: =IF(COUNTIFS('Detalle pipas'!$A$5:$A$281,A36,'Detalle pipas'!$B$5:$B$281,B36,'Detalle pipas'!$L$5:$L$281,"REGISTRO MANUAL*")>0,"Incluye "&COUNTIFS('Detalle pipas'!$A$5:$A$281,A36,'Detalle pipas'!$B$5:$B$281,B36,'Detalle pipas'!$L$5:$L$281,"REGISTRO MANUAL*")&" registro(s) manual(es) · ","")&IF(G36="SIN REPORTE","Falta el CSV de mermas de esta estación/producto",IF(G36="CUADRA",IF(I36>0,"Cuadra en el mes; hay pipas registradas en otro día (ver Detalle pipas)","Todo en orden"),"Revisar: "&H36&" pipa(s) sin registrar y "&J36&" compra(s) sin pipa"))&IF(COUNTIFS('Detalle pipas'!$A$5:$A$281,A36,'Detalle pipas'!$B$5:$B$281,B36,'Detalle pipas'!$M$5:$M$281,"No")>0," · "&COUNTIFS('Detalle pipas'!$A$5:$A$281,A36,'Detalle pipas'!$B$5:$B$281,B36,'Detalle pipas'!$M$5:$M$281,"No")&" pipa(s) antes del inicio del reporte (no se cuentan)","") -> Falta el CSV de mermas de esta estación/producto
A37: TOREMEX | B37: Diesel | C37: Sin reporte | D37: =SUMIFS('Detalle pipas'!$G$5:$G$281,'Detalle pipas'!$A$5:$A$281,A37,'Detalle pipas'!$B$5:$B$281,B37,'Detalle pipas'!$M$5:$M$281,"Sí") -> 59878 | E37: =COUNTIFS('Detalle pipas'!$A$5:$A$281,A37,'Detalle pipas'!$B$5:$B$281,B37,'Detalle pipas'!$M$5:$M$281,"Sí") -> 4 | F37: =IF(ISNUMBER(C37),C37-D37,"") | G37: =IF(NOT(ISNUMBER(C37)),"SIN REPORTE",IF(ABS(F37)<=Parámetros!$C$8*MAX(1,E37),"CUADRA","NO CUADRA")) -> SIN REPORTE | H37: =COUNTIFS('Detalle pipas'!$A$5:$A$281,A37,'Detalle pipas'!$B$5:$B$281,B37,'Detalle pipas'!$L$5:$L$281,"NO REGISTRADA*") -> 0 | I37: =COUNTIFS('Detalle pipas'!$A$5:$A$281,A37,'Detalle pipas'!$B$5:$B$281,B37,'Detalle pipas'!$L$5:$L$281,"Registrada con desfase*") -> 0 | J37: =COUNTIFS('Compras sin pipa'!$A$5:$A$5,A37,'Compras sin pipa'!$B$5:$B$5,B37)+COUNTIFS('Registros manuales'!$A$5:$A$104,A37,'Registros manuales'!$B$5:$B$104,B37,'Registros manuales'!$G$5:$G$104,"SIN PIPA*") -> 0 | K37: =IF(COUNTIFS('Detalle pipas'!$A$5:$A$281,A37,'Detalle pipas'!$B$5:$B$281,B37,'Detalle pipas'!$L$5:$L$281,"REGISTRO MANUAL*")>0,"Incluye "&COUNTIFS('Detalle pipas'!$A$5:$A$281,A37,'Detalle pipas'!$B$5:$B$281,B37,'Detalle pipas'!$L$5:$L$281,"REGISTRO MANUAL*")&" registro(s) manual(es) · ","")&IF(G37="SIN REPORTE","Falta el CSV de mermas de esta estación/producto",IF(G37="CUADRA",IF(I37>0,"Cuadra en el mes; hay pipas registradas en otro día (ver Detalle pipas)","Todo en orden"),"Revisar: "&H37&" pipa(s) sin registrar y "&J37&" compra(s) sin pipa"))&IF(COUNTIFS('Detalle pipas'!$A$5:$A$281,A37,'Detalle pipas'!$B$5:$B$281,B37,'Detalle pipas'!$M$5:$M$281,"No")>0," · "&COUNTIFS('Detalle pipas'!$A$5:$A$281,A37,'Detalle pipas'!$B$5:$B$281,B37,'Detalle pipas'!$M$5:$M$281,"No")&" pipa(s) antes del inicio del reporte (no se cuentan)","") -> Falta el CSV de mermas de esta estación/producto
A38: TEOLOYUCAN | B38: Regular | C38: ='Mermas mensual'!D20 -> 143283 | D38: =SUMIFS('Detalle pipas'!$G$5:$G$281,'Detalle pipas'!$A$5:$A$281,A38,'Detalle pipas'!$B$5:$B$281,B38,'Detalle pipas'!$M$5:$M$281,"Sí") -> 143283 | E38: =COUNTIFS('Detalle pipas'!$A$5:$A$281,A38,'Detalle pipas'!$B$5:$B$281,B38,'Detalle pipas'!$M$5:$M$281,"Sí") -> 6 | F38: =IF(ISNUMBER(C38),C38-D38,"") -> 0 | G38: =IF(NOT(ISNUMBER(C38)),"SIN REPORTE",IF(ABS(F38)<=Parámetros!$C$8*MAX(1,E38),"CUADRA","NO CUADRA")) -> CUADRA | H38: =COUNTIFS('Detalle pipas'!$A$5:$A$281,A38,'Detalle pipas'!$B$5:$B$281,B38,'Detalle pipas'!$L$5:$L$281,"NO REGISTRADA*") -> 0 | I38: =COUNTIFS('Detalle pipas'!$A$5:$A$281,A38,'Detalle pipas'!$B$5:$B$281,B38,'Detalle pipas'!$L$5:$L$281,"Registrada con desfase*") -> 0 | J38: =COUNTIFS('Compras sin pipa'!$A$5:$A$5,A38,'Compras sin pipa'!$B$5:$B$5,B38)+COUNTIFS('Registros manuales'!$A$5:$A$104,A38,'Registros manuales'!$B$5:$B$104,B38,'Registros manuales'!$G$5:$G$104,"SIN PIPA*") -> 0 | K38: =IF(COUNTIFS('Detalle pipas'!$A$5:$A$281,A38,'Detalle pipas'!$B$5:$B$281,B38,'Detalle pipas'!$L$5:$L$281,"REGISTRO MANUAL*")>0,"Incluye "&COUNTIFS('Detalle pipas'!$A$5:$A$281,A38,'Detalle pipas'!$B$5:$B$281,B38,'Detalle pipas'!$L$5:$L$281,"REGISTRO MANUAL*")&" registro(s) manual(es) · ","")&IF(G38="SIN REPORTE","Falta el CSV de mermas de esta estación/producto",IF(G38="CUADRA",IF(I38>0,"Cuadra en el mes; hay pipas registradas en otro día (ver Detalle pipas)","Todo en orden"),"Revisar: "&H38&" pipa(s) sin registrar y "&J38&" compra(s) sin pipa"))&IF(COUNTIFS('Detalle pipas'!$A$5:$A$281,A38,'Detalle pipas'!$B$5:$B$281,B38,'Detalle pipas'!$M$5:$M$281,"No")>0," · "&COUNTIFS('Detalle pipas'!$A$5:$A$281,A38,'Detalle pipas'!$B$5:$B$281,B38,'Detalle pipas'!$M$5:$M$281,"No")&" pipa(s) antes del inicio del reporte (no se cuentan)","") -> Todo en orden
A39: TEOLOYUCAN | B39: Premium | C39: ='Mermas mensual'!D21 -> 30314 | D39: =SUMIFS('Detalle pipas'!$G$5:$G$281,'Detalle pipas'!$A$5:$A$281,A39,'Detalle pipas'!$B$5:$B$281,B39,'Detalle pipas'!$M$5:$M$281,"Sí") -> 30314 | E39: =COUNTIFS('Detalle pipas'!$A$5:$A$281,A39,'Detalle pipas'!$B$5:$B$281,B39,'Detalle pipas'!$M$5:$M$281,"Sí") -> 3 | F39: =IF(ISNUMBER(C39),C39-D39,"") -> 0 | G39: =IF(NOT(ISNUMBER(C39)),"SIN REPORTE",IF(ABS(F39)<=Parámetros!$C$8*MAX(1,E39),"CUADRA","NO CUADRA")) -> CUADRA | H39: =COUNTIFS('Detalle pipas'!$A$5:$A$281,A39,'Detalle pipas'!$B$5:$B$281,B39,'Detalle pipas'!$L$5:$L$281,"NO REGISTRADA*") -> 0 | I39: =COUNTIFS('Detalle pipas'!$A$5:$A$281,A39,'Detalle pipas'!$B$5:$B$281,B39,'Detalle pipas'!$L$5:$L$281,"Registrada con desfase*") -> 0 | J39: =COUNTIFS('Compras sin pipa'!$A$5:$A$5,A39,'Compras sin pipa'!$B$5:$B$5,B39)+COUNTIFS('Registros manuales'!$A$5:$A$104,A39,'Registros manuales'!$B$5:$B$104,B39,'Registros manuales'!$G$5:$G$104,"SIN PIPA*") -> 0 | K39: =IF(COUNTIFS('Detalle pipas'!$A$5:$A$281,A39,'Detalle pipas'!$B$5:$B$281,B39,'Detalle pipas'!$L$5:$L$281,"REGISTRO MANUAL*")>0,"Incluye "&COUNTIFS('Detalle pipas'!$A$5:$A$281,A39,'Detalle pipas'!$B$5:$B$281,B39,'Detalle pipas'!$L$5:$L$281,"REGISTRO MANUAL*")&" registro(s) manual(es) · ","")&IF(G39="SIN REPORTE","Falta el CSV de mermas de esta estación/producto",IF(G39="CUADRA",IF(I39>0,"Cuadra en el mes; hay pipas registradas en otro día (ver Detalle pipas)","Todo en orden"),"Revisar: "&H39&" pipa(s) sin registrar y "&J39&" compra(s) sin pipa"))&IF(COUNTIFS('Detalle pipas'!$A$5:$A$281,A39,'Detalle pipas'!$B$5:$B$281,B39,'Detalle pipas'!$M$5:$M$281,"No")>0," · "&COUNTIFS('Detalle pipas'!$A$5:$A$281,A39,'Detalle pipas'!$B$5:$B$281,B39,'Detalle pipas'!$M$5:$M$281,"No")&" pipa(s) antes del inicio del reporte (no se cuentan)","") -> Todo en orden
A40: TEOLOYUCAN | B40: Diesel | C40: ='Mermas mensual'!D22 -> 166412 | D40: =SUMIFS('Detalle pipas'!$G$5:$G$281,'Detalle pipas'!$A$5:$A$281,A40,'Detalle pipas'!$B$5:$B$281,B40,'Detalle pipas'!$M$5:$M$281,"Sí") -> 166412 | E40: =COUNTIFS('Detalle pipas'!$A$5:$A$281,A40,'Detalle pipas'!$B$5:$B$281,B40,'Detalle pipas'!$M$5:$M$281,"Sí") -> 7 | F40: =IF(ISNUMBER(C40),C40-D40,"") -> 0 | G40: =IF(NOT(ISNUMBER(C40)),"SIN REPORTE",IF(ABS(F40)<=Parámetros!$C$8*MAX(1,E40),"CUADRA","NO CUADRA")) -> CUADRA | H40: =COUNTIFS('Detalle pipas'!$A$5:$A$281,A40,'Detalle pipas'!$B$5:$B$281,B40,'Detalle pipas'!$L$5:$L$281,"NO REGISTRADA*") -> 0 | I40: =COUNTIFS('Detalle pipas'!$A$5:$A$281,A40,'Detalle pipas'!$B$5:$B$281,B40,'Detalle pipas'!$L$5:$L$281,"Registrada con desfase*") -> 0 | J40: =COUNTIFS('Compras sin pipa'!$A$5:$A$5,A40,'Compras sin pipa'!$B$5:$B$5,B40)+COUNTIFS('Registros manuales'!$A$5:$A$104,A40,'Registros manuales'!$B$5:$B$104,B40,'Registros manuales'!$G$5:$G$104,"SIN PIPA*") -> 0 | K40: =IF(COUNTIFS('Detalle pipas'!$A$5:$A$281,A40,'Detalle pipas'!$B$5:$B$281,B40,'Detalle pipas'!$L$5:$L$281,"REGISTRO MANUAL*")>0,"Incluye "&COUNTIFS('Detalle pipas'!$A$5:$A$281,A40,'Detalle pipas'!$B$5:$B$281,B40,'Detalle pipas'!$L$5:$L$281,"REGISTRO MANUAL*")&" registro(s) manual(es) · ","")&IF(G40="SIN REPORTE","Falta el CSV de mermas de esta estación/producto",IF(G40="CUADRA",IF(I40>0,"Cuadra en el mes; hay pipas registradas en otro día (ver Detalle pipas)","Todo en orden"),"Revisar: "&H40&" pipa(s) sin registrar y "&J40&" compra(s) sin pipa"))&IF(COUNTIFS('Detalle pipas'!$A$5:$A$281,A40,'Detalle pipas'!$B$5:$B$281,B40,'Detalle pipas'!$M$5:$M$281,"No")>0," · "&COUNTIFS('Detalle pipas'!$A$5:$A$281,A40,'Detalle pipas'!$B$5:$B$281,B40,'Detalle pipas'!$M$5:$M$281,"No")&" pipa(s) antes del inicio del reporte (no se cuentan)","") -> Todo en orden

Sheet Detalle pipas
A1: Detalle pipa por pipa (PIPAS DEL MES vs registro en mermas)
A2: Periodo: Agosto 2026 · Generado: 22/09/2026 17:01 · Límite SAT: merma ≤ 0.5% de la venta
A4: Estación | B4: Producto | C4: Factura | D4: BOL | E4: Fecha BOL | F4: Transportista | G4: Litros | H4: Costo unit. | I4: Fecha registro en mermas | J4: Desfase (días) | K4: Importe ($) | L4: Estado | M4: En periodo del reporte | N4: Estado original (sin registros manuales)
A5: ATB | B5: Diesel | C5: 75986 | D5: 206835 | E5: 46244 | F5: TCMC | G5: 33383 | H5: 21.565466 | K5: =G5*H5 -> 719919.95 | L5: SIN REPORTE DE MERMAS | M5: Sí | N5: SIN REPORTE DE MERMAS
A6: ATB | B6: Diesel | C6: 76542 | D6: 207673 | E6: 46254 | F6: TCMC | G6: 33384 | H6: 22.124413 | K6: =G6*H6 -> 738601.4 | L6: SIN REPORTE DE MERMAS | M6: Sí | N6: SIN REPORTE DE MERMAS
A7: ATB | B7: Premium | C7: 76149 | D7: 207103 | E7: 46247 | F7: TCMC | G7: 10198 | H7: 22.437439 | K7: =G7*H7 -> 228817 | L7: SIN REPORTE DE MERMAS | M7: Sí | N7: SIN REPORTE DE MERMAS
A8: ATB | B8: Regular | C8: 75828 | D8: 206511 | E8: 46241 | F8: TCMC | G8: 33613 | H8: 18.594645 | K8: =G8*H8 -> 625021.8 | L8: SIN REPORTE DE MERMAS | M8: Sí | N8: SIN REPORTE DE MERMAS
A9: ATB | B9: Regular | C9: 76150 | D9: 207104 | E9: 46247 | F9: TCMC | G9: 20064 | H9: 19.030109 | K9: =G9*H9 -> 381820.11 | L9: SIN REPORTE DE MERMAS | M9: Sí | N9: SIN REPORTE DE MERMAS
A10: ATB | B10: Regular | C10: 76916 | D10: 208278 | E10: 46261 | F10: TCMC | G10: 33534 | H10: 19.030242 | K10: =G10*H10 -> 638160.14 | L10: SIN REPORTE DE MERMAS | M10: Sí | N10: SIN REPORTE DE MERMAS
A11: ATP | B11: Diesel | C11: 76026 | D11: 206896 | E11: 46245 | F11: TCMC | G11: 33556 | H11: 22.039604 | K11: =G11*H11 -> 739560.95 | L11: SIN REPORTE DE MERMAS | M11: Sí | N11: SIN REPORTE DE MERMAS
A12: ATP | B12: Diesel | C12: 76721 | D12: 207971 | E12: 46258 | F12: TCMC | G12: 33482 | H12: 22.038206 | K12: =G12*H12 -> 737883.21 | L12: SIN REPORTE DE MERMAS | M12: Sí | N12: SIN REPORTE DE MERMAS
A13: ATP | B13: Premium | C13: 75604 | D13: 206094 | E13: 46238 | F13: TCMC | G13: 10139 | H13: 22.457571 | K13: =G13*H13 -> 227697.31 | L13: SIN REPORTE DE MERMAS | M13: Sí | N13: SIN REPORTE DE MERMAS
A14: ATP | B14: Regular | C14: 75603 | D14: 206095 | E14: 46238 | F14: TCMC | G14: 19997 | H14: 18.866187 | K14: =G14*H14 -> 377267.14 | L14: SIN REPORTE DE MERMAS | M14: Sí | N14: SIN REPORTE DE MERMAS
A15: ATP | B15: Regular | C15: 75870 | D15: 206662 | E15: 46242 | F15: TCMC | G15: 30008 | H15: 18.943902 | K15: =G15*H15 -> 568468.61 | L15: SIN REPORTE DE MERMAS | M15: Sí | N15: SIN REPORTE DE MERMAS
A16: ATP | B16: Regular | C16: 76349 | D16: 207441 | E16: 46251 | F16: TCMC | G16: 33388 | H16: 19.030242 | K16: =G16*H16 -> 635381.72 | L16: SIN REPORTE DE MERMAS | M16: Sí | N16: SIN REPORTE DE MERMAS
... A39: AVE FENIX | B39: Regular | C39: 77113 | D39: 208594 | E39: 46264 | F39: BENZIN | G39: 31051 | H39: 18.808979 | K39: =G39*H39 -> 584037.61 | L39: SIN REPORTE DE MERMAS | M39: Sí | N39: SIN REPORTE DE MERMAS
A40: AURORA | B40: Diesel | C40: 75496 | D40: 205859 | E40: 46235 | F40: TCMC | G40: 35778 | H40: 21.734004 | I40: 46235 | J40: 0 | K40: =G40*H40 -> 777599.2 | L40: OK - mismo día | M40: Sí | N40: OK - mismo día
A41: AURORA | B41: Diesel | C41: 75723 | D41: 206282 | E41: 46239 | F41: TCMC | G41: 35835 | H41: 21.306845 | I41: 46239 | J41: 0 | K41: =G41*H41 -> 763530.79 | L41: OK - mismo día | M41: Sí | N41: OK - mismo día
A42: AURORA | B42: Diesel | C42: 75987 | D42: 206841 | E42: 46244 | F42: TCMC | G42: 35875 | H42: 21.565466 | I42: 46246 | J42: 2 | K42: =G42*H42 -> 773661.09 | L42: Registrada con desfase de +2 día(s) | M42: Sí | N42: Registrada con desfase de +2 día(s)
A43: AURORA | B43: Diesel | C43: 76163 | D43: 207126 | E43: 46247 | F43: TCMC | G43: 35921 | H43: 22.125811 | I43: 46247 | J43: 0 | K43: =G43*H43 -> 794781.26 | L43: OK - mismo día | M43: Sí | N43: OK - mismo día
A44: AURORA | B44: Diesel | C44: 76343 | D44: 207422 | E44: 46251 | F44: TCMC | G44: 35870 | H44: 22.020964 | I44: 46251 | J44: 0 | K44: =G44*H44 -> 789891.98 | L44: OK - mismo día | M44: Sí | N44: OK - mismo día
A45: AURORA | B45: Diesel | C45: 76603 | D45: 207772 | E45: 46255 | F45: TCMC | G45: 35888 | H45: 22.124413 | I45: 46255 | J45: 0 | K45: =G45*H45 -> 794000.93 | L45: OK - mismo día | M45: Sí | N45: OK - mismo día
A46: AURORA | B46: Diesel | C46: 76837 | D46: 208097 | E46: 46259 | F46: TCMC | G46: 35957 | H46: 21.688734 | I46: 46260 | J46: 1 | K46: =G46*H46 -> 779861.81 | L46: Registrada con desfase de +1 día(s) | M46: Sí | N46: Registrada con desfase de +1 día(s)
A47: AURORA | B47: Diesel | C47: 77010 | D47: 208395 | E47: 46262 | F47: TCMC | G47: 35877 | H47: 21.688734 | I47: 46264 | J47: 2 | K47: =G47*H47 -> 778126.71 | L47: Registrada con desfase de +2 día(s) | M47: Sí | N47: Registrada con desfase de +2 día(s)
A48: AURORA | B48: Premium | C48: 75762 | D48: 206390 | E48: 46240 | F48: TCMC | G48: 35986 | H48: 22.095512 | I48: 46243 | J48: 3 | K48: =G48*H48 -> 795129.09 | L48: Registrada con desfase de +3 día(s) — FUERA DE TOLERANCIA ±2 | M48: Sí | N48: Registrada con desfase de +3 día(s) — FUERA DE TOLERANCIA ±2
A49: AURORA | B49: Premium | C49: 76797 | D49: 208057 | E49: 46259 | F49: TCMC | G49: 36063 | H49: 22.662656 | I49: 46260 | J49: 1 | K49: =G49*H49 -> 817283.36 | L49: Registrada con desfase de +1 día(s) | M49: Sí | N49: Registrada con desfase de +1 día(s)
A50: AURORA | B50: Regular | C50: 75491 | D50: 205808 | E50: 46235 | F50: TCMC | G50: 36301 | H50: 19.038601 | I50: 46235 | J50: 0 | K50: =G50*H50 -> 691120.25 | L50: OK - mismo día | M50: Sí | N50: OK - mismo día
A51: AURORA | B51: Regular | C51: 75571 | D51: 206006 | E51: 46237 | F51: TCMC | G51: 36045 | H51: 19.038601 | I51: 46238 | J51: 1 | K51: =G51*H51 -> 686246.37 | L51: Registrada con desfase de +1 día(s) | M51: Sí | N51: Registrada con desfase de +1 día(s)
... A68: AURORA | B68: Regular | C68: 77073 | D68: 208524 | E68: 46263 | F68: TCMC | G68: 35920 | H68: 19.030242 | I68: 46264 | J68: 1 | K68: =G68*H68 -> 683566.29 | L68: Registrada con desfase de +1 día(s) | M68: Sí | N68: Registrada con desfase de +1 día(s)
A69: AURORA | B69: Regular | C69: 77144 | D69: 208670 | E69: 46265 | F69: TCMC | G69: 33465 | H69: 19.030242 | I69: =IF(COUNTIFS('Registros manuales'!$E$5:$E$104,C69,'Registros manuales'!$A$5:$A$104,A69,'Registros manuales'!$B$5:$B$104,B69)>0,SUMIFS('Registros manuales'!$C$5:$C$104,'Registros manuales'!$E$5:$E$104,C69,'Registros manuales'!$A$5:$A$104,A69,'Registros manuales'!$B$5:$B$104,B69),IF(COUNTIFS('Registros manuales'!$A$5:$A$104,A69,'Registros manuales'!$B$5:$B$104,B69,'Registros manuales'!$E$5:$E$104,"",'Registros manuales'!$D$5:$D$104,">="&(G69-Parámetros!$C$8),'Registros manuales'!$D$5:$D$104,"<="&(G69+Parámetros!$C$8))>0,SUMIFS('Registros manuales'!$C$5:$C$104,'Registros manuales'!$A$5:$A$104,A69,'Registros manuales'!$B$5:$B$104,B69,'Registros manuales'!$E$5:$E$104,"",'Registros manuales'!$D$5:$D$104,">="&(G69-Parámetros!$C$8),'Registros manuales'!$D$5:$D$104,"<="&(G69+Parámetros!$C$8)),"")) | J69: =IF(I69="","",I69-E69) | K69: =G69*H69 -> 636847.05 | L69: =IF(OR(COUNTIFS('Registros manuales'!$E$5:$E$104,C69,'Registros manuales'!$A$5:$A$104,A69,'Registros manuales'!$B$5:$B$104,B69)>0,COUNTIFS('Registros manuales'!$A$5:$A$104,A69,'Registros manuales'!$B$5:$B$104,B69,'Registros manuales'!$E$5:$E$104,"",'Registros manuales'!$D$5:$D$104,">="&(G69-Parámetros!$C$8),'Registros manuales'!$D$5:$D$104,"<="&(G69+Parámetros!$C$8))>0),"REGISTRO MANUAL el "&TEXT(I69,"dd/mm"),N69) -> NO REGISTRADA (posible registro en el mes siguiente) | M69: Sí | N69: NO REGISTRADA (posible registro en el mes siguiente)
A70: COMBULUB | B70: Diesel | C70: 75602 | D70: 206058 | E70: 46238 | F70: TCMC | G70: 19962 | H70: 21.381146 | K70: =G70*H70 -> 426810.44 | L70: SIN REPORTE DE MERMAS | M70: Sí | N70: SIN REPORTE DE MERMAS
A71: COMBULUB | B71: Diesel | C71: 76028 | D71: 206921 | E71: 46245 | F71: TCMC | G71: 10131 | H71: 21.984604 | K71: =G71*H71 -> 222726.02 | L71: SIN REPORTE DE MERMAS | M71: Sí | N71: SIN REPORTE DE MERMAS
A72: COMBULUB | B72: Diesel | C72: 76344 | D72: 207425 | E72: 46251 | F72: TCMC | G72: 29880 | H72: 21.965964 | K72: =G72*H72 -> 656343 | L72: SIN REPORTE DE MERMAS | M72: Sí | N72: SIN REPORTE DE MERMAS
A73: COMBULUB | B73: Diesel | C73: 76802 | D73: 208067 | E73: 46259 | F73: TCMC | G73: 29943 | H73: 21.633734 | K73: =G73*H73 -> 647778.9 | L73: SIN REPORTE DE MERMAS | M73: Sí | N73: SIN REPORTE DE MERMAS
A74: COMBULUB | B74: Premium | C74: 76869 | D74: 208166 | E74: 46260 | F74: TCMC | G74: 10087 | H74: 22.570292 | K74: =G74*H74 -> 227666.54 | L74: SIN REPORTE DE MERMAS | M74: Sí | N74: SIN REPORTE DE MERMAS
A75: COMBULUB | B75: Regular | C75: 75601 | D75: 206057 | E75: 46238 | F75: TCMC | G75: 10159 | H75: 18.867639 | K75: =G75*H75 -> 191676.34 | L75: SIN REPORTE DE MERMAS | M75: Sí | N75: SIN REPORTE DE MERMAS
A76: COMBULUB | B76: Regular | C76: 76029 | D76: 206922 | E76: 46245 | F76: TCMC | G76: 19957 | H76: 19.01691 | K76: =G76*H76 -> 379520.47 | L76: SIN REPORTE DE MERMAS | M76: Sí | N76: SIN REPORTE DE MERMAS
A77: COMBULUB | B77: Regular | C77: 76416 | D77: 207520 | E77: 46252 | F77: TCMC | G77: 29801 | H77: 19.01691 | K77: =G77*H77 -> 566722.93 | L77: SIN REPORTE DE MERMAS | M77: Sí | N77: SIN REPORTE DE MERMAS
A78: COMBULUB | B78: Regular | C78: 76870 | D78: 208167 | E78: 46260 | F78: TCMC | G78: 19855 | H78: 19.01691 | K78: =G78*H78 -> 377580.75 | L78: SIN REPORTE DE MERMAS | M78: Sí | N78: SIN REPORTE DE MERMAS
A79: HUEHUETOCA | B79: Diesel | C79: 75490 | D79: 205811 | E79: 46235 | F79: TCMC | G79: 33447 | H79: 21.627926 | I79: 46236 | J79: 1 | K79: =G79*H79 -> 723389.24 | L79: Registrada con desfase de +1 día(s) | M79: Sí | N79: Registrada con desfase de +1 día(s)
A80: HUEHUETOCA | B80: Diesel | C80: 75713 | D80: 206257 | E80: 46239 | F80: TCMC | G80: 29862 | H80: 21.200768 | I80: 46239 | J80: 0 | K80: =G80*H80 -> 633097.33 | L80: OK - mismo día | M80: Sí | N80: OK - mismo día
A81: HUEHUETOCA | B81: Diesel | C81: 75889 | D81: 206671 | E81: 46242 | F81: TCMC | G81: 29896 | H81: 21.459389 | I81: 46242 | J81: 0 | K81: =G81*H81 -> 641549.89 | L81: OK - mismo día | M81: Sí | N81: OK - mismo día
A82: HUEHUETOCA | B82: Diesel | C82: 76111 | D82: 207037 | E82: 46246 | F82: TCMC | G82: 29953 | H82: 22.019733 | I82: 46246 | J82: 0 | K82: =G82*H82 -> 659557.06 | L82: OK - mismo día | M82: Sí | N82: OK - mismo día
A83: HUEHUETOCA | B83: Diesel | C83: 76280 | D83: 207306 | E83: 46249 | F83: TCMC | G83: 29894 | H83: 21.914887 | I83: 46249 | J83: 0 | K83: =G83*H83 -> 655123.63 | L83: OK - mismo día | M83: Sí | N83: OK - mismo día
A84: HUEHUETOCA | B84: Diesel | C84: 76503 | D84: 207619 | E84: 46253 | F84: TCMC | G84: 29966 | H84: 22.018335 | I84: 46254 | J84: 1 | K84: =G84*H84 -> 659801.43 | L84: Registrada con desfase de +1 día(s) | M84: Sí | N84: Registrada con desfase de +1 día(s)
A85: HUEHUETOCA | B85: Diesel | C85: 76666 | D85: 207852 | E85: 46256 | F85: TCMC | G85: 29915 | H85: 21.932128 | I85: 46256 | J85: 0 | K85: =G85*H85 -> 656099.61 | L85: OK - mismo día | M85: Sí | N85: OK - mismo día
A86: HUEHUETOCA | B86: Diesel | C86: 76881 | D86: 208194 | E86: 46260 | F86: TCMC | G86: 29912 | H86: 21.582657 | I86: 46260 | J86: 0 | K86: =G86*H86 -> 645580.44 | L86: OK - mismo día | M86: Sí | N86: OK - mismo día
A87: HUEHUETOCA | B87: Diesel | C87: 77068 | D87: 208494 | E87: 46263 | F87: TCMC | G87: 30094 | H87: 21.582657 | I87: 46263 | J87: 0 | K87: =G87*H87 -> 649508.48 | L87: OK - mismo día | M87: Sí | N87: OK - mismo día
A88: HUEHUETOCA | B88: Premium | C88: 76201 | D88: 207182 | E88: 46248 | F88: TCMC | G88: 10181 | H88: 22.179071 | I88: 46248 | J88: 0 | K88: =G88*H88 -> 225805.12 | L88: OK - mismo día | M88: Sí | N88: OK - mismo día
A89: HUEHUETOCA | B89: Premium | C89: 76202 | D89: 207183 | E89: 46248 | F89: TCMC | G89: 19977 | H89: 22.179071 | I89: 46248 | J89: 0 | K89: =G89*H89 -> 443071.3 | L89: OK - mismo día | M89: Sí | N89: OK - mismo día
A90: HUEHUETOCA | B90: Premium | C90: 77150 | D90: 208691 | E90: 46265 | F90: TCMC | G90: 29943 | H90: 22.645421 | I90: 46265 | J90: 0 | K90: =G90*H90 -> 678071.84 | L90: OK - mismo día | M90: Sí | N90: OK - mismo día
... A177: IXTAZACUALA | B177: Premium | C177: 77146 | D177: 208677 | E177: 46265 | F177: TCMC | G177: 29905 | H177: 22.821499 | I177: 46265 | J177: 0 | K177: =G177*H177 -> 682476.93 | L177: OK - mismo día | M177: Sí | N177: OK - mismo día
A178: IXTAZACUALA | B178: Regular | C178: 75492 | D178: 205832 | E178: 46235 | F178: TCMC | G178: 10080 | H178: 19.200053 | K178: =G178*H178 -> 193536.53 | L178: FUERA DEL PERIODO DEL REPORTE (el reporte de mermas inicia el 03/08) | M178: No | N178: FUERA DEL PERIODO DEL REPORTE (el reporte de mermas inicia el 03/08)
A179: IXTAZACUALA | B179: Regular | C179: 75493 | D179: 205833 | E179: 46235 | F179: TCMC | G179: 19797 | H179: 19.200053 | K179: =G179*H179 -> 380103.45 | L179: FUERA DEL PERIODO DEL REPORTE (el reporte de mermas inicia el 03/08) | M179: No | N179: FUERA DEL PERIODO DEL REPORTE (el reporte de mermas inicia el 03/08)
A180: IXTAZACUALA | B180: Regular | C180: 75656 | D180: 206118 | E180: 46238 | F180: TCMC | G180: 29821 | H180: 19.027639 | I180: 46238 | J180: 0 | K180: =G180*H180 -> 567423.22 | L180: OK - mismo día | M180: Sí | N180: OK - mismo día
A181: IXTAZACUALA | B181: Regular | C181: 75849 | D181: 206540 | E181: 46241 | F181: TCMC | G181: 29839 | H181: 18.708385 | I181: 46241 | J181: 0 | K181: =G181*H181 -> 558239.5 | L181: OK - mismo día | M181: Sí | N181: OK - mismo día
A182: IXTAZACUALA | B182: Regular | C182: 76061 | D182: 206959 | E182: 46245 | F182: TCMC | G182: 29907 | H182: 19.17691 | I182: 46245 | J182: 0 | K182: =G182*H182 -> 573523.85 | L182: OK - mismo día | M182: Sí | N182: OK - mismo día
A183: IXTAZACUALA | B183: Regular | C183: 76137 | D183: 207102 | E183: 46247 | F183: TCMC | G183: 30152 | H183: 19.17691 | I183: 46247 | J183: 0 | K183: =G183*H183 -> 578222.19 | L183: OK - mismo día | M183: Sí | N183: OK - mismo día
A184: IXTAZACUALA | B184: Regular | C184: 76273 | D184: 207304 | E184: 46249 | F184: TCMC | G184: 29864 | H184: 19.17691 | I184: 46249 | J184: 0 | K184: =G184*H184 -> 572699.24 | L184: OK - mismo día | M184: Sí | N184: OK - mismo día
A185: IXTAZACUALA | B185: Regular | C185: 76320 | D185: 207396 | E185: 46251 | F185: TCMC | G185: 30154 | H185: 19.17691 | I185: 46251 | J185: 0 | K185: =G185*H185 -> 578260.54 | L185: OK - mismo día | M185: Sí | N185: OK - mismo día
A186: IXTAZACUALA | B186: Regular | C186: 76529 | D186: 207656 | E186: 46254 | F186: TCMC | G186: 29997 | H186: 19.17691 | I186: 46254 | J186: 0 | K186: =G186*H186 -> 575249.77 | L186: OK - mismo día | M186: Sí | N186: OK - mismo día
A187: IXTAZACUALA | B187: Regular | C187: 76669 | D187: 207860 | E187: 46256 | F187: TCMC | G187: 33332 | H187: 19.17691 | I187: 46256 | J187: 0 | K187: =G187*H187 -> 639204.76 | L187: OK - mismo día | M187: Sí | N187: OK - mismo día
A188: IXTAZACUALA | B188: Regular | C188: 76824 | D188: 208092 | E188: 46259 | F188: TCMC | G188: 29922 | H188: 19.17691 | I188: 46259 | J188: 0 | K188: =G188*H188 -> 573811.5 | L188: OK - mismo día | M188: Sí | N188: OK - mismo día
A189: IXTAZACUALA | B189: Regular | C189: 76943 | D189: 208291 | E189: 46261 | F189: TCMC | G189: 29925 | H189: 19.17691 | I189: 46261 | J189: 0 | K189: =G189*H189 -> 573869.03 | L189: OK - mismo día | M189: Sí | N189: OK - mismo día
A190: IXTAZACUALA | B190: Regular | C190: 77110 | D190: 208602 | E190: 46264 | F190: TCMC | G190: 29910 | H190: 19.17691 | I190: 46264 | J190: 0 | K190: =G190*H190 -> 573581.38 | L190: OK - mismo día | M190: Sí | N190: OK - mismo día
A191: TREHER | B191: Diesel | C191: 75473 | D191: 205797 | E191: 46235 | F191: TCMC | G191: 29982 | H191: 21.834004 | K191: =G191*H191 -> 654627.11 | L191: FUERA DEL PERIODO DEL REPORTE (el reporte de mermas inicia el 03/08) | M191: No | N191: FUERA DEL PERIODO DEL REPORTE (el reporte de mermas inicia el 03/08)
A192: TREHER | B192: Diesel | C192: 75599 | D192: 206037 | E192: 46237 | F192: TCMC | G192: 10051 | H192: 21.834004 | I192: 46237 | J192: 0 | K192: =G192*H192 -> 219453.57 | L192: OK - mismo día | M192: Sí | N192: OK - mismo día
A193: TREHER | B193: Diesel | C193: 75600 | D193: 206038 | E193: 46237 | F193: TCMC | G193: 19789 | H193: 21.834004 | I193: 46237 | J193: 0 | K193: =G193*H193 -> 432073.11 | L193: OK - mismo día | M193: Sí | N193: OK - mismo día
A194: TREHER | B194: Diesel | C194: 75866 | D194: 206621 | E194: 46242 | F194: TCMC | G194: 36004 | H194: 21.665466 | I194: 46242 | J194: 0 | K194: =G194*H194 -> 780043.44 | L194: OK - mismo día | M194: Sí | N194: OK - mismo día
A195: TREHER | B195: Diesel | C195: 75989 | D195: 206840 | E195: 46244 | F195: TCMC | G195: 29893 | H195: 21.665466 | I195: 46244 | J195: 0 | K195: =G195*H195 -> 647645.78 | L195: OK - mismo día | M195: Sí | N195: OK - mismo día
A196: TREHER | B196: Diesel | C196: 76226 | D196: 207210 | E196: 46248 | F196: TCMC | G196: 29934 | H196: 22.225811 | I196: 46248 | J196: 0 | K196: =G196*H196 -> 665307.43 | L196: OK - mismo día | M196: Sí | N196: OK - mismo día
A197: TREHER | B197: Diesel | C197: 76390 | D197: 207479 | E197: 46252 | F197: TCMC | G197: 10117 | H197: 22.224011 | I197: 46252 | J197: 0 | K197: =G197*H197 -> 224840.32 | L197: OK - mismo día | M197: Sí | N197: OK - mismo día
A198: TREHER | B198: Diesel | C198: 76551 | D198: 207684 | E198: 46254 | F198: TCMC | G198: 10064 | H198: 22.224413 | I198: 46254 | J198: 0 | K198: =G198*H198 -> 223666.49 | L198: OK - mismo día | M198: Sí | N198: OK - mismo día
A199: TREHER | B199: Diesel | C199: 76552 | D199: 207685 | E199: 46254 | F199: TCMC | G199: 19823 | H199: 22.224413 | I199: 46254 | J199: 0 | K199: =G199*H199 -> 440554.54 | L199: OK - mismo día | M199: Sí | N199: OK - mismo día
A200: TREHER | B200: Diesel | C200: 76663 | D200: 207847 | E200: 46256 | F200: TCMC | G200: 29937 | H200: 22.138206 | I200: 46256 | J200: 0 | K200: =G200*H200 -> 662751.47 | L200: OK - mismo día | M200: Sí | N200: OK - mismo día
A201: TREHER | B201: Diesel | C201: 76861 | D201: 208006 | E201: 46259 | F201: TCMC | G201: 10123 | H201: 21.788734 | I201: 46259 | J201: 0 | K201: =G201*H201 -> 220567.35 | L201: OK - mismo día | M201: Sí | N201: OK - mismo día
A202: TREHER | B202: Diesel | C202: 76866 | D202: 208170 | E202: 46260 | F202: TCMC | G202: 29936 | H202: 21.788734 | I202: 46260 | J202: 0 | K202: =G202*H202 -> 652267.54 | L202: OK - mismo día | M202: Sí | N202: OK - mismo día
A203: TREHER | B203: Diesel | C203: 77066 | D203: 208487 | E203: 46263 | F203: TCMC | G203: 30099 | H203: 21.788734 | I203: 46263 | J203: 0 | K203: =G203*H203 -> 655819.1 | L203: OK - mismo día | M203: Sí | N203: OK - mismo día
... A205: TREHER | B205: Premium | C205: 76389 | D205: 207480 | E205: 46252 | F205: TCMC | G205: 20083 | H205: 22.656748 | I205: 46252 | J205: 0 | K205: =G205*H205 -> 455015.47 | L205: OK - mismo día | M205: Sí | N205: OK - mismo día
A206: TREHER | B206: Regular | C206: 75474 | D206: 205798 | E206: 46235 | F206: TCMC | G206: 30199 | H206: 19.200053 | K206: =G206*H206 -> 579822.4 | L206: FUERA DEL PERIODO DEL REPORTE (el reporte de mermas inicia el 03/08) | M206: No | N206: FUERA DEL PERIODO DEL REPORTE (el reporte de mermas inicia el 03/08)
A207: TREHER | B207: Regular | C207: 75724 | D207: 206280 | E207: 46239 | F207: TCMC | G207: 19740 | H207: 18.833385 | I207: 46239 | J207: 0 | K207: =G207*H207 -> 371771.02 | L207: OK - mismo día | M207: Sí | N207: OK - mismo día
A208: TREHER | B208: Regular | C208: 75725 | D208: 206279 | E208: 46239 | F208: TCMC | G208: 10025 | H208: 18.833385 | I208: 46239 | J208: 0 | K208: =G208*H208 -> 188804.68 | L208: OK - mismo día | M208: Sí | N208: OK - mismo día
A209: TREHER | B209: Regular | C209: 75867 | D209: 206622 | E209: 46242 | F209: TCMC | G209: 10136 | H209: 18.918289 | I209: 46242 | J209: 0 | K209: =G209*H209 -> 191755.78 | L209: OK - mismo día | M209: Sí | N209: OK - mismo día
A210: TREHER | B210: Regular | C210: 75868 | D210: 206623 | E210: 46242 | F210: TCMC | G210: 19911 | H210: 18.918289 | I210: 46242 | J210: 0 | K210: =G210*H210 -> 376682.05 | L210: OK - mismo día | M210: Sí | N210: OK - mismo día
A211: TREHER | B211: Regular | C211: 75990 | D211: 206844 | E211: 46244 | F211: TCMC | G211: 10056 | H211: 18.918289 | I211: 46244 | J211: 0 | K211: =G211*H211 -> 190242.31 | L211: OK - mismo día | M211: Sí | N211: OK - mismo día
A212: TREHER | B212: Regular | C212: 76106 | D212: 207034 | E212: 46246 | F212: TCMC | G212: 10104 | H212: 19.17691 | I212: 46246 | J212: 0 | K212: =G212*H212 -> 193763.5 | L212: OK - mismo día | M212: Sí | N212: OK - mismo día
A213: TREHER | B213: Regular | C213: 76107 | D213: 207035 | E213: 46246 | F213: TCMC | G213: 19883 | H213: 19.17691 | I213: 46246 | J213: 0 | K213: =G213*H213 -> 381294.5 | L213: OK - mismo día | M213: Sí | N213: OK - mismo día
A214: TREHER | B214: Regular | C214: 76227 | D214: 207259 | E214: 46249 | F214: TCMC | G214: 10132 | H214: 19.17691 | I214: 46249 | J214: 0 | K214: =G214*H214 -> 194300.45 | L214: OK - mismo día | M214: Sí | N214: OK - mismo día
A215: TREHER | B215: Regular | C215: 76228 | D215: 207260 | E215: 46249 | F215: TCMC | G215: 19875 | H215: 19.17691 | I215: 46249 | J215: 0 | K215: =G215*H215 -> 381141.09 | L215: OK - mismo día | M215: Sí | N215: OK - mismo día
A216: TREHER | B216: Regular | C216: 76419 | D216: 207589 | E216: 46253 | F216: TCMC | G216: 10096 | H216: 19.17691 | I216: 46253 | J216: 0 | K216: =G216*H216 -> 193610.08 | L216: OK - mismo día | M216: Sí | N216: OK - mismo día
A217: TREHER | B217: Regular | C217: 76420 | D217: 207590 | E217: 46253 | F217: TCMC | G217: 19856 | H217: 19.17691 | I217: 46253 | J217: 0 | K217: =G217*H217 -> 380776.72 | L217: OK - mismo día | M217: Sí | N217: OK - mismo día
A218: TREHER | B218: Regular | C218: 76604 | D218: 207773 | E218: 46255 | F218: TCMC | G218: 10082 | H218: 19.17691 | I218: 46255 | J218: 0 | K218: =G218*H218 -> 193341.61 | L218: OK - mismo día | M218: Sí | N218: OK - mismo día
... A223: TREHER | B223: Regular | C223: 77067 | D223: 208488 | E223: 46263 | F223: TCMC | G223: 30070 | H223: 19.17691 | I223: 46263 | J223: 0 | K223: =G223*H223 -> 576649.68 | L223: OK - mismo día | M223: Sí | N223: OK - mismo día
A224: TH | B224: Diesel | C224: 75655 | D224: 206110 | E224: 46238 | F224: TCMC | G224: 33369 | H224: 21.536146 | K224: =G224*H224 -> 718639.66 | L224: SIN REPORTE DE MERMAS | M224: Sí | N224: SIN REPORTE DE MERMAS
A225: TH | B225: Diesel | C225: 75711 | D225: 206253 | E225: 46239 | F225: TCMC | G225: 33339 | H225: 21.406845 | K225: =G225*H225 -> 713682.81 | L225: SIN REPORTE DE MERMAS | M225: Sí | N225: SIN REPORTE DE MERMAS
A226: TH | B226: Diesel | C226: 75825 | D226: 206472 | E226: 46241 | F226: TCMC | G226: 33485 | H226: 21.406845 | K226: =G226*H226 -> 716808.2 | L226: SIN REPORTE DE MERMAS | M226: Sí | N226: SIN REPORTE DE MERMAS
A227: TH | B227: Diesel | C227: 75869 | D227: 206629 | E227: 46242 | F227: TCMC | G227: 33464 | H227: 21.665466 | K227: =G227*H227 -> 725013.15 | L227: SIN REPORTE DE MERMAS | M227: Sí | N227: SIN REPORTE DE MERMAS
A228: TH | B228: Diesel | C228: 75985 | D228: 206831 | E228: 46244 | F228: TCMC | G228: 33366 | H228: 21.665466 | K228: =G228*H228 -> 722889.94 | L228: SIN REPORTE DE MERMAS | M228: Sí | N228: SIN REPORTE DE MERMAS
A229: TH | B229: Diesel | C229: 76073 | D229: 206956 | E229: 46245 | F229: TCMC | G229: 33473 | H229: 22.139604 | K229: =G229*H229 -> 741078.96 | L229: SIN REPORTE DE MERMAS | M229: Sí | N229: SIN REPORTE DE MERMAS
A230: TH | B230: Diesel | C230: 76152 | D230: 207105 | E230: 46247 | F230: TCMC | G230: 33561 | H230: 22.225811 | K230: =G230*H230 -> 745920.44 | L230: SIN REPORTE DE MERMAS | M230: Sí | N230: SIN REPORTE DE MERMAS
...

Sheet Registros manuales
A1: Registros manuales de pipas
A2: Captura aquí las pipas que faltaban por registrar (celdas amarillas). Todo el libro se recalcula solo; no hay que volver a correr el script.
A4: Estación | B4: Producto | C4: Fecha registro | D4: Litros | E4: Factura (opcional) | F4: Comentario | G4: Resultado
G5: =IF(AND(A5="",D5=""),"",IF(OR(A5="",B5="",C5="",D5=""),"FALTAN DATOS: Estación, Producto, Fecha y Litros son obligatorios",IF(COUNTIFS('Detalle diario'!$A$5:$A$550,A5,'Detalle diario'!$B$5:$B$550,B5,'Detalle diario'!$C$5:$C$550,C5)=0,"NO APLICA: no hay reporte de mermas de esa estación/producto en esa fecha",IF(E5<>"",IF(COUNTIFS('Detalle pipas'!$C$5:$C$281,E5,'Detalle pipas'!$A$5:$A$281,A5,'Detalle pipas'!$B$5:$B$281,B5,'Detalle pipas'!$N$5:$N$281,"NO REGISTRADA*")>0,"APLICADO: registra la factura "&E5,IF(COUNTIFS('Detalle pipas'!$C$5:$C$281,E5,'Detalle pipas'!$A$5:$A$281,A5,'Detalle pipas'!$B$5:$B$281,B5)>0,"OJO: la factura "&E5&" ya estaba registrada; se estaría sumando doble","SIN PIPA: la factura "&E5&" no existe en PIPAS DEL MES para esa estación/producto")),IF(COUNTIFS('Detalle pipas'!$A$5:$A$281,A5,'Detalle pipas'!$B$5:$B$281,B5,'Detalle pipas'!$G$5:$G$281,">="&(D5-Parámetros!$C$8),'Detalle pipas'!$G$5:$G$281,"<="&(D5+Parámetros!$C$8),'Detalle pipas'!$N$5:$N$281,"NO REGISTRADA*")>0,"APLICADO: registra la pipa de "&TEXT(D5,"#,##0")&" L","SIN PIPA: no hay pipa pendiente con esos litros (revisa litros o pon la factura)")))))
G6: =IF(AND(A6="",D6=""),"",IF(OR(A6="",B6="",C6="",D6=""),"FALTAN DATOS: Estación, Producto, Fecha y Litros son obligatorios",IF(COUNTIFS('Detalle diario'!$A$5:$A$550,A6,'Detalle diario'!$B$5:$B$550,B6,'Detalle diario'!$C$5:$C$550,C6)=0,"NO APLICA: no hay reporte de mermas de esa estación/producto en esa fecha",IF(E6<>"",IF(COUNTIFS('Detalle pipas'!$C$5:$C$281,E6,'Detalle pipas'!$A$5:$A$281,A6,'Detalle pipas'!$B$5:$B$281,B6,'Detalle pipas'!$N$5:$N$281,"NO REGISTRADA*")>0,"APLICADO: registra la factura "&E6,IF(COUNTIFS('Detalle pipas'!$C$5:$C$281,E6,'Detalle pipas'!$A$5:$A$281,A6,'Detalle pipas'!$B$5:$B$281,B6)>0,"OJO: la factura "&E6&" ya estaba registrada; se estaría sumando doble","SIN PIPA: la factura "&E6&" no existe en PIPAS DEL MES para esa estación/producto")),IF(COUNTIFS('Detalle pipas'!$A$5:$A$281,A6,'Detalle pipas'!$B$5:$B$281,B6,'Detalle pipas'!$G$5:$G$281,">="&(D6-Parámetros!$C$8),'Detalle pipas'!$G$5:$G$281,"<="&(D6+Parámetros!$C$8),'Detalle pipas'!$N$5:$N$281,"NO REGISTRADA*")>0,"APLICADO: registra la pipa de "&TEXT(D6,"#,##0")&" L","SIN PIPA: no hay pipa pendiente con esos litros (revisa litros o pon la factura)")))))
G7: =IF(AND(A7="",D7=""),"",IF(OR(A7="",B7="",C7="",D7=""),"FALTAN DATOS: Estación, Producto, Fecha y Litros son obligatorios",IF(COUNTIFS('Detalle diario'!$A$5:$A$550,A7,'Detalle diario'!$B$5:$B$550,B7,'Detalle diario'!$C$5:$C$550,C7)=0,"NO APLICA: no hay reporte de mermas de esa estación/producto en esa fecha",IF(E7<>"",IF(COUNTIFS('Detalle pipas'!$C$5:$C$281,E7,'Detalle pipas'!$A$5:$A$281,A7,'Detalle pipas'!$B$5:$B$281,B7,'Detalle pipas'!$N$5:$N$281,"NO REGISTRADA*")>0,"APLICADO: registra la factura "&E7,IF(COUNTIFS('Detalle pipas'!$C$5:$C$281,E7,'Detalle pipas'!$A$5:$A$281,A7,'Detalle pipas'!$B$5:$B$281,B7)>0,"OJO: la factura "&E7&" ya estaba registrada; se estaría sumando doble","SIN PIPA: la factura "&E7&" no existe en PIPAS DEL MES para esa estación/producto")),IF(COUNTIFS('Detalle pipas'!$A$5:$A$281,A7,'Detalle pipas'!$B$5:$B$281,B7,'Detalle pipas'!$G$5:$G$281,">="&(D7-Parámetros!$C$8),'Detalle pipas'!$G$5:$G$281,"<="&(D7+Parámetros!$C$8),'Detalle pipas'!$N$5:$N$281,"NO REGISTRADA*")>0,"APLICADO: registra la pipa de "&TEXT(D7,"#,##0")&" L","SIN PIPA: no hay pipa pendiente con esos litros (revisa litros o pon la factura)")))))
G8: =IF(AND(A8="",D8=""),"",IF(OR(A8="",B8="",C8="",D8=""),"FALTAN DATOS: Estación, Producto, Fecha y Litros son obligatorios",IF(COUNTIFS('Detalle diario'!$A$5:$A$550,A8,'Detalle diario'!$B$5:$B$550,B8,'Detalle diario'!$C$5:$C$550,C8)=0,"NO APLICA: no hay reporte de mermas de esa estación/producto en esa fecha",IF(E8<>"",IF(COUNTIFS('Detalle pipas'!$C$5:$C$281,E8,'Detalle pipas'!$A$5:$A$281,A8,'Detalle pipas'!$B$5:$B$281,B8,'Detalle pipas'!$N$5:$N$281,"NO REGISTRADA*")>0,"APLICADO: registra la factura "&E8,IF(COUNTIFS('Detalle pipas'!$C$5:$C$281,E8,'Detalle pipas'!$A$5:$A$281,A8,'Detalle pipas'!$B$5:$B$281,B8)>0,"OJO: la factura "&E8&" ya estaba registrada; se estaría sumando doble","SIN PIPA: la factura "&E8&" no existe en PIPAS DEL MES para esa estación/producto")),IF(COUNTIFS('Detalle pipas'!$A$5:$A$281,A8,'Detalle pipas'!$B$5:$B$281,B8,'Detalle pipas'!$G$5:$G$281,">="&(D8-Parámetros!$C$8),'Detalle pipas'!$G$5:$G$281,"<="&(D8+Parámetros!$C$8),'Detalle pipas'!$N$5:$N$281,"NO REGISTRADA*")>0,"APLICADO: registra la pipa de "&TEXT(D8,"#,##0")&" L","SIN PIPA: no hay pipa pendiente con esos litros (revisa litros o pon la factura)")))))
G9: =IF(AND(A9="",D9=""),"",IF(OR(A9="",B9="",C9="",D9=""),"FALTAN DATOS: Estación, Producto, Fecha y Litros son obligatorios",IF(COUNTIFS('Detalle diario'!$A$5:$A$550,A9,'Detalle diario'!$B$5:$B$550,B9,'Detalle diario'!$C$5:$C$550,C9)=0,"NO APLICA: no hay reporte de mermas de esa estación/producto en esa fecha",IF(E9<>"",IF(COUNTIFS('Detalle pipas'!$C$5:$C$281,E9,'Detalle pipas'!$A$5:$A$281,A9,'Detalle pipas'!$B$5:$B$281,B9,'Detalle pipas'!$N$5:$N$281,"NO REGISTRADA*")>0,"APLICADO: registra la factura "&E9,IF(COUNTIFS('Detalle pipas'!$C$5:$C$281,E9,'Detalle pipas'!$A$5:$A$281,A9,'Detalle pipas'!$B$5:$B$281,B9)>0,"OJO: la factura "&E9&" ya estaba registrada; se estaría sumando doble","SIN PIPA: la factura "&E9&" no existe en PIPAS DEL MES para esa estación/producto")),IF(COUNTIFS('Detalle pipas'!$A$5:$A$281,A9,'Detalle pipas'!$B$5:$B$281,B9,'Detalle pipas'!$G$5:$G$281,">="&(D9-Parámetros!$C$8),'Detalle pipas'!$G$5:$G$281,"<="&(D9+Parámetros!$C$8),'Detalle pipas'!$N$5:$N$281,"NO REGISTRADA*")>0,"APLICADO: registra la pipa de "&TEXT(D9,"#,##0")&" L","SIN PIPA: no hay pipa pendiente con esos litros (revisa litros o pon la factura)")))))
G10: =IF(AND(A10="",D10=""),"",IF(OR(A10="",B10="",C10="",D10=""),"FALTAN DATOS: Estación, Producto, Fecha y Litros son obligatorios",IF(COUNTIFS('Detalle diario'!$A$5:$A$550,A10,'Detalle diario'!$B$5:$B$550,B10,'Detalle diario'!$C$5:$C$550,C10)=0,"NO APLICA: no hay reporte de mermas de esa estación/producto en esa fecha",IF(E10<>"",IF(COUNTIFS('Detalle pipas'!$C$5:$C$281,E10,'Detalle pipas'!$A$5:$A$281,A10,'Detalle pipas'!$B$5:$B$281,B10,'Detalle pipas'!$N$5:$N$281,"NO REGISTRADA*")>0,"APLICADO: registra la factura "&E10,IF(COUNTIFS('Detalle pipas'!$C$5:$C$281,E10,'Detalle pipas'!$A$5:$A$281,A10,'Detalle pipas'!$B$5:$B$281,B10)>0,"OJO: la factura "&E10&" ya estaba registrada; se estaría sumando doble","SIN PIPA: la factura "&E10&" no existe en PIPAS DEL MES para esa estación/producto")),IF(COUNTIFS('Detalle pipas'!$A$5:$A$281,A10,'Detalle pipas'!$B$5:$B$281,B10,'Detalle pipas'!$G$5:$G$281,">="&(D10-Parámetros!$C$8),'Detalle pipas'!$G$5:$G$281,"<="&(D10+Parámetros!$C$8),'Detalle pipas'!$N$5:$N$281,"NO REGISTRADA*")>0,"APLICADO: registra la pipa de "&TEXT(D10,"#,##0")&" L","SIN PIPA: no hay pipa pendiente con esos litros (revisa litros o pon la factura)")))))
G11: =IF(AND(A11="",D11=""),"",IF(OR(A11="",B11="",C11="",D11=""),"FALTAN DATOS: Estación, Producto, Fecha y Litros son obligatorios",IF(COUNTIFS('Detalle diario'!$A$5:$A$550,A11,'Detalle diario'!$B$5:$B$550,B11,'Detalle diario'!$C$5:$C$550,C11)=0,"NO APLICA: no hay reporte de mermas de esa estación/producto en esa fecha",IF(E11<>"",IF(COUNTIFS('Detalle pipas'!$C$5:$C$281,E11,'Detalle pipas'!$A$5:$A$281,A11,'Detalle pipas'!$B$5:$B$281,B11,'Detalle pipas'!$N$5:$N$281,"NO REGISTRADA*")>0,"APLICADO: registra la factura "&E11,IF(COUNTIFS('Detalle pipas'!$C$5:$C$281,E11,'Detalle pipas'!$A$5:$A$281,A11,'Detalle pipas'!$B$5:$B$281,B11)>0,"OJO: la factura "&E11&" ya estaba registrada; se estaría sumando doble","SIN PIPA: la factura "&E11&" no existe en PIPAS DEL MES para esa estación/producto")),IF(COUNTIFS('Detalle pipas'!$A$5:$A$281,A11,'Detalle pipas'!$B$5:$B$281,B11,'Detalle pipas'!$G$5:$G$281,">="&(D11-Parámetros!$C$8),'Detalle pipas'!$G$5:$G$281,"<="&(D11+Parámetros!$C$8),'Detalle pipas'!$N$5:$N$281,"NO REGISTRADA*")>0,"APLICADO: registra la pipa de "&TEXT(D11,"#,##0")&" L","SIN PIPA: no hay pipa pendiente con esos litros (revisa litros o pon la factura)")))))
G12: =IF(AND(A12="",D12=""),"",IF(OR(A12="",B12="",C12="",D12=""),"FALTAN DATOS: Estación, Producto, Fecha y Litros son obligatorios",IF(COUNTIFS('Detalle diario'!$A$5:$A$550,A12,'Detalle diario'!$B$5:$B$550,B12,'Detalle diario'!$C$5:$C$550,C12)=0,"NO APLICA: no hay reporte de mermas de esa estación/producto en esa fecha",IF(E12<>"",IF(COUNTIFS('Detalle pipas'!$C$5:$C$281,E12,'Detalle pipas'!$A$5:$A$281,A12,'Detalle pipas'!$B$5:$B$281,B12,'Detalle pipas'!$N$5:$N$281,"NO REGISTRADA*")>0,"APLICADO: registra la factura "&E12,IF(COUNTIFS('Detalle pipas'!$C$5:$C$281,E12,'Detalle pipas'!$A$5:$A$281,A12,'Detalle pipas'!$B$5:$B$281,B12)>0,"OJO: la factura "&E12&" ya estaba registrada; se estaría sumando doble","SIN PIPA: la factura "&E12&" no existe en PIPAS DEL MES para esa estación/producto")),IF(COUNTIFS('Detalle pipas'!$A$5:$A$281,A12,'Detalle pipas'!$B$5:$B$281,B12,'Detalle pipas'!$G$5:$G$281,">="&(D12-Parámetros!$C$8),'Detalle pipas'!$G$5:$G$281,"<="&(D12+Parámetros!$C$8),'Detalle pipas'!$N$5:$N$281,"NO REGISTRADA*")>0,"APLICADO: registra la pipa de "&TEXT(D12,"#,##0")&" L","SIN PIPA: no hay pipa pendiente con esos litros (revisa litros o pon la factura)")))))
G13: =IF(AND(A13="",D13=""),"",IF(OR(A13="",B13="",C13="",D13=""),"FALTAN DATOS: Estación, Producto, Fecha y Litros son obligatorios",IF(COUNTIFS('Detalle diario'!$A$5:$A$550,A13,'Detalle diario'!$B$5:$B$550,B13,'Detalle diario'!$C$5:$C$550,C13)=0,"NO APLICA: no hay reporte de mermas de esa estación/producto en esa fecha",IF(E13<>"",IF(COUNTIFS('Detalle pipas'!$C$5:$C$281,E13,'Detalle pipas'!$A$5:$A$281,A13,'Detalle pipas'!$B$5:$B$281,B13,'Detalle pipas'!$N$5:$N$281,"NO REGISTRADA*")>0,"APLICADO: registra la factura "&E13,IF(COUNTIFS('Detalle pipas'!$C$5:$C$281,E13,'Detalle pipas'!$A$5:$A$281,A13,'Detalle pipas'!$B$5:$B$281,B13)>0,"OJO: la factura "&E13&" ya estaba registrada; se estaría sumando doble","SIN PIPA: la factura "&E13&" no existe en PIPAS DEL MES para esa estación/producto")),IF(COUNTIFS('Detalle pipas'!$A$5:$A$281,A13,'Detalle pipas'!$B$5:$B$281,B13,'Detalle pipas'!$G$5:$G$281,">="&(D13-Parámetros!$C$8),'Detalle pipas'!$G$5:$G$281,"<="&(D13+Parámetros!$C$8),'Detalle pipas'!$N$5:$N$281,"NO REGISTRADA*")>0,"APLICADO: registra la pipa de "&TEXT(D13,"#,##0")&" L","SIN PIPA: no hay pipa pendiente con esos litros (revisa litros o pon la factura)")))))
G14: =IF(AND(A14="",D14=""),"",IF(OR(A14="",B14="",C14="",D14=""),"FALTAN DATOS: Estación, Producto, Fecha y Litros son obligatorios",IF(COUNTIFS('Detalle diario'!$A$5:$A$550,A14,'Detalle diario'!$B$5:$B$550,B14,'Detalle diario'!$C$5:$C$550,C14)=0,"NO APLICA: no hay reporte de mermas de esa estación/producto en esa fecha",IF(E14<>"",IF(COUNTIFS('Detalle pipas'!$C$5:$C$281,E14,'Detalle pipas'!$A$5:$A$281,A14,'Detalle pipas'!$B$5:$B$281,B14,'Detalle pipas'!$N$5:$N$281,"NO REGISTRADA*")>0,"APLICADO: registra la factura "&E14,IF(COUNTIFS('Detalle pipas'!$C$5:$C$281,E14,'Detalle pipas'!$A$5:$A$281,A14,'Detalle pipas'!$B$5:$B$281,B14)>0,"OJO: la factura "&E14&" ya estaba registrada; se estaría sumando doble","SIN PIPA: la factura "&E14&" no existe en PIPAS DEL MES para esa estación/producto")),IF(COUNTIFS('Detalle pipas'!$A$5:$A$281,A14,'Detalle pipas'!$B$5:$B$281,B14,'Detalle pipas'!$G$5:$G$281,">="&(D14-Parámetros!$C$8),'Detalle pipas'!$G$5:$G$281,"<="&(D14+Parámetros!$C$8),'Detalle pipas'!$N$5:$N$281,"NO REGISTRADA*")>0,"APLICADO: registra la pipa de "&TEXT(D14,"#,##0")&" L","SIN PIPA: no hay pipa pendiente con esos litros (revisa litros o pon la factura)")))))
G15: =IF(AND(A15="",D15=""),"",IF(OR(A15="",B15="",C15="",D15=""),"FALTAN DATOS: Estación, Producto, Fecha y Litros son obligatorios",IF(COUNTIFS('Detalle diario'!$A$5:$A$550,A15,'Detalle diario'!$B$5:$B$550,B15,'Detalle diario'!$C$5:$C$550,C15)=0,"NO APLICA: no hay reporte de mermas de esa estación/producto en esa fecha",IF(E15<>"",IF(COUNTIFS('Detalle pipas'!$C$5:$C$281,E15,'Detalle pipas'!$A$5:$A$281,A15,'Detalle pipas'!$B$5:$B$281,B15,'Detalle pipas'!$N$5:$N$281,"NO REGISTRADA*")>0,"APLICADO: registra la factura "&E15,IF(COUNTIFS('Detalle pipas'!$C$5:$C$281,E15,'Detalle pipas'!$A$5:$A$281,A15,'Detalle pipas'!$B$5:$B$281,B15)>0,"OJO: la factura "&E15&" ya estaba registrada; se estaría sumando doble","SIN PIPA: la factura "&E15&" no existe en PIPAS DEL MES para esa estación/producto")),IF(COUNTIFS('Detalle pipas'!$A$5:$A$281,A15,'Detalle pipas'!$B$5:$B$281,B15,'Detalle pipas'!$G$5:$G$281,">="&(D15-Parámetros!$C$8),'Detalle pipas'!$G$5:$G$281,"<="&(D15+Parámetros!$C$8),'Detalle pipas'!$N$5:$N$281,"NO REGISTRADA*")>0,"APLICADO: registra la pipa de "&TEXT(D15,"#,##0")&" L","SIN PIPA: no hay pipa pendiente con esos litros (revisa litros o pon la factura)")))))
G16: =IF(AND(A16="",D16=""),"",IF(OR(A16="",B16="",C16="",D16=""),"FALTAN DATOS: Estación, Producto, Fecha y Litros son obligatorios",IF(COUNTIFS('Detalle diario'!$A$5:$A$550,A16,'Detalle diario'!$B$5:$B$550,B16,'Detalle diario'!$C$5:$C$550,C16)=0,"NO APLICA: no hay reporte de mermas de esa estación/producto en esa fecha",IF(E16<>"",IF(COUNTIFS('Detalle pipas'!$C$5:$C$281,E16,'Detalle pipas'!$A$5:$A$281,A16,'Detalle pipas'!$B$5:$B$281,B16,'Detalle pipas'!$N$5:$N$281,"NO REGISTRADA*")>0,"APLICADO: registra la factura "&E16,IF(COUNTIFS('Detalle pipas'!$C$5:$C$281,E16,'Detalle pipas'!$A$5:$A$281,A16,'Detalle pipas'!$B$5:$B$281,B16)>0,"OJO: la factura "&E16&" ya estaba registrada; se estaría sumando doble","SIN PIPA: la factura "&E16&" no existe en PIPAS DEL MES para esa estación/producto")),IF(COUNTIFS('Detalle pipas'!$A$5:$A$281,A16,'Detalle pipas'!$B$5:$B$281,B16,'Detalle pipas'!$G$5:$G$281,">="&(D16-Parámetros!$C$8),'Detalle pipas'!$G$5:$G$281,"<="&(D16+Parámetros!$C$8),'Detalle pipas'!$N$5:$N$281,"NO REGISTRADA*")>0,"APLICADO: registra la pipa de "&TEXT(D16,"#,##0")&" L","SIN PIPA: no hay pipa pendiente con esos litros (revisa litros o pon la factura)")))))
... G104: =IF(AND(A104="",D104=""),"",IF(OR(A104="",B104="",C104="",D104=""),"FALTAN DATOS: Estación, Producto, Fecha y Litros son obligatorios",IF(COUNTIFS('Detalle diario'!$A$5:$A$550,A104,'Detalle diario'!$B$5:$B$550,B104,'Detalle diario'!$C$5:$C$550,C104)=0,"NO APLICA: no hay reporte de mermas de esa estación/producto en esa fecha",IF(E104<>"",IF(COUNTIFS('Detalle pipas'!$C$5:$C$281,E104,'Detalle pipas'!$A$5:$A$281,A104,'Detalle pipas'!$B$5:$B$281,B104,'Detalle pipas'!$N$5:$N$281,"NO REGISTRADA*")>0,"APLICADO: registra la factura "&E104,IF(COUNTIFS('Detalle pipas'!$C$5:$C$281,E104,'Detalle pipas'!$A$5:$A$281,A104,'Detalle pipas'!$B$5:$B$281,B104)>0,"OJO: la factura "&E104&" ya estaba registrada; se estaría sumando doble","SIN PIPA: la factura "&E104&" no existe en PIPAS DEL MES para esa estación/producto")),IF(COUNTIFS('Detalle pipas'!$A$5:$A$281,A104,'Detalle pipas'!$B$5:$B$281,B104,'Detalle pipas'!$G$5:$G$281,">="&(D104-Parámetros!$C$8),'Detalle pipas'!$G$5:$G$281,"<="&(D104+Parámetros!$C$8),'Detalle pipas'!$N$5:$N$281,"NO REGISTRADA*")>0,"APLICADO: registra la pipa de "&TEXT(D104,"#,##0")&" L","SIN PIPA: no hay pipa pendiente con esos litros (revisa litros o pon la factura)")))))
A106: Fecha registro = día del reporte de mermas en que se suma la compra. Con Factura, se liga a esa pipa; sin Factura, se busca una pipa NO REGISTRADA de la misma estación/producto con esos litros (± tolerancia de Parámetros).

Sheet Notas
A1: Notas, metodología y avisos
A2: Periodo: Agosto 2026 · Generado: 22/09/2026 17:01 · Límite SAT: merma ≤ 0.5% de la venta
A4: Metodología
B5: • Merma diaria = Sdo. Real − Sdo. Final, con Sdo. Final = Sdo. Inicial + Compras − Ventas + Ajustes (igual que el reporte del sistema).
B6: • Merma mensual = suma de las mermas diarias = Sdo. Real del último día − (Sdo. Inicial del 1er día + Compras − Ventas + Ajustes). Merma % mensual = Merma mensual / Ventas del mes.
B7: • El % mensual es el indicador confiable: las mermas diarias se distorsionan cuando una pipa se registra un día distinto a su descarga (se ve como +30,000 L un día y −30,000 L al siguiente).
B8: • Conciliación: primero se compara el total de compras del reporte de mermas contra el total de PIPAS DEL MES por estación y producto; después se busca cada pipa en las compras diarias, primero el mismo día y luego hasta ±N días (Parámetros). Una compra puede corresponder a la suma de 2+ pipas del mismo día.
B9: • Desfase = Fecha de registro en mermas − Fecha BOL. Positivo = se registró después de la fecha de la factura.
B10: • Costo promedio = promedio ponderado del CTO UNIT de las pipas del mes; Merma ($) = Merma (L) × costo promedio.
B11: • Registros manuales: lo que captures en la hoja 'Registros manuales' se suma a Compras (columna Compras manuales de Detalle diario) en la fecha indicada, y la pipa correspondiente pasa de NO REGISTRADA a REGISTRO MANUAL. Mermas, semáforos, conciliación y resumen se recalculan solos. La hoja 'Compras sin pipa' es la lista original del sistema; los registros manuales sin pipa se ven en la columna Resultado de 'Registros manuales'.
A12: Equivalencias de nombres (PIPAS → estación oficial)
B13: • TREHER T → TREHER
B14: • ATEPO → ATP
B15: • AVE. FENIX → AVE FENIX
B16: • AVEFENIX → AVE FENIX
A17: Archivos procesados
B18: • Pipas: PIPAS DEL MES.xlsx
B19: • Mermas: AURORA - Diesel.CSV
B20: • Mermas: AURORA - Premium 91 octanos.CSV
B21: • Mermas: AURORA- Regular 87 octanos.CSV
B22: • Mermas: HUEHUETOCA- Premium 91 octanos.CSV
B23: • Mermas: HUEHUETOCA- Regular 87 octanos.CSV
B24: • Mermas: HUEHUETOCA-Diesel.CSV
B25: • Mermas: IXTAZACUALA- Diesel.CSV
B26: • Mermas: IXTAZACUALA- Premium 91 octanos.CSV
B27: • Mermas: IXTAZACUALA- Regular 87 octanos.CSV
B28: • Mermas: QL - Diesel.CSV
B29: • Mermas: QL - Regular 87 octanos.CSV
... B36: • Mermas: TREHER- Diesel.CSV
A37: Avisos de calidad de datos
B38: • IXTAZACUALA Diesel: el reporte inicia el 03/08 (no trae los primeros días del mes). Las pipas anteriores a esa fecha se marcan FUERA DEL PERIODO.
B39: • IXTAZACUALA Diesel: el 03/08 el Sdo. Inicial viene en 0 y el inventario de arranque se capturó como Ajuste (38,703 L).
B40: • IXTAZACUALA Premium: el reporte inicia el 03/08 (no trae los primeros días del mes). Las pipas anteriores a esa fecha se marcan FUERA DEL PERIODO.
B41: • IXTAZACUALA Premium: el 03/08 el Sdo. Inicial viene en 0 y el inventario de arranque se capturó como Ajuste (27,932 L).
B42: • IXTAZACUALA Regular: el reporte inicia el 03/08 (no trae los primeros días del mes). Las pipas anteriores a esa fecha se marcan FUERA DEL PERIODO.
B43: • IXTAZACUALA Regular: el 03/08 el Sdo. Inicial viene en 0 y el inventario de arranque se capturó como Ajuste (51,578 L).
B44: • TREHER Premium: el reporte inicia el 03/08 (no trae los primeros días del mes). Las pipas anteriores a esa fecha se marcan FUERA DEL PERIODO.
B45: • TREHER Premium: el 03/08 el Sdo. Inicial venía en 0, lo que generaba una 'merma' ficticia de +18,774 L. Se tomó como saldo inicial el inventario real de ese día (Sdo. Real + Ventas − Compras). Corrige el arranque en el sistema.
B46: • TREHER Regular: el reporte inicia el 03/08 (no trae los primeros días del mes). Las pipas anteriores a esa fecha se marcan FUERA DEL PERIODO.
B47: • TREHER Regular: el 03/08 el Sdo. Inicial venía en 0, lo que generaba una 'merma' ficticia de +103,989 L. Se tomó como saldo inicial el inventario real de ese día (Sdo. Real + Ventas − Compras). Corrige el arranque en el sistema.
B48: • TREHER Diesel: el reporte inicia el 03/08 (no trae los primeros días del mes). Las pipas anteriores a esa fecha se marcan FUERA DEL PERIODO.
B49: • TREHER Diesel: el 03/08 el Sdo. Inicial venía en 0, lo que generaba una 'merma' ficticia de +33,527 L. Se tomó como saldo inicial el inventario real de ese día (Sdo. Real + Ventas − Compras). Corrige el arranque en el sistema.

Sheet Parámetros
A1: Parámetros
A2: Cambia los valores en amarillo y todo el libro se recalcula
B4: Parámetro | C4: Valor | D4: Descripción
B5: Límite SAT merma / venta | C5: 0.005 | D5: Arriba de este % el foco es ROJO (FUERA)
B6: Umbral de alerta | C6: 0.004 | D6: Entre este % y el límite el foco es AMARILLO (ALERTA)
B7: Ventana de desfase (días) | C7: 2 | D7: Días ± entre fecha BOL y registro en mermas (se usó al generar)
B8: Tolerancia por pipa (L) | C8: 5 | D8: Diferencia máxima en litros para considerar que una pipa cuadra
B9: Umbral salto diario (L) | C9: 5000 | D9: |Merma diaria| mayor a esto = posible pipa registrada en otro día
